Workbook
Name SegmentaçãodeDados_Área: #N/A
Name SegmentaçãodeDados_Peso: #N/A
Name _ftn1: 'Formulário de Conformidade'!#REF!
Name _ftnref1: 'Formulário de Conformidade'!#REF!

Sheet Formulário de Perfil
B3: QTDE | C3: DADOS BÁSICOS | D3: Tooltip | E3: TIPO | F3: Opções
B4: 1 | C4: DB1. Nome da pessoa jurídica - Razão Social: | D4: Informar a denominação pela qual a pessoa jurídica está registrada no Cadastro Nacional da Pessoa Jurídica. | E4: Texto | F4: JDS ENGENHARIA E CONSULTORIA LTDA
B5: 2 | C5: DB2. E-mail institucional da área de integridade: | D5: Informar o e-mail da área ou pessoa responsável pelo programa de integridade. Indicar e-mail institucional, evitando-se conta de uso pessoal. Este e-mail poderá ser utilizado pela CGU para dúvidas, informes, pedidos de esclarecimentos etc. | E5: Texto (máscara: e-mail) | F5: E-mail: jdseng@jdseng.com.br
B6: 3 | C6: DB3. CNPJ: | D6: Informar o CNPJ da pessoa jurídica. | E6: Texto (máscara: CNPJ) | F6: 40.376.139/0001-59
B7: 4 | C7: DB4. Representante do programa de integridade: | D7: Informar o nome do representante da pessoa jurídica para ser comunicado em relação à avaliação do programa de integridade. | E7: Texto | F7: Yuri Renan Procopio dos Santos Pinto Zolet
B8: 5 | C8: DB5. Cargo do representante: | D8: Informar o cargo do representante da pessoa jurídica. | E8: Texto | F8: Oficial de Compliance
B9: 6 | C9: DB6. Telefone do representante: | D9: Informar o telefone do representante da pessoa jurídica. | E9: Texto (máscara: telefone) | F9: (21) 8899-6848
C10: ESTRUTURA E ATIVIDADE ECONÔMICA
B11: 1 | C11: EA1. Qual a atividade econômica principal? | D11: Selecionar a opção que se refere a sua atividade econômica principal. A pessoa jurídica deverá observar os dois primeiros dígitos do CNAE e correlacioná-los com alguma das atividades descritas na lista. Exemplo: CNAE: 64.62-0-00 Atividade a ser selecionada na lista: (64 a 66) | E11: Lista Seleção Única | F11: (41 a 43) Construção CÓDIGO DE ATIVIDADES ECONÔMICAS (CAE): 2.60.39.8 - SUPERVISÃO DE OBRAS E DE SERVIÇOS DE ENGENHARIA 2.26.29.7 - PROJETOS E ESTUDOS DE ENGENHARIA 2.61.28.9 - ENGENHARIA, SERVIÇOS DE 2.27.12.9 - CONSULTORIA TÉCNICA 2.26.51.3 - ANÁLISE E PROGRAMAÇÃO DE SISTEMAS 2.27.15.3 - ASSESSORIA TÉCNICA
B12: 2 | C12: EA2. Qual o porte da pessoa jurídica?1 | D12: Critério para a definição do porte conf. faturamento anual: - Microempresa: até R$ 360 mil - Empresa de Pequeno Porte: de R$ 360 mil até R$ 4,8 milhões - Média empresa: de R$ 4,8 milhões até R$ 300 milhões - Grande empresa: acima de R$ 300 milhões. | E12: Lista Seleção Única | F12: Micro e Pequeno porte (de acordo com o Estatuto da Micro e Pequena Empresa) Médio Grande
B13: 3 | C13: EA3. Qual o faturamento anual? | D13: Selecionar a opção que se refere ao faturamento estimado, obtido pela pessoa jurídica a cada ano. | E13: Lista Seleção Única | F13: <= R$ 360 mil > R$ 360 mil e <= R$ 4,8 milhões > R$ 4,8 milhões e <= R$ 16 milhões > R$ 16 milhões e <= R$ 90 milhões > R$ 90 milhões e <= R$ 300 milhões > R$ 300 milhões e <= R$ 1 bilhão > R$ 1 bilhão
B14: 4 | C14: EA4. Descrever a estrutura organizacional da pessoa jurídica (Ex.: presidência, conselhos, comitês, diretorias etc.): | D14: Informar a estrutura organizacional, apresentando breve resumo das instâncias que a compõem, suas atribuições, membros e as relações de hierarquia/subordinação existentes. | E14: Texto Longo | F14: JDS Engenharia e Consultoria Ltda., ao longo de mais de três décadas, é uma empresa que presta serviços técnicos especializados, notadamente nas áreas de elaboração de estudos de viabilidade, desenvolvimento de projetos, supervisão e gerenciamento de obras, com atuação destacada em empreendimentos de infraestrutura. E também atua na área de consultoria técnica especializada. Em termos de estrutura a empresa possui: uma Diretoria Executiva; as Diretorias Técnicas e Administrativa; e Áreas Técnicas Operacionais.
B15: 5 | C15: EA5. Integra algum grupo econômico? 2 | D15: Selecionar “Sim” ou “Não”, conforme o caso. | E15: Sim/Não | F15: Não
B16: 6 | C16: EA5.1. Informar o nome do grupo econômico: | D16: Informar o nome do grupo econômico ao qual a pessoa jurídica pertence. | E16: Texto Longo | F16: Não se aplica.
B17: 7 | C17: EA5.2. Informar se o programa de integridade se aplica a mais de uma pessoa jurídica do grupo e para quais pessoas jurídicas se aplica: | D17: Informar para quais outras pessoas jurídicas do grupo econômico o programa de integridade é aplicado. | E17: Texto Longo | F17: Não se aplica.
B18: 8 | C18: EA5.3. Informar se é controladora, controlada, coligada, subsidiária, etc., indicando as principais pessoas jurídicas que integram o grupo e os países em que atuam: | D18: Informar a condição da pessoa jurídica no seu grupo econômico, bem como citar as principais pessoa jurídicas que integram esse grupo e os países em que elas exercem atividade. | E18: Texto Longo | F18: Não se aplica.
B19: 9 | C19: EA6. Realizou, nos últimos 24 meses, operações societárias envolvendo outras pessoas jurídicas (Ex.: fusão, incorporação etc.)?3 4 | D19: Selecionar “Sim” ou “Não”, conforme o caso. As operações societárias incluem: fusões, incorporações, aquisições, cisões etc. | E19: Sim/Não | F19: Não.
B20: 10 | C20: EA6.1. Descrever as operações societárias realizadas: | D20: Ex.: data, tipo de operação, pessoas jurídicas envolvidas, ações relacionadas à operação, alterações na estrutura societária e de mercado das pessoas jurídicas, aprovação pelos órgãos de fiscalização e de defesa econômica etc. | E20: Texto Longo | F20: Não se aplica.
B21: 11 | C21: EA7. Qual o percentual de colaboradores que possuem acesso à internet, fornecido pela pessoa jurídica, no local de trabalho? | D21: Selecionar a opção que se refere ao percentual de colaboradores com acesso à internet no local de trabalho. | E21: Lista Seleção Única | F21: 0 % - Nenhum possui acesso à internet Entre 1% e 20% Entre 21% e 40% Entre 41% e 60% Entre 61% e 80% Entre 81% e 100%
B22: 12 | C22: EA8. Quantos colaboradores possui? | D22: Informar a quantidade de colaboradores que a pessoa jurídica possui, incluindo funcionários, terceirizados, estagiários e aprendizes. | E22: Número | F22: Conta atualmente com 38 (trinta e oito) emprega-dos sob o regime da CLT e 24 (vinte e quatro) colaboradores contratados na modalidade de Pessoa Jurídica.
C23: INTERAÇÃO COM PODER PÚBLICO
B24: 1 | C24: IP1. A pessoa jurídica se submete à regulação de agência/órgão governamental?5 | D24: Selecionar “Sim” ou “Não”, conforme o caso. | E24: Sim/Não | F24: Não.
B25: 2 | C25: IP1.1. Informar quais são as agências/órgãos reguladores a que a pessoa jurídica está submetida: | D25: Informar as agências/órgãos governamentais responsáveis por regular as atividades exercidas pela pessoa jurídica. | E25: Texto Longo | F25: Não se aplica.
B26: 3 | C26: IP2. Em relação à obtenção de licenças, autorizações e permissões governamentais, como poderia ser classificada a situação da pessoa jurídica? | D26: Selecionar a opção que se refere à situação da pessoa jurídica com relação às licenças, autorizações e permissões governamentais. | E26: Lista Seleção Única | F26: a) Não necessita de licenças, autorizações ou permissões no exercício de suas atividades (exceto licenças básicas para funcionamento da pessoa jurídica, como alvarás de funcionamento e de vistoria do corpo de bombeiros).
B27: 4 | C27: IP2.1. Descrever as licenças, autorizações e permissões das quais a pessoa jurídica necessite: | D27: Informar as licenças, autorizações e permissões das quais a pessoa jurídica necessite no exercício de suas atividades, incluindo licenças básicas para funcionamento. | E27: Texto Longo | F27: Não se aplica.
B28: 5 | C28: IP3. Em relação à participação em licitações públicas, como poderia ser classificada a situação da pessoa jurídica? | D28: Selecionar a opção que se refere à situação da pessoa jurídica com relação a sua participação em licitações públicas. | E28: Lista Seleção Única | F28: Participa com frequência de licitações.
B29: 6 | C29: IP4. Em relação à celebração de contratos com a Administração Pública, como poderia ser classificada a situação da pessoa jurídica? | D29: Selecionar a opção que se refere à situação da pessoa jurídica com relação à celebração de contratos com a Administração Pública. | E29: Lista Seleção Única | F29: Celebra com frequência contratos com a Administração Pública.
B30: 7 | C30: IP5. Qual das faixas mais se aproxima do percentual médio do faturamento proveniente de contratos firmados com o poder público? | D30: Selecionar a opção que se refere ao % que os contratos representam do faturamento total da pessoa jurídica. | E30: Lista Seleção Única | F30: 1% a 20% 21% a 40% 41% a 60% 61% a 80% 81% a 100%
B31: 8 | C31: IP6. Utiliza intermediários no contato com a Administração Pública para execução de contratos administrativos, obtenção de autorizações, licenças e permissões, protocolo de documentos, desembaraço aduaneiro etc.?6 | D31: Selecionar “Sim” ou “Não”, conforme o caso. Intermediários incluem: consultores, advogados, assessores, despachantes, procuradores etc. | E31: Sim/Não
B32: 9 | C32: IP6.1. Descrever como ocorreu a utilização de intermediários no contato com a Administração Pública por parte da pessoa jurídica: | D32: Ex.: data, terceiro contratado, objeto, órgão ou entidade pública relacionada, atividades desempenhadas etc. | E32: Texto Longo
B33: 10 | C33: IP7. A pessoa jurídica subcontratou atividades relacionadas à execução de contratos administrativos?7 | D33: Selecionar “Sim” ou “Não”, conforme o caso. Entende-se por “subcontratação” a situação em que a pessoa jurídica contrata um terceiro para executar determinada parcela do contrato administrativo. | E33: Sim/Não
B34: 11 | C34: IP7.1. Explicar como ocorreram as subcontratações de atividades relacionadas à execução de contratos administrativos por parte da pessoa jurídica: | D34: Ex.: data, contrato administrativo, terceiro e objeto subcontratado, aprovação pelo órgão ou entidade pública etc. | E34: Texto Longo
C35: DOAÇÕES E PATROCÍNIOS
B36: 1 | C36: DP1. A pessoa jurídica realizou patrocínios esportivos ou culturais, nos últimos 24 meses? | D36: Selecionar “Sim” ou “Não”, conforme o caso. | E36: Sim/Não | F36: Não informado.
B37: 2 | C37: DP2. A pessoa jurídica efetuou doações, nos últimos 24 meses? | D37: Selecionar “Sim” ou “Não”, conforme o caso. | E37: Sim/Não | F37: Não informado.
C38: PRÁTICAS SOCIOAMBIENTAIS
B39: 1 | C39: PS1. A atividade da pessoa jurídica envolve potencial de dano ao meio ambiente?8 | D39: Selecionar “Sim” ou “Não”, conforme o caso. | E39: Sim/Não | F39: Sim
B40: 2 | C40: PS1.1 Apresentar justificativas por entender que não possui atividades que podem causar impactos ambientais: | D40: Explicar os motivos que levam a pessoa jurídica a concluir que suas atividades não geram impactos ambientais, tais como: localização, natureza das operações, uso mínimo de recursos naturais etc., e outras avaliações que fundamentem esse entendimento. | E40: Texto Longo
C41: PROGRAMA DE INTEGRIDADE
B42: 1 | C42: PI1. Quando entende que seu programa de integridade foi formalmente instituído? | D42: Selecionar a opção que se refere ao tempo decorrido desde o ano de instituição do programa de integridade, conforme a existência dos seguintes elementos básicos: Código de Ética/Conduta; Canal de Denúncias; e Área Específica ou Pessoa Responsável pelo programa. | E42: Lista Seleção Única | F42: Em até 1 ano Entre 1 e 3 anos Entre 3 e 5 anos Acima de 5 anos
B43: 2 | C43: PI2. Descrever a estrutura da área de integridade, a sua posição hierárquica e o seu reporte com a alta direção e, no caso de pessoa jurídica multinacional com programa global de integridade, com a área de integridade da matriz: | D43: Informar aspectos da estrutura da área de integridade da pessoa jurídica, conforme solicitado no item. | E43: Texto Longo | F43: Não há essa informação nos documentos.
B44: 3 | C44: PI3. A área de integridade conta com quantos colaboradores que se dedicam exclusivamente ao programa de integridade da pessoa jurídica? | D44: Informar a quantidade de colaboradores com dedicação exclusiva ao programa de integridade, isto é, que não desempenham funções em outras áreas. | E44: Número | F44: Não há essa informação nos documentos.
B45: 4 | C45: PI4. A pessoa jurídica conta com quantos colaboradores que se dedicam parcialmente ao programa de integridade? | D45: Informar a quantidade de colaboradores com dedicação parcial ao programa de integridade, isto é, que desempenham funções em outras áreas (ex.: embaixadores de integridade lotados em outras unidades) | E45: Número | F45: Não há essa informação nos documentos.
B46: 5 | C46: PI5. Recebeu alguma denúncia relacionada com atos de fraude e corrupção, atos de desrespeito à legislação ambiental, preconceito, discriminação e assédio de qualquer natureza nos últimos 24 meses?10 | D46: Selecionar “Sim” ou “Não”, conforme o caso. | E46: Sim/Não | F46: Não há essa informação nos documentos.
B47: 6 | C47: PI6. Está sendo investigada ou é parte em processo administrativo ou judicial, ou já foi condenada, nos últimos 3 (três) anos, pela prática de atos de corrupção, improbidade administrativa e/ou fraudes em licitação?11 | D47: Selecionar “Sim” ou “Não”, conforme o caso. | E47: Sim/Não | F47: Sim.
B48: 7 | C48: PI6.1. Apresentar breve esclarecimento sobre o caso indicado no item anterior, e as medidas de integridade adotadas em reação ao ilícito: | D48: Informar sobre o(s) caso(s) ocorrido(s) na pessoa jurídica no item anterior, bem como as medidas de integridades adotadas. | E48: Texto Longo | F48: A JDS Engenharia e Consultoria Ltda. foi declarada inidônea para licitar ou contratar com a Administração Pública em 28 de março de 2024, em razão de omissão deliberada na supervisão técnica de obras rodoviárias (BR-429/RO, Operação Anjos do Asfalto), com dano estimado ao erário de R$ 30.884.297,74. O prazo de inidoneidade de 2 anos encerrou-se em 28 de março de 2026, e o pedido de reabilitação foi protocolado em 9 de abril de 2026. Com o objetivo de reabilitar-se perante a Administração Pública, a empresa apresentou seu Programa de Integridade contendo o código de ética, código de Investigações internas, POLÍTICA DE USO ACEITÁVEL DE RECURSOS DE TI E SEGURANÇA DA INFORMAÇÃO, POLÍTICA DE DESPESAS E BENEFÍCIOS, RELATÓRIO DE DUE DILIGENCE e realização de treinamentos internos.
B49: 8 | C49: PI7. Algum membro da alta direção está sendo investigado ou é parte em processo administrativo ou judicial, ou já foi condenado, nos últimos 3 (três) anos, pela prática de atos de corrupção, improbidade administrativa e/ou fraudes em licitação?12 | D49: Selecionar “Sim” ou “Não”, conforme o caso. | E49: Sim/Não | F49: Sim.
B50: 9 | C50: PI7.1. Apresentar quais foram as medidas adotadas a partir da ciência da prática do ato lesivo por membro da alta direção, indicado no item anterior: | D50: Informar sobre as medidas adotadas em resposta ao ato lesivo praticado por membro da alta direção, indicado no item anterior. | E50: Texto Longo | F50: Não há essa informação nos documentos.

Sheet Formulário de Conformidade
B2: FORMULÁRIO DE CONFORMIDADE
C3: Processo: 00190.104729/2021-05
C4: Pessoa Jurídica: 40.376.139/0001-59 - JDS
C5: Avaliado por/data:
C6: Revisado por/data:
B8: Área | C8: Tipo | D8: Item | E8: Tipo de Resposta | F8: Nível | G8: Valor | H8: Avaliação | I8: Pont. Resdist. | J8: Pontuação | K8: Evidência | L8: Análise | M8: Vinculação Condicional | N8: Distribuição "Não se aplica"
B9: I | C9: Área | D9: Área I - Comprometimento da Alta Direção da Pessoa jurídica
B10: I | C10: Grupo | D10: 1. Adoção de critérios de integridade para seleção e remuneração de candidatos a cargos da alta direção
B11: I | C11: Questão | D11: 1.1 A pessoa jurídica possui critérios de integridade formalizados para seleção dos candidatos aos cargos da alta direção? Se sim, anexar documentos que comprovem a existência dos critérios de integridade para seleção e informar os cargos a que são aplicados, a forma como os critérios são considerados e os responsáveis por sua avaliação. | E11: Sim, Não | F11: QN2 | G11: 15 | H11: Não | J11: =IF(H11="Sim",G11, IF(H11="Parcialmente",G11/2, IF(OR(H11="Não",H11="Não se aplica"),0,""))) +IF(OR(H11="Sim",H11="Parcialmente"),Tabela1[[#This Row],[Pont. Resdist.]],0) | K11: Ausência de documento | L11: NÃO ATENDIDA. • Análise inicial (resposta anterior: Não): Não foram localizados critérios formalizados de integridade para seleção de candidatos à alta direção. A documentação não apresenta qualquer política de recursos humanos nesse sentido. • Complementação (nova documentação): Não foi apresentada política de RH com critérios de integridade formalizados para seleção da alta direção. Lacuna não sanada.
B12: I | C12: Questão | D12: 1.2 A pessoa jurídica aplicou critérios de integridade para seleção dos ocupantes de cargos da alta direção contratados nos últimos 24 meses? Se sim, anexar documentos que comprovem a aplicação dos critérios de integridade para seleção. | E12: Sim, Não, Não se aplica | F12: QN5 | G12: 18 | H12: Não se Aplica | J12: =IF(H12="Sim",G12, IF(H12="Parcialmente",G12/2, IF(OR(H12="Não",H12="Não se aplica"),0,""))) +IF(OR(H12="Sim",H12="Parcialmente"),Tabela1[[#This Row],[Pont. Resdist.]],0) | K12: Doc 01 - Estatuto Social | L12: NÃO SE APLICA (mantida da 1ª análise). Empresa sem conselho de administração ou fiscal formalmente constituído. | M12: Grupo: ESTRUTURA E ATIVIDADE ECONÔMICA Questão: Qual o porte da pessoa jurídica? Alternativa: Micro e Pequeno porte (de acordo com o Estatuto da Micro e Pequena pessoa jurídica) | N12: Distribuir 2,25 pontos para cada uma das questões (8): 1.1 2.1 2.3 3.1 3.2.1 3.2.2 3.2.3 3.3
B13: I | C13: Questão | D13: 1.3 A pessoa jurídica possui política de remuneração variável para os membros da alta direção condicionada ao atingimento de metas de desempenho relacionadas aos indicadores de aplicação ao programa de integridade? Se sim, anexar a política de remuneração que comprova a existência dessa regra e descrever como ela é aplicada. | E13: Sim, Não, Não se aplica | F13: QN2 | G13: 15 | H13: Não se Aplica | J13: =IF(H13="Sim",G13, IF(H13="Parcialmente",G13/2, IF(OR(H13="Não",H13="Não se aplica"),0,""))) +IF(OR(H13="Sim",H13="Parcialmente"),Tabela1[[#This Row],[Pont. Resdist.]],0) | K13: Ausência de documento | L13: NÃO SE APLICA (mantida da 1ª análise). Não foram apresentadas evidências de política de remuneração variável vinculada a metas de integridade. A estrutura da empresa de médio porte não contempla este mecanismo. | M13: Grupo: ESTRUTURA E ATIVIDADE ECONÔMICA Questão: Qual o porte da pessoa jurídica? Alternativa: Micro e Pequeno porte (de acordo com o Estatuto da Micro e Pequena pessoa jurídica) | N13: Distribuir pontos para cada uma das questões (8): 1.1 = 1,87 2.1 = 1,88 2.3 = 1,88 3.1 = 1,88 3.2.1 = 1,87 3.2.2 = 1,87 3.2.3 = 1,87 3.3 = 1,88
B14: I | C14: Grupo | D14: 2. Envolvimento da alta direção na implementação e supervisão do programa de integridade
B15: I | C15: Questão | D15: 2.1 A aprovação das principais políticas relacionadas ao programa de integridade é feita pelas mais elevadas instâncias decisórias da pessoa jurídica? Se sim, anexar documentos que comprovem a aprovação das principais políticas relacionadas ao programa de integridade pela alta direção. | E15: Sim, Não | F15: QN1 | G15: 20 | H15: Sim | J15: =IF(H15="Sim",G15, IF(H15="Parcialmente",G15/2, IF(OR(H15="Não",H15="Não se aplica"),0,""))) +IF(OR(H15="Sim",H15="Parcialmente"),Tabela1[[#This Row],[Pont. Resdist.]],0) | K15: Cód_Etica.pdf (Doc 12.1, ass. digital 11/08/2025); Políticas_Internas.pdf (Doc 12.5, aprovadas 13/03/2026) | L15: QUESTÃO CRÍTICA - As políticas foram aprovadas e assinadas, mas não há registros documentados de reunião deliberativa formal da alta direção aprovando o conjunto das políticas de integridade. O Código de Ética (V.01.2025) foi assinado digitalmente em 11/08/2025 e as Políticas Internas foram aprovadas em 13/03/2026. Como não há o quesito do julgamento parcial, opta-se pelo Sim.
B16: I | C16: Questão | D16: 2.2 A pessoa jurídica possui em sua estrutura de governança órgão colegiado (como comitê ou conselho de ética) para deliberar sobre temas de ética e integridade, que contam com a participação de membros da alta direção? Se sim, anexar documentos que comprovem a existência do órgão colegiado e a participação dos membros da alta direção em sua composição. | E16: Sim, Não, Não se aplica | F16: QN2 | G16: 15 | H16: Não se Aplica | J16: =IF(H16="Sim",G16, IF(H16="Parcialmente",G16/2, IF(OR(H16="Não",H16="Não se aplica"),0,""))) +IF(OR(H16="Sim",H16="Parcialmente"),Tabela1[[#This Row],[Pont. Resdist.]],0) | K16: Doc 01 - Estatuto Social | L16: Empresa sem órgão colegiado (conselho/comitê de integridade). | M16: Grupo: ESTRUTURA E ATIVIDADE ECONÔMICA Questão: Qual o porte da pessoa jurídica? Alternativa: Micro e Pequeno porte (de acordo com o Estatuto da Micro e Pequena pessoa jurídica) | N16: Distribuir pontos para cada uma das questões (8): 1.1 = 1,87 2.1 = 1,88 2.3 = 1,88 3.1 = 1,88 3.2.1 = 1,87 3.2.2 = 1,87 3.2.3 = 1,87 3.3 = 1,88
B17: I | C17: Questão | D17: 2.3 A alta direção da pessoa jurídica supervisiona, diretamente ou por intermédio de órgão colegiado do qual ela participe, a implantação e a aplicação do programa de integridade, por meio do recebimento e avaliação de relatórios periódicos de acompanhamento das atividades relacionadas ao programa de integridade? | E17: Sim, Não, Parcialmente | F17: QN5 | G17: 18 | H17: Sim | J17: =IF(H17="Sim",G17, IF(H17="Parcialmente",G17/2, IF(OR(H17="Não",H17="Não se aplica"),0,""))) +IF(OR(H17="Sim",H17="Parcialmente"),Tabela1[[#This Row],[Pont. Resdist.]],0) | K17: 1ª análise: Rel_Conformidade.pdf (Doc 12, 31/03/2026) Documentação complementar: Procedimento de Monitoramento Contínuo do PI V.01.2026; Termo de Designação do Oficial de Compliance, 07/07/2026; Matriz de Riscos de Integridade V.01/V.02.2026 (Termo de Aprovação da Diretoria, 24/03 e 30/07/2026) | L17: ATENDIDA — superada com a documentação complementar. • Análise inicial (resposta anterior: Parcialmente): Existe Relatório de Conformidade emitido em 31/03/2026 (Rel_Conformidade.pdf), mas não há evidências de supervisão periódica formalizada pela alta direção com reuniões ou relatórios recorrentes de acompanhamento do PI. • Complementação (nova documentação): O Procedimento de Monitoramento Contínuo prevê relatórios trimestrais/anuais à Diretoria; o Termo de Designação garante participação do Compliance em reuniões da Diretoria; e a Matriz de Riscos foi aprovada pela Diretoria — evidenciando supervisão periódica formalizada pela alta direção.
B18: I | C18: Grupo | D18: 3. Apoio visível e inequívoco da alta direção ao programa de integridade, incluindo a destinação de recursos adequados
B19: I | C19: Questão | D19: 3.1 Os membros da alta direção, individualmente, manifestam publicamente apoio ao programa de integridade? Se sim, anexar documentos e/ou indicar, no campo correspondente, link em que seja possível visualizar as manifestações de apoio ao programa de integridade por membros da alta direção. | E19: Sim, Não | F19: QN1 | G19: 20 | H19: Sim | J19: =IF(H19="Sim",G19, IF(H19="Parcialmente",G19/2, IF(OR(H19="Não",H19="Não se aplica"),0,""))) +IF(OR(H19="Sim",H19="Parcialmente"),Tabela1[[#This Row],[Pont. Resdist.]],0) | K19: 1ª análise: Doc 12.2; Doc 12.4 Documentação complementar: E-mails da Diretoria (João Darous) a todos os colaboradores, 02 e 17/07/2026 | L19: ATENDIDA — superada com a documentação complementar. • Análise inicial (resposta anterior: Não): Não foram localizadas manifestações públicas pessoais dos membros da alta direção (João Darous) em apoio ao Programa de Integridade. As comunicações sobre integridade foram emitidas pelo Oficial de Compliance (Yuri Renan), e não diretamente pela direção. • Complementação (nova documentação): Os e-mails de 02 e 17/07/2026, assinados pessoalmente pelo sócio-administrador João Darous e enviados a todos os colaboradores, manifestam apoio pessoal e expresso ao Programa de Integridade, suprindo a lacuna apontada.
B20: I | C20: Agrupadora | D20: 3.2 As manifestações de apoio ao programa de integridade por membros da alta direção:
B21: I | C21: Questão | D21: 3.2.1 são feitas de forma periódica e divulgadas por diferentes meios para alcançar o público interno e externo da pessoa jurídica em toda sua diversidade? Se sim, demonstrar a medida em que as manifestações de apoio ao programa de integridade ocorreram de forma periódica e direcionadas aos diferentes públicos da entidade. | E21: Sim, Não, Parcialmente | F21: QN3 | G21: 5 | H21: Parcialmente | J21: =IF(H21="Sim",G21, IF(H21="Parcialmente",G21/2, IF(OR(H21="Não",H21="Não se aplica"),0,""))) +IF(OR(H21="Sim",H21="Parcialmente"),Tabela1[[#This Row],[Pont. Resdist.]],0) | K21: 1ª análise: (sem documento) Documentação complementar: E-mails da Diretoria (João Darous) a todos os colaboradores, 02 e 17/07/2026; Calendário de Comunicações 2026 | L21: PARCIALMENTE ATENDIDA. • Análise inicial (resposta anterior: Não): Não foram identificadas comunicações formais periódicas do Diretor-Presidente sobre integridade. • Complementação (nova documentação): O Calendário de Comunicações 2026 e os e-mails da Diretoria evidenciam manifestações por diferentes meios; a periodicidade está prevista, mas parte das ações ainda consta como PREVISTA (execução em curso).
B22: I | C22: Questão | D22: 3.2.2 expressam uma mensagem de incentivo à adoção de uma conduta ética, seguindo os ditames do programa de integridade? Se sim, demonstrar a medida em que as manifestações de apoio ao programa de integridade expressaram o compromisso com os temas. | E22: Sim, Não | F22: QN3 | G22: 5 | H22: Sim | J22: =IF(H22="Sim",G22, IF(H22="Parcialmente",G22/2, IF(OR(H22="Não",H22="Não se aplica"),0,""))) +IF(OR(H22="Sim",H22="Parcialmente"),Tabela1[[#This Row],[Pont. Resdist.]],0) | K22: 1ª análise: (sem documento) Documentação complementar: E-mails da Diretoria (João Darous) a todos os colaboradores, 02 e 17/07/2026 | L22: ATENDIDA — superada com a documentação complementar. • Análise inicial (resposta anterior: Não): Sem manifestações individuais do Diretor-Presidente sobre conduta ética ou mensagens de incentivo. • Complementação (nova documentação): O e-mail da Diretoria expressa mensagem clara de incentivo à conduta ética e ao uso do canal de denúncias.
B23: I | C23: Questão | D23: 3.2.3 expressam o compromisso da alta direção com o combate ao preconceito, à discriminação e ao assédio de qualquer natureza? Se sim, demonstrar a medida em que as manifestações de apoio ao programa de integridade expressaram o compromisso com os temas. | E23: Sim, Não | F23: QN3 | G23: 5 | H23: Sim | J23: =IF(H23="Sim",G23, IF(H23="Parcialmente",G23/2, IF(OR(H23="Não",H23="Não se aplica"),0,""))) +IF(OR(H23="Sim",H23="Parcialmente"),Tabela1[[#This Row],[Pont. Resdist.]],0) | K23: Doc 12.4 - Email sobre assédio e canal de denúncias (26/03/2026) | L23: ATENDIDA (mantida da 1ª análise). Comunicação sobre assédio, discriminação e canal de denúncias enviada a toda a equipe (escritório e campo em grupos separados) em 26/03/2026, com cartilha institucional. Confirmada na reavaliação; a documentação complementar não a contradiz.
B24: I | C24: Questão | D24: 3.3 A pessoa jurídica destina recursos em seu orçamento para a manutenção das atividades relacionadas ao programa de integridade? Se sim, anexar documentos que comprovem a destinação de recursos para o programa de integridade. | E24: Sim, Não | F24: QN5 | G24: 18 | H24: Sim | J24: =IF(H24="Sim",G24, IF(H24="Parcialmente",G24/2, IF(OR(H24="Não",H24="Não se aplica"),0,""))) +IF(OR(H24="Sim",H24="Parcialmente"),Tabela1[[#This Row],[Pont. Resdist.]],0) | K24: Rel_Conformidade.pdf (Doc 12); Investig_Internas.pdf (Doc 12.6); Rel_Due_Diligence.pdf (Doc 12.7) | L24: ATENDIDA (mantida da 1ª análise). A empresa possui Oficial de Compliance (Yuri Renan) contratado e utiliza escritório de advocacia externo (Asseff Advogados) para conduções do Programa de Integridade, o que implica alocação de recursos financeiros. Contudo, não foi apresentado orçamento formal destinado ao PI. Como não há o quesito do julgamento parcial, opta-se pelo Sim. Confirmada na reavaliação; a documentação complementar não a contradiz.
B25: II | C25: Área | D25: Área II - Instância Interna Responsável pela Aplicação do Programa de Integridade
B26: II | C26: Grupo | D26: 4. Existência e estrutura da instância interna responsável pela aplicação do programa de integridade
B27: II | C27: Questão | D27: 4.1 A pessoa jurídica possui área ou pessoa responsável pela aplicação do programa de integridade? Se sim, anexar documentos que comprovem a existência da área específica ou pessoa responsável, informando a data em que a área foi instituída ou em que a pessoa responsável foi contratada/designada para a função e o currículo do atual responsável pelo programa de integridade. | E27: Sim, Não | F27: QN1 | G27: 20 | H27: Sim | J27: =IF(H27="Sim",G27, IF(H27="Parcialmente",G27/2, IF(OR(H27="Não",H27="Não se aplica"),0,""))) +IF(OR(H27="Sim",H27="Parcialmente"),Tabela1[[#This Row],[Pont. Resdist.]],0) | K27: Cód_Etica.pdf (Doc 12.1); Rel_Conformidade.pdf (Doc 12); Treinamento_Cód_Ética.pdf (Doc 12.2); Assédio.pdf (Doc 12.4) | L27: ATENDIDA (mantida da 1ª análise). QUESTÃO CRÍTICA ATENDIDA. A empresa possui Oficial de Compliance formalmente designado: Yuri Renan Procopio dos Santos Pinto Zolet (yuri.renan@jdseng.com.br). O profissional é mencionado no Código de Ética, no Relatório de Conformidade e nas comunicações internas, demonstrando atuação efetiva na função. Confirmada na reavaliação; a documentação complementar não a contradiz. Reforçada pela documentação complementar.
B28: II | C28: Questão | D28: 4.2 A instância interna responsável pelo programa de integridade está formalmente constituída, tendo suas atribuições expressamente previstas em documento aprovado pela alta direção da pessoa jurídica? Se sim, anexar documentos que comprovem a constituição formal da área responsável pelo programa de integridade, com suas atribuições e responsabilidades definidas. | E28: Sim, Não, Parcialmente | F28: QN2 | G28: 15 | H28: Sim | J28: =IF(H28="Sim",G28, IF(H28="Parcialmente",G28/2, IF(OR(H28="Não",H28="Não se aplica"),0,""))) +IF(OR(H28="Sim",H28="Parcialmente"),Tabela1[[#This Row],[Pont. Resdist.]],0) | K28: 1ª análise: Cód_Etica.pdf (Doc 12.1) Documentação complementar: Termo de Designação do Oficial de Compliance, 07/07/2026 | L28: ATENDIDA — superada com a documentação complementar. • Análise inicial (resposta anterior: Parcialmente): O Código de Ética menciona o Oficial de Compliance e suas atribuições gerais, mas não foi apresentado documento formal (resolução, portaria ou contrato) que constitua expressamente a instância, defina todas as suas atribuições e responsabilidades e registre a aprovação pela alta direção. • Complementação (nova documentação): O Termo de Designação do Oficial de Compliance (07/07/2026) assegura recursos, orçamento próprio e remuneração compatível, suprindo a parcialidade anterior.
B29: II | C29: Questão | D29: 4.3 A instância interna responsável pelo programa possui estrutura independente, não estando subordinada a outro departamento da pessoa jurídica – jurídico, auditoria, RH etc.? Se sim, anexar organograma que demonstre a estrutura atual da instância interna e suas linhas de reporte ou política/procedimento que formalize tal estrutura e linhas de reporte. | E29: Sim, Não, Não se aplica | F29: QN2 | G29: 15 | H29: Sim | J29: =IF(H29="Sim",G29, IF(H29="Parcialmente",G29/2, IF(OR(H29="Não",H29="Não se aplica"),0,""))) +IF(OR(H29="Sim",H29="Parcialmente"),Tabela1[[#This Row],[Pont. Resdist.]],0) | K29: 1ª análise: Doc 12.1, item 2.5; Doc 12, item 2.1 Documentação complementar: Termo de Designação do Oficial de Compliance, 07/07/2026 | L29: ATENDIDA — superada com a documentação complementar. • Análise inicial (resposta anterior: Não): O posicionamento hierárquico é mencionado no Código, mas sem documento formal que assegure independência e linha de reporte direto à alta direção. • Complementação (nova documentação): O Termo de Designação estabelece reporte direto à Diretoria, sem subordinação a outro departamento, conferindo independência à instância. | M29: Grupo: ESTRUTURA E ATIVIDADE ECONÔMICA Questão: Qual o porte da pessoa jurídica? Alternativa: Micro e Pequeno porte (de acordo com o Estatuto da Micro e Pequena pessoa jurídica) | N29: Distribuir 3,0 pontos para cada uma das questões (5): 4.1 4.2 4.4 5.1 5.2
B30: II | C30: Questão | D30: 4.4 A instância interna responsável pelo programa de integridade conta com quantitativo de funcionários proporcional às atribuições conferidas à área? Se sim, anexar documentos que demonstrem de forma expressa a estrutura de colaboradores alocados à área responsável pelo programa de integridade. | E30: Sim, Não | F30: QN5 | G30: 18 | H30: Sim | J30: =IF(H30="Sim",G30, IF(H30="Parcialmente",G30/2, IF(OR(H30="Não",H30="Não se aplica"),0,""))) +IF(OR(H30="Sim",H30="Parcialmente"),Tabela1[[#This Row],[Pont. Resdist.]],0) | K30: Doc 12.6; Doc 12.7 | L30: ATENDIDA (mantida da 1ª análise). O Oficial de Compliance conta com suporte da assessoria jurídica externa (Asseff Advogados) para investigações e due diligence, evidenciando acesso a recursos técnicos externos. Confirmada na reavaliação; a documentação complementar não a contradiz.
B31: II | C31: Grupo | D31: 5. Garantias atribuídas ao responsável pela instância interna para o exercício de suas atividades com autoridade e independência
B32: II | C32: Questão | D32: 5.1 O responsável pela instância interna de integridade possui garantias expressas que possibilitam o exercício das suas atribuições com independência e autoridade? Se sim, anexar documentos que comprovem a existência das garantias, a exemplo de mandato, nível de reporte, remuneração compatível com outras funções de mesmo nível hierárquico, livre acesso a documentos, pessoas e ativos da organização. | E32: Sim, Não, Parcialmente | F32: QN2 | G32: 15 | H32: Sim | J32: =IF(H32="Sim",G32, IF(H32="Parcialmente",G32/2, IF(OR(H32="Não",H32="Não se aplica"),0,""))) +IF(OR(H32="Sim",H32="Parcialmente"),Tabela1[[#This Row],[Pont. Resdist.]],0) | K32: 1ª análise: Cód_Etica.pdf (Doc 12.1) Documentação complementar: Termo de Designação do Oficial de Compliance, 07/07/2026 | L32: ATENDIDA — superada com a documentação complementar. • Análise inicial (resposta anterior: Não): Não foram apresentadas garantias expressas de independência e autoridade para o Oficial de Compliance, como mandato, nível de reporte formal à alta direção ou livre acesso documentado a sistemas e pessoas. O Código de Ética menciona a função mas não detalha as garantias. • Complementação (nova documentação): O Termo de Designação assegura garantias ao responsável: reporte direto, vedação de destituição/retaliação, livre acesso e participação em reuniões da Diretoria.
B33: II | C33: Questão | D33: 5.2 O responsável pela instância interna de integridade atua (diretamente ou como instância supervisora) na investigação e apuração de situações que configurem violações éticas ou legais? Se sim, anexar documentos que comprovem, no fluxo de tratamento de investigações e apurações de violações éticas e legais, que a instância interna atua diretamente ou mediante supervisão. | E33: Sim, Não | F33: QN4 | G33: 25 | H33: Sim | J33: =IF(H33="Sim",G33, IF(H33="Parcialmente",G33/2, IF(OR(H33="Não",H33="Não se aplica"),0,""))) +IF(OR(H33="Sim",H33="Parcialmente"),Tabela1[[#This Row],[Pont. Resdist.]],0) | K33: Doc 12.6; Doc 12.7; Doc 12.2; Doc 12.4 | L33: ATENDIDA (mantida da 1ª análise). O Oficial de Compliance participou diretamente: Investigação Interna 01/2024. Evidências de due diligence (09/2025), treinamento (08/2025) e comunicações sobre assédio (03/2026) não são aqui consideradas. Confirmada na reavaliação; a documentação complementar não a contradiz.
B34: III | C34: Área | D34: Área III - Gestão de Riscos para Integridade
B35: III | C35: Grupo | D35: 6. Gestão de riscos para integridade
B36: III | C36: Questão | D36: 6.1 Existe na pessoa jurídica política ou planejamento que trate da gestão de riscos e que defina a metodologia para a realização da análise de riscos? Se sim, anexar a política, metodologia ou outros documentos que formalizam a atividade de gestão de riscos. | E36: Sim, Não, Parcialmente | F36: QN2 | G36: 15 | H36: Sim | J36: =IF(H36="Sim",G36, IF(H36="Parcialmente",G36/2, IF(OR(H36="Não",H36="Não se aplica"),0,""))) +IF(OR(H36="Sim",H36="Parcialmente"),Tabela1[[#This Row],[Pont. Resdist.]],0) | K36: 1ª análise: Rel_Conformidade.pdf (Doc 12) — menciona gestão de riscos sem documentar a metodologia Documentação complementar: Matriz de Riscos de Integridade V.01/V.02.2026 (Termo de Aprovação da Diretoria, 24/03 e 30/07/2026) | L36: ATENDIDA — superada com a documentação complementar. • Análise inicial (resposta anterior: Não): Não foi apresentada política ou metodologia formal de gestão de riscos de integridade. O Relatório de Conformidade menciona a gestão de riscos como componente do programa, mas nenhum documento específico de política ou metodologia de análise de riscos foi juntado ao dossiê. • Complementação (nova documentação): A Matriz de Riscos de Integridade e seu Termo de Aprovação estabelecem metodologia, critérios de revisão e responsáveis, configurando planejamento formal de gestão de riscos.
B37: III | C37: Agrupadora | D37: 6.2 A política ou planejamento que trata da gestão de riscos:
B38: III | C38: Questão | D38: 6.2.1 institui a periodicidade mínima para atualização/revisão do processo de análise de riscos? Se sim, informar o item ou página da política, metodologia ou outro documento que comprove a existência do requisito. | E38: Sim, Não | F38: QN3 | G38: 5 | H38: Sim | J38: =IF(H38="Sim",G38, IF(H38="Parcialmente",G38/2, IF(OR(H38="Não",H38="Não se aplica"),0,""))) +IF(OR(H38="Sim",H38="Parcialmente"),Tabela1[[#This Row],[Pont. Resdist.]],0) | K38: 1ª análise: (sem documento) Documentação complementar: Matriz de Riscos de Integridade V.01/V.02.2026 (Termo de Aprovação da Diretoria, 24/03 e 30/07/2026) | L38: ATENDIDA — superada com a documentação complementar. • Análise inicial (resposta anterior: Não): Sem política formal de gestão de riscos, este quesito não é atendido. • Complementação (nova documentação): O Termo de Aprovação define revisão anual (ou por fato relevante), com próxima revisão ordinária em março/2027.
B39: III | C39: Questão | D39: 6.2.2 determina a área ou pessoa responsável pela gestão de riscos? Se sim, informar o item ou página da política, metodologia ou outro documento que comprove a existência do requisito. | E39: Sim, Não | F39: QN3 | G39: 5 | H39: Sim | J39: =IF(H39="Sim",G39, IF(H39="Parcialmente",G39/2, IF(OR(H39="Não",H39="Não se aplica"),0,""))) +IF(OR(H39="Sim",H39="Parcialmente"),Tabela1[[#This Row],[Pont. Resdist.]],0) | K39: 1ª análise: (sem documento) Documentação complementar: Matriz de Riscos de Integridade V.01/V.02.2026 (Termo de Aprovação da Diretoria, 24/03 e 30/07/2026); Termo de Designação do Oficial de Compliance, 07/07/2026 | L39: ATENDIDA — superada com a documentação complementar. • Análise inicial (resposta anterior: Não): Sem política formal de gestão de riscos, este quesito não é atendido. • Complementação (nova documentação): A gestão de riscos é atribuída ao Oficial de Compliance, com responsáveis por risco definidos na Matriz.
B40: III | C40: Questão | D40: 6.2.3 inclui sua revisão e aprovação pela alta direção? Se sim, informar o item ou página da política, metodologia ou outro documento que comprove a existência do requisito. | E40: Sim, Não | F40: QN3 | G40: 5 | H40: Sim | J40: =IF(H40="Sim",G40, IF(H40="Parcialmente",G40/2, IF(OR(H40="Não",H40="Não se aplica"),0,""))) +IF(OR(H40="Sim",H40="Parcialmente"),Tabela1[[#This Row],[Pont. Resdist.]],0) | K40: 1ª análise: (sem documento) Documentação complementar: Matriz de Riscos de Integridade V.01/V.02.2026 (Termo de Aprovação da Diretoria, 24/03 e 30/07/2026) | L40: ATENDIDA — superada com a documentação complementar. • Análise inicial (resposta anterior: Não): Sem política formal de gestão de riscos, este quesito não é atendido. • Complementação (nova documentação): A Matriz foi revisada e aprovada formalmente pela Diretoria Executiva (24/03/2026 e 30/07/2026).
B41: III | C41: Questão | D41: 6.3 A pessoa jurídica realizou, nos últimos 24 meses, uma análise de riscos que contempla expressamente riscos para integridade, isto é, aqueles relacionados a corrupção e fraude? Se sim, anexar a matriz de riscos ou documento equivalente, incluindo comprovação de que foi aprovado pela alta direção da entidade, no período indicado. | E41: Sim, Não | F41: QN1 | G41: 20 | H41: Sim | J41: =IF(H41="Sim",G41, IF(H41="Parcialmente",G41/2, IF(OR(H41="Não",H41="Não se aplica"),0,""))) +IF(OR(H41="Sim",H41="Parcialmente"),Tabela1[[#This Row],[Pont. Resdist.]],0) | K41: 1ª análise: Relatorio_Perfil.pdf (Doc 10, PGR-NR1, STARMED, 10/07/2025, folhas 132-141) — riscos OCUPACIONAIS apenas. Ausência de matriz de riscos de integridade/compliance. Documentação complementar: Matriz de Riscos de Integridade V.01/V.02.2026 (Termo de Aprovação da Diretoria, 24/03 e 30/07/2026) | L41: ATENDIDA — superada com a documentação complementar. • Análise inicial (resposta anterior: Não): QUESTÃO CRÍTICA — RESULTADO ELIMINATÓRIO. Não foi apresentada análise de riscos de INTEGRIDADE (corrupção e fraude). O Doc 10 (Relatorio_Perfil.pdf) contém um PGR - Programa de Gerenciamento de Riscos Ocupacionais (NR-1), elaborado pela STARMED em 10/07/2025, com matriz de riscos e inventário por GHE (riscos físicos, químicos, ergonômicos e de acidente de trabalho). Contudo, este é um documento de saúde e segurança ocupacional, obrigatório pela NR-1 do Ministério do Trabalho, que NÃO se confunde com a análise de riscos para integridade exigida pelo Decreto 12.304/2024 e pela Portaria SE/CGU nº 226/2025. A Portaria exige expressamente mapeamento de riscos 'relacionados a corrupção e fraude' — dimensão completamente ausente no PGR. A questão configura hipótese de indeferimento automático. • Complementação (nova documentação): A Matriz de Riscos de Integridade contempla expressamente riscos de corrupção e fraude, abrangendo TI, Financeiro, Projetos, Operações e Licitações, aprovada pela alta direção no período. Supre a lacuna eliminatória.
B42: III | C42: Questão | D42: 6.3.1 A análise de riscos contempla o mapeamento dos riscos para integridade relacionados à sua participação em licitações e na execução de contratos administrativos? Se sim, anexar a matriz de riscos ou documento equivalente que contenha os riscos mapeados relacionados à participação da entidade em licitações e contratos administrativos. | E42: Sim, Não | F42: QN3 | G42: 5 | H42: Sim | J42: =IF(H42="Sim",G42, IF(H42="Parcialmente",G42/2, IF(OR(H42="Não",H42="Não se aplica"),0,""))) +IF(OR(H42="Sim",H42="Parcialmente"),Tabela1[[#This Row],[Pont. Resdist.]],0) | K42: 1ª análise: (sem documento) Documentação complementar: Matriz de Riscos de Integridade V.01/V.02.2026 (Termo de Aprovação da Diretoria, 24/03 e 30/07/2026) | L42: ATENDIDA — superada com a documentação complementar. • Análise inicial (resposta anterior: Não): Ausência de matriz de riscos que contemple especificamente os riscos relacionados à participação em licitações e execução de contratos administrativos. • Complementação (nova documentação): A Matriz mapeia os riscos de integridade por área/subprocesso, com evento, causa e consequência. | O42: Bom ponto para citar no Relatório Final
B43: III | C43: Questão | D43: 6.3.2 A análise de riscos realizada contempla a classificação dos riscos com base em sua probabilidade e impacto? Se sim, anexar a matriz de riscos ou documento equivalente que contenha a análise e avaliação dos riscos com base em seu impacto e probabilidade. | E43: Sim, Não | F43: QN3 | G43: 5 | H43: Sim | J43: =IF(H43="Sim",G43, IF(H43="Parcialmente",G43/2, IF(OR(H43="Não",H43="Não se aplica"),0,""))) +IF(OR(H43="Sim",H43="Parcialmente"),Tabela1[[#This Row],[Pont. Resdist.]],0) | K43: 1ª análise: (sem documento) Documentação complementar: Matriz de Riscos de Integridade V.01/V.02.2026 (Termo de Aprovação da Diretoria, 24/03 e 30/07/2026) | L43: ATENDIDA — superada com a documentação complementar. • Análise inicial (resposta anterior: Não): Ausência de classificação de riscos por probabilidade e impacto. • Complementação (nova documentação): A Matriz classifica os riscos por probabilidade (1–5), impacto (1–4), score e nível (Baixo a Crítico).
B44: III | C44: Questão | D44: 6.3.3 A pessoa jurídica estabeleceu medidas voltadas para a mitigação dos riscos identificados, com a definição de prazos para implementação dessas medidas e dos responsáveis por sua implementação? Se sim, anexar documentos que demonstrem a definição das medidas de mitigação dos riscos identificados. | E44: Sim, Não, Parcialmente | F44: QN5 | G44: 18 | H44: Sim | J44: =IF(H44="Sim",G44, IF(H44="Parcialmente",G44/2, IF(OR(H44="Não",H44="Não se aplica"),0,""))) +IF(OR(H44="Sim",H44="Parcialmente"),Tabela1[[#This Row],[Pont. Resdist.]],0) | K44: 1ª análise: (sem documento) Documentação complementar: Matriz de Riscos de Integridade V.01/V.02.2026 (Termo de Aprovação da Diretoria, 24/03 e 30/07/2026) | L44: ATENDIDA — superada com a documentação complementar. • Análise inicial (resposta anterior: Não): Ausência de medidas de mitigação documentadas com prazos e responsáveis. • Complementação (nova documentação): A Matriz estabelece medidas mitigadoras de curto, médio e longo prazo, com responsáveis, prioridade e tipo de evidência.
B45: IV | C45: Área | D45: Área IV - Código de Ética e Conduta
B46: IV | C46: Grupo | D46: 7. Código de Ética e Conduta
B47: IV | C47: Questão | D47: 7.1 A pessoa jurídica possui código de ética e conduta, ou documento equivalente, disponível em português? Se sim, anexar o código ou documento equivalente. | E47: Sim, Não | F47: QN1 | G47: 20 | H47: Sim | J47: =IF(H47="Sim",G47, IF(H47="Parcialmente",G47/2, IF(OR(H47="Não",H47="Não se aplica"),0,""))) +IF(OR(H47="Sim",H47="Parcialmente"),Tabela1[[#This Row],[Pont. Resdist.]],0) | K47: Doc 12.1 - Código de Ética V.01.2025 | L47: ATENDIDA (mantida da 1ª análise). Código de Ética e Integridade V.01.2025, em português, com 13 páginas mais 2 anexos (Termo de Compromisso e Código de Investigações Internas). Confirmada na reavaliação; a documentação complementar não a contradiz. Reforçada pela documentação complementar.
B48: IV | C48: Agrupadora | D48: 7.2 O código de ética e conduta ou documento equivalente:
B49: IV | C49: Questão | D49: 7.2.1 foi formalmente aprovado pela alta direção da pessoa jurídica? Se sim, anexar documento ou registro que comprove a aprovação do código pela alta direção da entidade. | E49: Sim, Não | F49: QN3 | G49: 5 | H49: Sim | J49: =IF(H49="Sim",G49, IF(H49="Parcialmente",G49/2, IF(OR(H49="Não",H49="Não se aplica"),0,""))) +IF(OR(H49="Sim",H49="Parcialmente"),Tabela1[[#This Row],[Pont. Resdist.]],0) | K49: Cód_Etica.pdf (Doc 12.1 — assinatura digital 11/08/2025) | L49: ATENDIDA (mantida da 1ª análise). O Código de Ética foi assinado digitalmente em 11/08/2025, o que configura aprovação formal pela liderança da empresa. Confirmada na reavaliação; a documentação complementar não a contradiz.
B50: IV | C50: Questão | D50: 7.2.2 inclui expressamente a ética e/ou a integridade entre os princípios ou valores da pessoa jurídica? Se sim, indicar o dispositivo do código que atenda ao requisito. | E50: Sim, Não | F50: QN3 | G50: 5 | H50: Sim | J50: =IF(H50="Sim",G50, IF(H50="Parcialmente",G50/2, IF(OR(H50="Não",H50="Não se aplica"),0,""))) +IF(OR(H50="Sim",H50="Parcialmente"),Tabela1[[#This Row],[Pont. Resdist.]],0) | K50: Cód_Etica.pdf (Doc 12.1) | L50: ATENDIDA (mantida da 1ª análise). O Código de Ética trata explicitamente de ética e integridade como princípios norteadores da empresa, estabelecendo valores de transparência, honestidade e responsabilidade. Confirmada na reavaliação; a documentação complementar não a contradiz.
B51: IV | C51: Questão | D51: 7.2.3 está alinhado com a legislação anticorrupção brasileira, contendo vedações expressas à prática de atos de corrupção e fraude e prevenção de conflito de interesses? Se sim, indicar o(s) dispositivo(s) do código que atenda(m) ao requisito. | E51: Sim, Não, Parcialmente | F51: QN3 | G51: 5 | H51: Sim | J51: =IF(H51="Sim",G51, IF(H51="Parcialmente",G51/2, IF(OR(H51="Não",H51="Não se aplica"),0,""))) +IF(OR(H51="Sim",H51="Parcialmente"),Tabela1[[#This Row],[Pont. Resdist.]],0) | K51: Cód_Etica.pdf (Doc 12.1, item 4.4.4) | L51: ATENDIDA (mantida da 1ª análise). O Código de Ética contém vedação expressa à prática de atos de corrupção em relação a agentes públicos (item 4.4.4 — política de tolerância zero à corrupção) e disposições sobre prevenção de conflito de interesses, alinhadas com a legislação anticorrupção brasileira. Confirmada na reavaliação; a documentação complementar não a contradiz.
B52: IV | C52: Questão | D52: 7.2.4 expressa o compromisso da pessoa jurídica em combater o preconceito, a discriminação e o assédio de qualquer natureza em suas relações internas e externas? Se sim, indicar o(s) dispositivo(s) do código que atenda(m) ao requisito. | E52: Sim, Não, Parcialmente | F52: QN3 | G52: 5 | H52: Sim | J52: =IF(H52="Sim",G52, IF(H52="Parcialmente",G52/2, IF(OR(H52="Não",H52="Não se aplica"),0,""))) +IF(OR(H52="Sim",H52="Parcialmente"),Tabela1[[#This Row],[Pont. Resdist.]],0) | K52: Cód_Etica.pdf (Doc 12.1); Assédio.pdf (Doc 12.4) | L52: ATENDIDA (mantida da 1ª análise). O Código de Ética inclui disposições sobre assédio moral e sexual, discriminação e combate a preconceitos, complementadas pela comunicação específica sobre o tema enviada em 26/03/2026. Confirmada na reavaliação; a documentação complementar não a contradiz.
B53: IV | C53: Questão | D53: 7.2.5 estabelece as condutas permitidas e proibidas na pessoa jurídica? Se sim, indicar o(s) dispositivo(s) do código que atenda(m) ao requisito. | E53: Sim, Não | F53: QN3 | G53: 5 | H53: Sim | J53: =IF(H53="Sim",G53, IF(H53="Parcialmente",G53/2, IF(OR(H53="Não",H53="Não se aplica"),0,""))) +IF(OR(H53="Sim",H53="Parcialmente"),Tabela1[[#This Row],[Pont. Resdist.]],0) | K53: Cód_Etica.pdf (Doc 12.1) | L53: ATENDIDA (mantida da 1ª análise). O Código estabelece condutas permitidas e proibidas, incluindo: política de presentes e hospitalidades (brindes acima de R$ 100 requerem aprovação do Compliance Officer; refeições com agentes públicos limitadas a R$ 250/dia), vedações de conflito de interesses e proibição de atos corruptos. Confirmada na reavaliação; a documentação complementar não a contradiz.
B54: IV | C54: Questão | D54: 7.2.6 menciona a possibilidade de aplicação de sanções para aqueles que cometerem violações éticas/legais, inclusive para os membros da alta direção da pessoa jurídica? Se sim, indicar o(s) dispositivo(s) do código que atenda(m) ao requisito. | E54: Sim, Não, Parcialmente | F54: QN3 | G54: 5 | H54: Sim | J54: =IF(H54="Sim",G54, IF(H54="Parcialmente",G54/2, IF(OR(H54="Não",H54="Não se aplica"),0,""))) +IF(OR(H54="Sim",H54="Parcialmente"),Tabela1[[#This Row],[Pont. Resdist.]],0) | K54: Cód_Etica.pdf (Doc 12.1 — seção de sanções) | L54: ATENDIDA (mantida da 1ª análise). O Código prevê escala de sanções disciplinares: advertência formal, suspensão, demissão por justa causa (para colaboradores); rescisão contratual e ação judicial (para terceiros). Aplica-se a todos, incluindo membros da alta direção. Confirmada na reavaliação; a documentação complementar não a contradiz.
B55: IV | C55: Questão | D55: 7.3 O código de ética e conduta, ou documento equivalente, encontra-se disponível na página institucional da pessoa jurídica na internet? Se sim, informar o link e descrever o caminho, desde a página inicial da entidade, para acesso ao documento. | E55: Sim, Não | F55: QN5 | G55: 18 | H55: Não | J55: =IF(H55="Sim",G55, IF(H55="Parcialmente",G55/2, IF(OR(H55="Não",H55="Não se aplica"),0,""))) +IF(OR(H55="Sim",H55="Parcialmente"),Tabela1[[#This Row],[Pont. Resdist.]],0) | K55: 1ª análise: (sem documento) Documentação complementar: E-mails da Diretoria (João Darous) a todos os colaboradores, 02 e 17/07/2026; Procedimento de Prevenção a Ilícitos em Licitações e Contratos Administrativos V.01.2026; Procedimento de Monitoramento Contínuo do PI V.01.2026; Política de Doações e Patrocínios V.01.2026; Procedimento de Due Diligence de Terceiros V.01.2026 e Relatórios de DD 001/002/003-2026 | L55: • Análise inicial (resposta anterior: Não): Não foi apresentada evidência de que o Código de Ética esteja disponível no site institucional da empresa. Os documentos submetidos mencionam apenas o e-mail interno denuncia@jdseng.com.br, sem referência a link público de acesso ao Código. Ademais o site está apresentando problemas - Status do Site: Suspeito - quando se busca abrir outras abas. • Complementação (nova documentação): O Código é referenciado e complementado por novos normativos e Termos de Compromisso assinados; contudo, não foi juntada evidência (print) de sua publicação/disponibilização na página institucional. Além disso, o site da empresa (www.jsdeng.com.br) não funcionou no dia 11/08/2026. Segue a mensagem ao tentar visitar o site - "FortiGuard Intrusion Prevention - Access Blocked Web Page Blocked".
B56: IV | C56: Questão | D56: 7.4 A pessoa jurídica possui código de ética e conduta, ou documento equivalente, aplicável a terceiros e disponível em português? Se sim, informar o link e descrever o caminho, desde a página inicial da entidade para acesso ao documento. | E56: Sim, Não | F56: QN3 | G56: 5 | H56: Sim | J56: =IF(H56="Sim",G56, IF(H56="Parcialmente",G56/2, IF(OR(H56="Não",H56="Não se aplica"),0,""))) +IF(OR(H56="Sim",H56="Parcialmente"),Tabela1[[#This Row],[Pont. Resdist.]],0) | K56: Cód_Etica.pdf (Doc 12.1); Políticas_Internas.pdf (Doc 12.5 — Anexo I) | L56: ATENDIDA (mantida da 1ª análise). O Código de Ética menciona expressamente a extensão de seus princípios a terceiros e prestadores de serviços. As Políticas Internas incluem Termo de Ciência e Compromisso (Anexo I) a ser assinado por terceiros. Confirmada na reavaliação; a documentação complementar não a contradiz.
B57: IV | C57: Questão | D57: 7.5 A pessoa jurídica solicita aos terceiros que declarem expressamente que estão cientes da existência e do conteúdo do código, e que se comprometem a observar os termos e condições nele previstos? Se sim, anexar documentos que comprovem o comprometimento de terceiros e informar como e em que momento isso ocorre. | E57: Sim, Não | F57: QN5 | G57: 18 | H57: Sim | J57: =IF(H57="Sim",G57, IF(H57="Parcialmente",G57/2, IF(OR(H57="Não",H57="Não se aplica"),0,""))) +IF(OR(H57="Sim",H57="Parcialmente"),Tabela1[[#This Row],[Pont. Resdist.]],0) | K57: Termo_Compromisso.pdf (Doc 12.8) | L57: ATENDIDA (mantida da 1ª análise). Os Termos de Compromisso foram assinados por terceiros (Daniel Fernandes de Negreiros Paiva, Engenheiro Civil, CPF 036.301.044-01, em 30/03/2026), comprovando que a empresa solicita declaração expressa de conhecimento e comprometimento dos terceiros com as políticas. Confirmada na reavaliação; a documentação complementar não a contradiz.
B58: V | C58: Área | D58: Área V - Políticas e Procedimentos de Integridade e de Prevenção de Ilícitos em Licitações e Contratos Administrativos
B59: V | C59: Grupo | D59: 8. Políticas e procedimentos de integridade
B60: V | C60: Agrupadora | D60: 8.1 A pessoa jurídica possui políticas e procedimentos de integridade que:
B61: V | C61: Questão | D61: 8.1.1 vedam expressamente a concessão de vantagens indevidas, econômicas ou não, a agentes públicos? Se sim, anexar a política ou procedimento e indicar o(s) dispositivo(s) do documento que atenda(m) ao requisito. | E61: Sim, Não | F61: QN1 | G61: 20 | H61: Sim | J61: =IF(H61="Sim",G61, IF(H61="Parcialmente",G61/2, IF(OR(H61="Não",H61="Não se aplica"),0,""))) +IF(OR(H61="Sim",H61="Parcialmente"),Tabela1[[#This Row],[Pont. Resdist.]],0) | K61: Doc 12.1, item 4.4.4; Doc 12.5, item 8.1.3. | L61: ATENDIDA (mantida da 1ª análise). Código, item 4.4.4: "O oferecimento de brindes, presentes ou qualquer vantagem indevida a funcionários públicos é expressamente vedado." Política de Despesas §8.1.3 reforça: "para agente público, observar regra restritiva: não oferecer qualquer vantagem indevida." Confirmada na reavaliação; a documentação complementar não a contradiz. Reforçada pela documentação complementar.
B62: V | C62: Questão | D62: 8.1.2 tratam do oferecimento de presentes, brindes e hospitalidades (refeições, entretenimento, viagem e hospedagem) a agentes públicos? Se sim, anexar a política ou procedimento e indicar o(s) dispositivo(s) do documento que atenda(m) ao requisito. | E62: Sim, Não | F62: QN3 | G62: 5 | H62: Sim | J62: =IF(H62="Sim",G62, IF(H62="Parcialmente",G62/2, IF(OR(H62="Não",H62="Não se aplica"),0,""))) +IF(OR(H62="Sim",H62="Parcialmente"),Tabela1[[#This Row],[Pont. Resdist.]],0) | K62: Doc 12.1, item 4.2; Doc 12.5, itens 8.1 e 8.2 | L62: ATENDIDA (mantida da 1ª análise). Código Ética item 4.2 e Política de Despesas, itens 8.1, 8.2 e 8.3 tratam de presentes, brindes e hospitalidades com limites quantificados: R$100 para brindes (aprovação prévia do Compliance), R$250/dia para refeições, vedação de bebidas alcoólicas. Confirmada na reavaliação; a documentação complementar não a contradiz.
B63: V | C63: Questão | D63: 8.1.3 tratam da prevenção de conflito de interesses nas relações com a Administração Pública, incluindo contratações de agentes públicos e seus familiares? Se sim, anexar a política ou procedimento e indicar o(s) dispositivo(s) do documento que atenda(m) ao requisito. | E63: Sim, Não, Parcialmente | F63: QN3 | G63: 5 | H63: Sim | J63: =IF(H63="Sim",G63, IF(H63="Parcialmente",G63/2, IF(OR(H63="Não",H63="Não se aplica"),0,""))) +IF(OR(H63="Sim",H63="Parcialmente"),Tabela1[[#This Row],[Pont. Resdist.]],0) | K63: 1ª análise: Doc 12.1, item 3.3.2 Documentação complementar: Procedimento de Prevenção a Ilícitos em Licitações e Contratos Administrativos V.01.2026; Procedimento de Due Diligence de Terceiros V.01.2026 e Relatórios de DD 001/002/003-2026; Matriz de Riscos de Integridade V.01/V.02.2026 (Termo de Aprovação da Diretoria, 24/03 e 30/07/2026) | L63: ATENDIDA — superada com a documentação complementar. • Análise inicial (resposta anterior: Parcialmente): O Código item 3.3.2 exige comunicação ao Compliance sobre relações com membros da Administração Pública. Contudo, não há previsão específica sobre contratação de ex-agentes públicos ou seus familiares como colaboradores ou fornecedores. • Complementação (nova documentação): O Procedimento de Prevenção a Ilícitos (declaração prévia de conflito ao Compliance), o Procedimento de Due Diligence e a Matriz tratam expressamente a prevenção de conflito de interesses.
B64: V | C64: Questão | D64: 8.1.4 estabelecem orientações e controles sobre temas como realização de reuniões, encontros e outros tipos de interações entre administradores e empregados da pessoa jurídica com agentes públicos? Se sim, anexar a política ou procedimento e indicar o(s) dispositivo(s) do documento que atenda(m) ao requisito. | E64: Sim, Não, Parcialmente | F64: QN3 | G64: 5 | H64: Sim | J64: =IF(H64="Sim",G64, IF(H64="Parcialmente",G64/2, IF(OR(H64="Não",H64="Não se aplica"),0,""))) +IF(OR(H64="Sim",H64="Parcialmente"),Tabela1[[#This Row],[Pont. Resdist.]],0) | K64: Doc 12.1, item 4.4.2; Doc 12.5, item 8.3.1. | L64: ATENDIDA (mantida da 1ª análise). Código §4.4.2 exige documentação de toda comunicação com agentes públicos via ata enviada ao Compliance. Política de TI §8.3.1 determina registro formal de contatos em licitações por canal oficial. Confirmada na reavaliação; a documentação complementar não a contradiz.
B65: V | C65: Questão | D65: 8.1.5 tratam da realização de doação e patrocínio, ou informam claramente que a pessoa jurídica não realiza essas atividades? Se sim, anexar política/procedimento de integridade. Indicar, no campo correspondente, o artigo, item e/ou página em que há essa previsão. | E65: Sim, Não | F65: QN3 | G65: 5 | H65: Sim | J65: =IF(H65="Sim",G65, IF(H65="Parcialmente",G65/2, IF(OR(H65="Não",H65="Não se aplica"),0,""))) +IF(OR(H65="Sim",H65="Parcialmente"),Tabela1[[#This Row],[Pont. Resdist.]],0) | K65: 1ª análise: Ausência de política específica Documentação complementar: Política de Doações e Patrocínios V.01.2026 | L65: ATENDIDA — superada com a documentação complementar. • Análise inicial (resposta anterior: Não): Não foi apresentada política específica sobre realização ou vedação de doações e patrocínios. O tema não é abordado de forma estruturada nos documentos submetidos. • Complementação (nova documentação): A Política de Doações e Patrocínios V.01.2026 disciplina o tema, com aprovação prévia, due diligence do beneficiário e vedações (partidos, agentes públicos, espécie).
B66: V | C66: Questão | D66: 8.2 As políticas e procedimentos de integridade relacionados às interações com a Administração Pública foram aplicadas periodicamente pela pessoa jurídica nos últimos 12 meses? Se sim, descrever as ocasiões e a forma como as políticas e procedimentos foram aplicados, anexando a documentação comprobatória pertinente. | E66: Sim, Não, Parcialmente | F66: QN4 | G66: 25 | H66: Sim | J66: =IF(H66="Sim",G66, IF(H66="Parcialmente",G66/2, IF(OR(H66="Não",H66="Não se aplica"),0,""))) +IF(OR(H66="Sim",H66="Parcialmente"),Tabela1[[#This Row],[Pont. Resdist.]],0) | K66: 1ª análise: Doc 12.5; Doc 12.8; Doc 12 - Rel. Conformidade Documentação complementar: Procedimento de Prevenção a Ilícitos em Licitações e Contratos Administrativos V.01.2026 | L66: ATENDIDA — superada com a documentação complementar. • Análise inicial (resposta anterior: Parcialmente): As políticas foram aprovadas em março/2026 com vigência plena a partir de 01/04/2026. Termos de Compromisso assinados em 30/03/2026. Evidências de aplicação são incipientes dado o curto período de vigência (menos de 1 mês até a data do pedido de reabilitação). Há evidências de aplicação das políticas nos últimos 12 meses: treinamento sobre Código de Ética (26/08/2025), comunicação sobre assédio (26/03/2026), condução de due diligence em terceiro (22/09/2025) e investigação interna em 2024. Contudo, a aplicação é pontual, sem demonstrar sistematização. • Complementação (nova documentação): O Procedimento de Prevenção a Ilícitos em Licitações e Contratos estabelece regras específicas para as interações com a Administração Pública.
B67: V | C67: Grupo | D67: 9. Políticas e procedimentos específicos para prevenção de ilícitos em licitações e contratos administrativos
B68: V | C68: Questão | D68: 9.1. A pessoa jurídica possui políticas ou procedimentos específicos para prevenção de ilícitos em licitações e contratos administrativos? Se sim, anexar a política ou procedimentos que atenda(m) ao requisito. | E68: Sim, Não | F68: QN1 | G68: 20 | H68: Sim | J68: =IF(H68="Sim",G68, IF(H68="Parcialmente",G68/2, IF(OR(H68="Não",H68="Não se aplica"),0,""))) +IF(OR(H68="Sim",H68="Parcialmente"),Tabela1[[#This Row],[Pont. Resdist.]],0) | K68: 1ª análise: Doc 12.1, item 4.4.3 (disposições genéricas); Doc 12.5, item 8 (apenas segurança de TI) Documentação complementar: Procedimento de Prevenção a Ilícitos em Licitações e Contratos Administrativos V.01.2026 | L68: ATENDIDA — superada com a documentação complementar. • Análise inicial (resposta anterior: Não): QUESTÃO CRÍTICA ELIMINATÓRIA. Não existe política ou procedimento específico e abrangente para prevenção de ilícitos em licitações e contratos administrativos. A Política de TI §8 trata apenas de segurança informacional (credenciais, repositório), não de conduta anticorrupção. O Código de Ética aborda o tema de forma genérica (vedação de corrupção com agentes públicos), mas não contempla o nível de especificidade exigido por esta questão crítica, que constitui quesito de indeferimento automático do pedido de reabilitação. Esta lacuna é especialmente grave pois o ilícito original ocorreu exatamente na execução de contrato administrativo. • Complementação (nova documentação): O Procedimento de Prevenção a Ilícitos em Licitações e Contratos Administrativos V.01.2026 institui políticas/procedimentos específicos (condutas vedadas, regras operacionais, sanções) para o ambiente em que ocorreu o ilícito original. Supre a lacuna eliminatória.
B69: V | C69: Agrupadora | D69: 9.2 As políticas ou procedimentos:
B70: V | C70: Questão | D70: 9.2.1 estabelecem orientações sobre a conduta esperada (o que é permitido/proibido) para seus empregados e para terceiros que atuam em seu nome? Se sim, indicar o(s) dispositivo(s) da política ou procedimentos que atenda(m) ao requisito. | E70: Sim, Não, Parcialmente | F70: QN3 | G70: 5 | H70: Sim | J70: =IF(H70="Sim",G70, IF(H70="Parcialmente",G70/2, IF(OR(H70="Não",H70="Não se aplica"),0,""))) +IF(OR(H70="Sim",H70="Parcialmente"),Tabela1[[#This Row],[Pont. Resdist.]],0) | K70: 1ª análise: (sem documento) Documentação complementar: Procedimento de Prevenção a Ilícitos em Licitações e Contratos Administrativos V.01.2026 | L70: ATENDIDA — superada com a documentação complementar. • Análise inicial (resposta anterior: Não): Ausência de política específica para licitações e contratos. • Complementação (nova documentação): O Procedimento define expressamente a conduta esperada (o que é permitido/vedado) em licitações e contratos.
B71: V | C71: Questão | D71: 9.2.2 indicam expressamente os responsáveis por autorizar a adoção de medidas relacionadas à participação em licitações, bem como pela interação com os agentes públicos para tratar de questões relacionadas à gestão do contrato, como pagamento, alterações contratuais, aditivos e prorrogações? Se sim, indicar o(s) dispositivo(s) da política ou procedimentos que atenda(m) ao requisito. | E71: Sim, Não, Parcialmente | F71: QN3 | G71: 5 | H71: Não | J71: =IF(H71="Sim",G71, IF(H71="Parcialmente",G71/2, IF(OR(H71="Não",H71="Não se aplica"),0,""))) +IF(OR(H71="Sim",H71="Parcialmente"),Tabela1[[#This Row],[Pont. Resdist.]],0) | K71: Ausência de documento | L71: (Mantida da 1ª análise). Não foram definidos responsáveis por autorizar participação em licitações ou gerenciar contratos administrativos.
B72: V | C72: Questão | D72: 9.2.3 definem a necessidade de rotação periódica dos responsáveis por interagir com os agentes públicos em licitações e contratos administrativos? Se sim, indicar o(s) dispositivo(s) da política ou procedimentos que atenda(m) ao requisito. | E72: Sim, Não | F72: QN3 | G72: 5 | H72: Não | J72: =IF(H72="Sim",G72, IF(H72="Parcialmente",G72/2, IF(OR(H72="Não",H72="Não se aplica"),0,""))) +IF(OR(H72="Sim",H72="Parcialmente"),Tabela1[[#This Row],[Pont. Resdist.]],0) | K72: Ausência de documento | L72: (Mantida da 1ª análise). Não há previsão de rotação periódica de responsáveis por interações com agentes públicos em licitações e contratos.
B73: V | C73: Questão | D73: 9.2.4 orientam a relação da pessoa jurídica com seus concorrentes, a fim de evitar práticas anticoncorrenciais que possibilitem fraude em processos licitatórios? Se sim, indicar o(s) dispositivo(s) da política ou procedimentos que atenda(m) ao requisito. | E73: Sim, Não | F73: QN3 | G73: 5 | H73: Não | J73: =IF(H73="Sim",G73, IF(H73="Parcialmente",G73/2, IF(OR(H73="Não",H73="Não se aplica"),0,""))) +IF(OR(H73="Sim",H73="Parcialmente"),Tabela1[[#This Row],[Pont. Resdist.]],0) | K73: Ausência de documento | L73: (Mantida da 1ª análise). Não foram apresentadas orientações sobre a relação com concorrentes para prevenir práticas anticoncorrenciais e fraudes em licitações.
B74: V | C74: Questão | D74: 9.3 A pessoa jurídica aplicou, nos últimos 12 meses, as orientações e controles específicos para prevenção de fraudes e ilícitos em licitações e contratos administrativos? Se sim, descrever as ocasiões e a forma como as orientações e controles foram aplicados. | E74: Sim, Não, Parcialmente | F74: QN4 | G74: 25 | H74: Parcialmente | J74: =IF(H74="Sim",G74, IF(H74="Parcialmente",G74/2, IF(OR(H74="Não",H74="Não se aplica"),0,""))) +IF(OR(H74="Sim",H74="Parcialmente"),Tabela1[[#This Row],[Pont. Resdist.]],0) | K74: Ausência de documento | L74: PARCIALMENTE ATENDIDA. • Análise inicial (resposta anterior: Não): Ausência de políticas específicas para licitações impede a avaliação de sua aplicação prática. Nesse ponto, deveria haver o Tipo de Resposta "Não se Aplica". • Complementação (nova documentação): O procedimento é recente (mar/2026); há evidências iniciais de aplicação (registros de due diligence), mas a aplicação continuada nos 12 meses ainda está em consolidação.
B75: VI | C75: Área | D75: Área VI - Treinamentos e Ações de Comunicação sobre o Programa de Integridade
B76: VI | C76: Grupo | D76: 10. Treinamentos sobre o Programa de Integridade
B77: VI | C77: Questão | D77: 10.1 A pessoa jurídica possui um planejamento para a realização de treinamentos sobre integridade com definição do cronograma, temas, públicos-alvo, responsáveis e forma de execução? Se sim, anexar o documento ou informações que demonstrem o planejamento vigente. | E77: Sim, Não | F77: QN1 | G77: 20 | H77: Sim | J77: =IF(H77="Sim",G77, IF(H77="Parcialmente",G77/2, IF(OR(H77="Não",H77="Não se aplica"),0,""))) +IF(OR(H77="Sim",H77="Parcialmente"),Tabela1[[#This Row],[Pont. Resdist.]],0) | K77: 1ª análise: Doc 12.1 item 8 (genérico); ausência de plano de treinamento Documentação complementar: Calendário de Treinamentos 2026/2027 | L77: ATENDIDA — superada com a documentação complementar. • Análise inicial (resposta anterior: Não): QUESTÃO CRÍTICA — RESULTADO ELIMINATÓRIO. Não foi apresentado planejamento formal de treinamentos sobre integridade com cronograma, temas, públicos-alvo, responsáveis e forma de execução. O único documento apresentado é um e-mail de convocação avulso para um treinamento específico (26/08/2025), sem demonstrar que integra planejamento estruturado. • Complementação (nova documentação): O Calendário de Treinamentos 2026/2027 traz cronograma, temas, públicos-alvo, responsável (Compliance) e forma de execução, suprindo a lacuna eliminatória de planejamento.
B78: VI | C78: Questão | D78: 10.2 A pessoa jurídica realizou, nos últimos 12 meses, treinamento(s) direcionado(s) a todos os seus colaboradores, abordando conteúdo de integridade, como aqueles relacionados ao código de ética, canais de denúncia ou políticas anticorrupção? Se sim, anexar documentos e/ou indicar, no campo correspondente, link em que seja possível visualizar os treinamentos realizados e descrever as ocasiões, temas, carga horária e público alcançado. | E78: Sim, Não, Parcialmente | F78: QN4 | G78: 25 | H78: Parcialmente | J78: =IF(H78="Sim",G78, IF(H78="Parcialmente",G78/2, IF(OR(H78="Não",H78="Não se aplica"),0,""))) +IF(OR(H78="Sim",H78="Parcialmente"),Tabela1[[#This Row],[Pont. Resdist.]],0) | K78: 1ª análise: Doc 12.2 - Email de convocação (25/08/2025); Doc 12.3 - lista de presença e quiz Documentação complementar: Calendário de Treinamentos 2026/2027 | L78: PARCIALMENTE ATENDIDA. • Análise inicial (resposta anterior: Não): Treinamento on-line realizado em 26/08/2025, duração de ~30 min, para ~11 colaboradores do escritório (aproximadamente 18% dos 62 colaboradores). Cobertura insuficiente para ser considerado direcionado a todos os colaboradores. Além disso, trata-se de treinamento isolado e a questão fala de "treinamentos". • Complementação (nova documentação): Há treinamento a ser realizado (ago/2025) e novos previstos; a cobertura ampliada (meta de 70%) ainda depende da execução das ações programadas para 2026/2027.
B79: VI | C79: Questão | D79: 10.3 A pessoa jurídica realizou, nos últimos 12 meses, treinamento(s) direcionado(s) a públicos específicos, e, realização de diligências para contratação e supervisão de terceiros? Se sim, anexar documentos e/ou indicar, no campo correspondente, link em que seja possível visualizar os treinamentos realizados e descrever as ocasiões, temas, carga horária e público alcançado. | E79: Sim, Não, Parcialmente | F79: QN5 | G79: 18 | H79: Não | J79: =IF(H79="Sim",G79, IF(H79="Parcialmente",G79/2, IF(OR(H79="Não",H79="Não se aplica"),0,""))) +IF(OR(H79="Sim",H79="Parcialmente"),Tabela1[[#This Row],[Pont. Resdist.]],0) | K79: 1ª análise: Código de Ética Documentação complementar: Calendário de Treinamentos 2026/2027 | L79: • Análise inicial (resposta anterior: Não): Treinamento geral sobre Código de Ética (26/08/2025). Foi identificada comunicação específica sobre assédio e discriminação para equipes de campo e de escritório (26/03/2026) - não considerada neste bloco, que trata de treinamentos. Não foram identificados treinamentos específicos sobre due diligence de terceiros, contratos públicos ou supervisão de obras. • Complementação (nova documentação): O plano prevê treinamento específico para equipes de campo (set/2026) e gestores (nov/2026), ainda como PREVISTO; execução pendente. Contudo não foram realizados.
B80: VI | C80: Questão | D80: 10.4 Os treinamentos relacionados ao programa de integridade realizados pela pessoa jurídica nos últimos 12 meses atingiram, em média, 70% de cada um dos públicos-alvo? Se sim, anexar documentos ou informações que demonstrem o cumprimento do requisito. | E80: Sim, Não | F80: QN3 | G80: 5 | H80: Não | J80: =IF(H80="Sim",G80, IF(H80="Parcialmente",G80/2, IF(OR(H80="Não",H80="Não se aplica"),0,""))) +IF(OR(H80="Sim",H80="Parcialmente"),Tabela1[[#This Row],[Pont. Resdist.]],0) | K80: 1ª análise: Doc 12.2; Doc 12.3 - lista de presença com ~11 participantes de 62 colaboradores Documentação complementar: Calendário de Treinamentos 2026/2027 | L80: • Análise inicial (resposta anterior: Não): A cobertura do treinamento realizado foi insuficiente: ~11 colaboradores convocados para o treinamento sobre Código de Ética representam aproximadamente 18-29% do total de colaboradores (38 CLT + 24 PJ), bem abaixo da meta mínima de 70% por público-alvo. • Complementação (nova documentação): O plano estrutura conteúdos por público; o registro de execução e efetividade dependerá da realização das ações previstas. Contudo não foram realizados.
B81: VI | C81: Grupo | D81: 11. Comunicações sobre o Programa de Integridade
B82: VI | C82: Questão | D82: 11.1 A pessoa jurídica possui um planejamento para a realização de ações recorrentes de comunicação sobre integridade, com definição do cronograma, temas, responsáveis, públicos-alvo e meios de divulgação? Se sim, anexar o documento ou informações que demonstrem o planejamento vigente. | E82: Sim, Não | F82: QN1 | G82: 20 | H82: Sim | J82: =IF(H82="Sim",G82, IF(H82="Parcialmente",G82/2, IF(OR(H82="Não",H82="Não se aplica"),0,""))) +IF(OR(H82="Sim",H82="Parcialmente"),Tabela1[[#This Row],[Pont. Resdist.]],0) | K82: 1ª análise: Ausência de plano de comunicações Documentação complementar: Calendário de Comunicações 2026 | L82: ATENDIDA — superada com a documentação complementar. • Análise inicial (resposta anterior: Não): QUESTÃO CRÍTICA — RESULTADO ELIMINATÓRIO. Não foi apresentado planejamento formal de comunicações sobre integridade com cronograma, temas, responsáveis, públicos-alvo e meios de divulgação. As comunicações identificadas são pontuais e não decorrem de um plano estruturado de comunicação. • Complementação (nova documentação): O Calendário de Comunicações 2026 traz cronograma, temas, responsável, públicos-alvo e meios, suprindo a lacuna eliminatória de planejamento de comunicações.
B83: VI | C83: Questão | D83: 11.2 A pessoa jurídica promoveu, nos últimos 12 meses, ações de comunicação voltadas à divulgação dos aspectos gerais do programa de integridade, como código de ética e de conduta, política anticorrupção e canais de denúncia? Se sim, anexar documentos e/ou indicar, no campo correspondente, link em que seja possível visualizar as comunicações realizadas no período. | E83: Sim, Não, Parcialmente | F83: QN4 | G83: 25 | H83: Sim | J83: =IF(H83="Sim",G83, IF(H83="Parcialmente",G83/2, IF(OR(H83="Não",H83="Não se aplica"),0,""))) +IF(OR(H83="Sim",H83="Parcialmente"),Tabela1[[#This Row],[Pont. Resdist.]],0) | K83: Doc 12.2 - Email Código de Ética (25/08/2025); Doc 12.4 - Email sobre assédio (26/03/2026) | L83: ATENDIDA (mantida da 1ª análise). Foram realizadas ações de comunicação: (i) email de lançamento do Código de Ética com convocação para treinamento (25/08/2025) e (ii) email sobre assédio e canal de denúncias com cartilha institucional, enviado em grupos segmentados para escritório e campo (26/03/2026). Confirmada na reavaliação; a documentação complementar não a contradiz.
B84: VI | C84: Questão | D84: 11.2.1 As ações de comunicação realizadas pela empresa no período avaliado foram feitas de forma periódica e contínua? Se sim, anexar documentos e/ou indicar, no campo correspondente, informações que demonstrem a realização de comunicações de forma periódica e contínua sobre integridade. | E84: Sim, Não | F84: QN3 | G84: 5 | H84: não | J84: =IF(H84="Sim",G84, IF(H84="Parcialmente",G84/2, IF(OR(H84="Não",H84="Não se aplica"),0,""))) +IF(OR(H84="Sim",H84="Parcialmente"),Tabela1[[#This Row],[Pont. Resdist.]],0) | K84: 1ª análise: Doc 12.2; Doc 12.4 Documentação complementar: E-mails da Diretoria (João Darous) a todos os colaboradores, 02 e 17/07/2026; Calendário de Comunicações 2026 | L84: PARCIALMENTE ATENDIDA. • Análise inicial (resposta anterior: Não): Houve apenas 2 ações de comunicação identificadas em 7 meses (agosto/2025 e março/2026). Não configura comunicação periódica e contínua. • Complementação (nova documentação): As comunicações da Diretoria (jul/2026) alcançaram a totalidade dos colaboradores; a abrangência recorrente ao longo do ano ainda está em execução. Com apenas essas comunicações (pontuais), não se pode concluir pela continuidade, mas por um atendimento parcial. Como não há a opção do atendimento parcial nessa questão, a avaliação considerou pela negativa.
B85: VII | C85: Área | D85: Área VII - Controles Contábeis, Financeiros e Auditoria Interna
B86: VII | C86: Grupo | D86: 12. Controles Contábeis e Financeiros
B87: VII | C87: Questão | D87: 12.1 A pessoa jurídica possui procedimentos definidos para a realização dos lançamentos contábeis e financeiros? Se sim, anexar os documentos ou informações que estabeleçam os procedimentos existentes. | E87: Sim, Não | F87: QN1 | G87: 20 | H87: Sim | J87: =IF(H87="Sim",G87, IF(H87="Parcialmente",G87/2, IF(OR(H87="Não",H87="Não se aplica"),0,""))) +IF(OR(H87="Sim",H87="Parcialmente"),Tabela1[[#This Row],[Pont. Resdist.]],0) | K87: 1ª análise: Doc 12.5 - Política de Despesas, itens 5, 9 e 10 Documentação complementar: Escrituração Contábil Digital (ECD/SPED) — Livro Diário Geral | L87: ATENDIDA — superada com a documentação complementar. • Análise inicial (resposta anterior: Não): A Política de Despesas e Benefícios V.01.2026 (Doc 12.5) estabelece procedimentos financeiros para despesas, reembolsos, adiantamentos, aprovações e prestação de contas, com segregação de funções e auditoria amostral mensal. Contudo, não inclui procedimentos específicos para lançamentos contábeis, plano de contas ou reconciliações de balanço. O julgamento correto para o item seria pelo atendimento parcial, mas se optou pelo Não tendo em vista ser questão crítica. • Complementação (nova documentação): A Escrituração Contábil Digital (ECD/SPED) — Livro Diário Geral autenticado, com plano de contas estruturado e Balanço Patrimonial — evidencia procedimentos regulares e padronizados de lançamentos contábeis e financeiros, combinada à Política de Despesas (segregação de funções e auditoria amostral). Supre a lacuna eliminatória. (Aprimoramento recomendável: manual/política contábil interna descrevendo rotinas de lançamento e conciliações.)
B88: VII | C88: Questão | D88: 12.2 A pessoa jurídica possui regras que estabelecem a segregação de funções e a definição de níveis de aprovação (alçadas) de receitas e despesas? Se sim, anexar documentos que comprovem a existência das regras. Indicar, no campo correspondente, o artigo, item e/ou página em que há essa previsão. | E88: Sim, Não | F88: QN3 | G88: 5 | H88: Sim | J88: =IF(H88="Sim",G88, IF(H88="Parcialmente",G88/2, IF(OR(H88="Não",H88="Não se aplica"),0,""))) +IF(OR(H88="Sim",H88="Parcialmente"),Tabela1[[#This Row],[Pont. Resdist.]],0) | K88: Doc 12.5, item 5, item 9 | L88: ATENDIDA (mantida da 1ª análise). A Política de Despesas §5 define segregação clara: Financeiro (validação de documentos e controle de pagamentos), Gestor da área/obra (validação da necessidade e centro de custo), Compliance (aprovação de exceções sensíveis). §9 estabelece fluxo de aprovação para reembolsos e adiantamentos. Confirmada na reavaliação; a documentação complementar não a contradiz.
B89: VII | C89: Questão | D89: 12.3 A pessoa jurídica possui mecanismos e/ou "red flags" para detectar receitas e despesas fora do padrão durante o registro de lançamentos contábeis? Se sim, anexar os documentos ou informações que estabeleçam os procedimentos existentes. | E89: Sim, Não | F89: QN3 | G89: 5 | H89: Não | J89: =IF(H89="Sim",G89, IF(H89="Parcialmente",G89/2, IF(OR(H89="Não",H89="Não se aplica"),0,""))) +IF(OR(H89="Sim",H89="Parcialmente"),Tabela1[[#This Row],[Pont. Resdist.]],0) | K89: 1ª análise: (sem documento) Documentação complementar: Matriz de Riscos de Integridade V.01/V.02.2026 (Termo de Aprovação da Diretoria, 24/03 e 30/07/2026); Escrituração Contábil Digital (ECD/SPED) — Livro Diário Geral | L89: • Análise inicial (resposta anterior: Não): Não foram apresentados mecanismos ou red flags proativos para detecção de receitas e despesas fora do padrão durante o registro de lançamentos contábeis. • Complementação (nova documentação): A Matriz de Riscos e os controles financeiros trazem sinalizadores de risco; contudo, não há sistema formal de "red flags" contábeis descrito. O adequado seria o julgamento parcial, como não há a opção do atendimento parcial nessa questão, a avaliação considerou pela negativa.
B90: VII | C90: Questão | D90: 12.4 A pessoa jurídica possui regras que exigem a verificação do cumprimento do objeto do contrato para realização do pagamento? Se sim, anexar documentos ou informações que estabeleçam os procedimentos existentes. | E90: Sim, Não | F90: QN2 | G90: 15 | H90: Não | J90: =IF(H90="Sim",G90, IF(H90="Parcialmente",G90/2, IF(OR(H90="Não",H90="Não se aplica"),0,""))) +IF(OR(H90="Sim",H90="Parcialmente"),Tabela1[[#This Row],[Pont. Resdist.]],0) | K90: 1ª análise: Doc 12.5, itens 6.4.1 e 10.3 Documentação complementar: Matriz de Riscos de Integridade V.01/V.02.2026 (Termo de Aprovação da Diretoria, 24/03 e 30/07/2026) | L90: • Análise inicial (resposta anterior: Parcialmente): A Política de Despesas, item 6.4.1, exige que despesas de obra constem do centro de custo da obra/contrato e sejam aprovadas pelo gestor. O item 10.3 prevê auditoria amostral mensal de obras remotas. Contudo, não há procedimento específico de verificação técnica do cumprimento do objeto contratual antes do pagamento de serviços. • Complementação (nova documentação): A Matriz de Riscos (FIN-001) exige controle mínimo de prestação de contas por obra, com checklist e evidências, condicionando novos adiantamentos à prestação anterior; contudo, ainda não há procedimento específico de verificação técnica do cumprimento do objeto como condição formal de pagamento. O adequado seria o julgamento parcial, como não há a opção do atendimento parcial nessa questão, a avaliação considerou pela negativa.
B91: VII | C91: Grupo | D91: 13. Auditoria Interna
B92: VII | C92: Questão | D92: 13.1 A pessoa jurídica possui função de auditoria interna formalmente estabelecida, seja de forma direta ou terceirizada? Se sim, anexar o estatuto ou documento que demonstre o estabelecimento da função de auditoria interna. | E92: Sim, Não, Não se aplica | F92: QN2 | G92: 15 | H92: Sim | J92: =IF(H92="Sim",G92, IF(H92="Parcialmente",G92/2, IF(OR(H92="Não",H92="Não se aplica"),0,""))) +IF(OR(H92="Sim",H92="Parcialmente"),Tabela1[[#This Row],[Pont. Resdist.]],0) | K92: 1ª análise: Doc 12.1, item 2.5.5 (previsão futura não implementada) Documentação complementar: Procedimento de Monitoramento Contínuo do PI V.01.2026; Escrituração Contábil Digital (ECD/SPED) — Livro Diário Geral | L92: • Análise inicial (resposta anterior: Não): Não existe função de auditoria interna formalmente estabelecida. O Código de Ética, item 2.5.5, menciona futura contratação de auditoria externa independente, mas sem evidência de implementação. • Complementação (nova documentação): Há auditoria amostral mensal (Política de Despesas) e relatórios de conformidade trimestrais/anuais (Monitoramento); porém, não foi constituída função de auditoria interna independente formalizada. A avaliação mais adequadada para responder esse item seria o atendimento parcial. Como não há essa possibilidade, optou-se pelo Sim, pois as funções estão sendo conduzidas internamente. | M92: Grupo: ESTRUTURA E ATIVIDADE ECONÔMICA Questão: Qual o porte da pessoa jurídica? Alternativa: Micro e Pequeno porte (de acordo com o Estatuto da Micro e Pequena pessoa jurídica) | N92: Distribuir 3,75 pontos para cada uma das questões (4): 12.1 12.2 12.3 12.4
B93: VII | C93: Questão | D93: 13.2 A função de auditoria interna reporta-se diretamente à alta direção ou instância de governança da pessoa jurídica? Se sim, anexar o estatuto ou outro documento que demonstre o nível de reporte da função de auditoria interna. | E93: Sim, Não, Não se aplica | F93: QN3 | G93: 5 | H93: Não se aplica | J93: =IF(H93="Sim",G93, IF(H93="Parcialmente",G93/2, IF(OR(H93="Não",H93="Não se aplica"),0,""))) +IF(OR(H93="Sim",H93="Parcialmente"),Tabela1[[#This Row],[Pont. Resdist.]],0) | K93: — | L93: NÃO SE APLICA (mantida da 1ª análise). Não aplicável — ausência de função de auditoria interna. | M93: Grupo: ESTRUTURA E ATIVIDADE ECONÔMICA Questão: Qual o porte da pessoa jurídica? Alternativa: Micro e Pequeno porte (de acordo com o Estatuto da Micro e Pequena pessoa jurídica) | N93: Distribuir 1,25 pontos para cada uma das questões (4): 12.1 12.2 12.3 12.4
B94: VII | C94: Questão | D94: 13.3 A função de auditoria interna dispõe de estrutura, recursos e nível de acesso adequados ao cumprimento de suas atribuições? Se sim, anexar o estatuto e demais documentos que demonstrem a adequação da estrutura, recursos e nível de acesso da função de auditoria interna. | E94: Sim, Não, Parcialmente, Não se aplica | F94: QN3 | G94: 5 | H94: Não se aplica | J94: =IF(H94="Sim",G94, IF(H94="Parcialmente",G94/2, IF(OR(H94="Não",H94="Não se aplica"),0,""))) +IF(OR(H94="Sim",H94="Parcialmente"),Tabela1[[#This Row],[Pont. Resdist.]],0) | K94: — | L94: NÃO SE APLICA (mantida da 1ª análise). Não aplicável — ausência de função de auditoria interna. | M94: Grupo: ESTRUTURA E ATIVIDADE ECONÔMICA Questão: Qual o porte da pessoa jurídica? Alternativa: Micro e Pequeno porte (de acordo com o Estatuto da Micro e Pequena pessoa jurídica) | N94: Distribuir 1,25 pontos para cada uma das questões (4): 12.1 12.2 12.3 12.4
B95: VII | C95: Questão | D95: 13.4 São produzidos relatórios periódicos de auditoria interna? Se sim, anexar o último relatório anual de atividades da unidade de auditoria interna. | E95: Sim, Não, Não se aplica | F95: QN5 | G95: 18 | H95: Não se aplica | J95: =IF(H95="Sim",G95, IF(H95="Parcialmente",G95/2, IF(OR(H95="Não",H95="Não se aplica"),0,""))) +IF(OR(H95="Sim",H95="Parcialmente"),Tabela1[[#This Row],[Pont. Resdist.]],0) | K95: — | L95: NÃO SE APLICA (mantida da 1ª análise). Não aplicável — ausência de função de auditoria interna. | M95: Grupo: ESTRUTURA E ATIVIDADE ECONÔMICA Questão: Qual o porte da pessoa jurídica? Alternativa: Micro e Pequeno porte (de acordo com o Estatuto da Micro e Pequena pessoa jurídica) | N95: Distribuir 4,50 pontos para cada uma das questões (4): 12.1 12.2 12.3 12.4
B96: VII | C96: Questão | D96: 13.5 As recomendações ou apontamentos emitidos pela função de auditoria interna são adequada e tempestivamente implementadas pela pessoa jurídica? Se sim, anexar documentos que demonstrem a adequada e tempestiva implementação das recomendações emitidas pela função de auditoria interna. | E96: Sim, Não, Parcialmente, Não se aplica | F96: QN5 | G96: 18 | H96: Não se aplica | J96: =IF(H96="Sim",G96, IF(H96="Parcialmente",G96/2, IF(OR(H96="Não",H96="Não se aplica"),0,""))) +IF(OR(H96="Sim",H96="Parcialmente"),Tabela1[[#This Row],[Pont. Resdist.]],0) | K96: — | L96: NÃO SE APLICA (mantida da 1ª análise). Não aplicável — ausência de função de auditoria interna. | M96: Grupo: ESTRUTURA E ATIVIDADE ECONÔMICA Questão: Qual o porte da pessoa jurídica? Alternativa: Micro e Pequeno porte (de acordo com o Estatuto da Micro e Pequena pessoa jurídica) | N96: Distribuir 4,50 pontos para cada uma das questões (4): 12.1 12.2 12.3 12.4
B97: VIII | C97: Área | D97: Área VIII - Diligências para Contratação e Supervisão de Terceiros e para Fusões e Aquisições Societárias
B98: VIII | C98: Grupo | D98: 14. Diligências para contratação e supervisão de terceiros
B99: VIII | C99: Agrupadora | D99: 14.1 A pessoa jurídica possui políticas e procedimentos baseadas em risco para a realização de diligências, contratação e supervisão de terceiros, que:
B100: VIII | C100: Questão | D100: 14.1.1 determinam a verificação de possível envolvimento do terceiro em casos de corrupção e práticas de fraude contra a Administração Pública? Se sim, anexar as políticas e/ou procedimentos, indicando o artigo, item e/ou página onde consta essa previsão. | E100: Sim, Não | F100: QN1 | G100: 20 | H100: Sim | J100: =IF(H100="Sim",G100, IF(H100="Parcialmente",G100/2, IF(OR(H100="Não",H100="Não se aplica"),0,""))) +IF(OR(H100="Sim",H100="Parcialmente"),Tabela1[[#This Row],[Pont. Resdist.]],0) | K100: Rel_Due_Diligence.pdf (Doc 12.7, 22/09/2025); Cód_Etica.pdf (Doc 12.1) | L100: ATENDIDA (mantida da 1ª análise). QUESTÃO CRÍTICA ATENDIDA. O Código de Ética e o procedimento de due diligence evidenciam que a empresa verifica o envolvimento de terceiros em casos de corrupção antes da contratação. O Relatório de Due Diligence (22/09/2025) comprova a aplicação prática para o terceiro Raphael Luiz de Abreu Lima (PMC Serviços), com verificação de processos judiciais incluindo atos ilícitos contra a Administração Pública. Confirmada na reavaliação; a documentação complementar não a contradiz. Reforçada pela documentação complementar.
B101: VIII | C101: Questão | D101: 14.1.2 determinam a verificação da existência de registro do terceiro em “listas sujas” de trabalho escravo ou em condições análogas às de escravo? Se sim, anexar as políticas e/ou procedimentos, indicando o artigo, item e/ou página onde consta essa previsão. | E101: Sim, Não | F101: QN3 | G101: 5 | H101: Sim | J101: =IF(H101="Sim",G101, IF(H101="Parcialmente",G101/2, IF(OR(H101="Não",H101="Não se aplica"),0,""))) +IF(OR(H101="Sim",H101="Parcialmente"),Tabela1[[#This Row],[Pont. Resdist.]],0) | K101: 1ª análise: Doc 12.7 - ausência de verificação em lista de trabalho escravo Documentação complementar: Procedimento de Due Diligence de Terceiros V.01.2026 e Relatórios de DD 001/002/003-2026 | L101: ATENDIDA — superada com a documentação complementar. • Análise inicial (resposta anterior: Não): Não há verificação em listas de trabalho escravo (MTE/SRTE) nas diligências realizadas. O Relatório de Due Diligence não menciona consulta a esse registro. • Complementação (nova documentação): O Procedimento de Due Diligence (item 4.2) exige consulta a CEIS, CNEP, CEPIM, inidôneos do TCU/TCEs e CNJ, verificando registros do terceiro.
B102: VIII | C102: Questão | D102: 14.1.3 determinam a verificação de possível envolvimento do terceiro em crimes ambientais ou em práticas nocivas ao meio ambiente? Se sim, anexar as políticas e/ou procedimentos, indicando o artigo, item e/ou página onde consta essa previsão. | E102: Sim, Não, Não se aplica | F102: QN3 | G102: 5 | H102: Sim | J102: =IF(H102="Sim",G102, IF(H102="Parcialmente",G102/2, IF(OR(H102="Não",H102="Não se aplica"),0,""))) +IF(OR(H102="Sim",H102="Parcialmente"),Tabela1[[#This Row],[Pont. Resdist.]],0) | K102: 1ª análise: Doc 12.7 - ausência de verificação ambiental Documentação complementar: Procedimento de Due Diligence de Terceiros V.01.2026 e Relatórios de DD 001/002/003-2026 | L102: ATENDIDA — superada com a documentação complementar. • Análise inicial (resposta anterior: Não): Não há verificação de crimes ambientais ou histórico ambiental dos terceiros nas diligências realizadas. • Complementação (nova documentação): O Procedimento exige verificação de trabalho escravo (lista suja/MTE) e socioambiental (IBAMA/órgãos estaduais), com vedação de contratação em caso de registro. | M102: Grupo: PRÁTICAS SOCIOAMBIENTAIS Questão: A atividade da pessoa jurídica envolve potencial de dano ao meio ambiente? Alternativa: NÃO | N102: Distribuir pontos para cada uma das questões (7): 14.1.1 = 0,72 14.1.2 = 0,71 14.1.4 = 0,71 14.2 = 0,72 15.1.1 = 0,71 15.1.2 = 0,71 15.2 = 0,72
...

Sheet Contadores
B1: DADOS REFERENTES AO FORMULÁRIO DE CONFORMIDADE
B3: Áreas | C3: I | D3: II | E3: III | F3: IV | G3: V | H3: VI | I3: VII | J3: VIII | K3: IX | L3: X | M3: XI | N3: TOTAL | O3: XII | R3: Tipo | S3: Val Unit. | T3: Qtde Itens | U3: % total | V3: Pontos
B4: Grupos | C4: =COUNTIFS('Formulário de Conformidade'!$C:$C,"Grupo",'Formulário de Conformidade'!$B:$B,C3) | D4: =COUNTIFS('Formulário de Conformidade'!$C:$C,"Grupo",'Formulário de Conformidade'!$B:$B,D3) | E4: =COUNTIFS('Formulário de Conformidade'!$C:$C,"Grupo",'Formulário de Conformidade'!$B:$B,E3) | F4: =COUNTIFS('Formulário de Conformidade'!$C:$C,"Grupo",'Formulário de Conformidade'!$B:$B,F3) | G4: =COUNTIFS('Formulário de Conformidade'!$C:$C,"Grupo",'Formulário de Conformidade'!$B:$B,G3) | H4: =COUNTIFS('Formulário de Conformidade'!$C:$C,"Grupo",'Formulário de Conformidade'!$B:$B,H3) | I4: =COUNTIFS('Formulário de Conformidade'!$C:$C,"Grupo",'Formulário de Conformidade'!$B:$B,I3) | J4: =COUNTIFS('Formulário de Conformidade'!$C:$C,"Grupo",'Formulário de Conformidade'!$B:$B,J3) | ... M4: =COUNTIFS('Formulário de Conformidade'!$C:$C,"Grupo",'Formulário de Conformidade'!$B:$B,M3) | N4: =SUM(C4:M4) | O4: =COUNTIFS('Formulário de Conformidade'!$C:$C,"Grupo",'Formulário de Conformidade'!$B:$B,O3) | R4: QN1 | S4: 20 | T4: =COUNTIF('Formulário de Conformidade'!F1:F160, R4) | U4: =T4/N5 | V4: =S4*T4
B5: Questões | C5: =COUNTIFS('Formulário de Conformidade'!$C:$C,"Questão",'Formulário de Conformidade'!$B:$B,C3) | D5: =COUNTIFS('Formulário de Conformidade'!$C:$C,"Questão",'Formulário de Conformidade'!$B:$B,D3) | E5: =COUNTIFS('Formulário de Conformidade'!$C:$C,"Questão",'Formulário de Conformidade'!$B:$B,E3) | F5: =COUNTIFS('Formulário de Conformidade'!$C:$C,"Questão",'Formulário de Conformidade'!$B:$B,F3) | G5: =COUNTIFS('Formulário de Conformidade'!$C:$C,"Questão",'Formulário de Conformidade'!$B:$B,G3) | H5: =COUNTIFS('Formulário de Conformidade'!$C:$C,"Questão",'Formulário de Conformidade'!$B:$B,H3) | I5: =COUNTIFS('Formulário de Conformidade'!$C:$C,"Questão",'Formulário de Conformidade'!$B:$B,I3) | J5: =COUNTIFS('Formulário de Conformidade'!$C:$C,"Questão",'Formulário de Conformidade'!$B:$B,J3) | ... M5: =COUNTIFS('Formulário de Conformidade'!$C:$C,"Questão",'Formulário de Conformidade'!$B:$B,M3) | N5: =SUM(C5:M5) | O5: =COUNTIFS('Formulário de Conformidade'!$C:$C,"Questão",'Formulário de Conformidade'!$B:$B,O3) | R5: QN2 | S5: 15 | T5: =COUNTIF('Formulário de Conformidade'!F1:F160, R5) | U5: =T5/$N5 | V5: =S5*T5
B6: Pontuação | C6: =SUMIFS('Formulário de Conformidade'!$G:$G,'Formulário de Conformidade'!$C:$C,"Questão",'Formulário de Conformidade'!$B:$B,C3) | D6: =SUMIFS('Formulário de Conformidade'!$G:$G,'Formulário de Conformidade'!$C:$C,"Questão",'Formulário de Conformidade'!$B:$B,D3) | E6: =SUMIFS('Formulário de Conformidade'!$G:$G,'Formulário de Conformidade'!$C:$C,"Questão",'Formulário de Conformidade'!$B:$B,E3) | F6: =SUMIFS('Formulário de Conformidade'!$G:$G,'Formulário de Conformidade'!$C:$C,"Questão",'Formulário de Conformidade'!$B:$B,F3) | G6: =SUMIFS('Formulário de Conformidade'!$G:$G,'Formulário de Conformidade'!$C:$C,"Questão",'Formulário de Conformidade'!$B:$B,G3) | H6: =SUMIFS('Formulário de Conformidade'!$G:$G,'Formulário de Conformidade'!$C:$C,"Questão",'Formulário de Conformidade'!$B:$B,H3) | I6: =SUMIFS('Formulário de Conformidade'!$G:$G,'Formulário de Conformidade'!$C:$C,"Questão",'Formulário de Conformidade'!$B:$B,I3) | J6: =SUMIFS('Formulário de Conformidade'!$G:$G,'Formulário de Conformidade'!$C:$C,"Questão",'Formulário de Conformidade'!$B:$B,J3) | ... M6: =SUMIFS('Formulário de Conformidade'!$G:$G,'Formulário de Conformidade'!$C:$C,"Questão",'Formulário de Conformidade'!$B:$B,M3) | N6: =SUM(C6:M6) | O6: =SUMIFS('Formulário de Conformidade'!$G:$G,'Formulário de Conformidade'!$C:$C,"Questão",'Formulário de Conformidade'!$B:$B,O3) | R6: QN3 | S6: 5 | T6: =COUNTIF('Formulário de Conformidade'!F1:F160, R6) | U6: =T6/$N5 | V6: =S6*T6
B7: % Pontuação Metodologia | C7: =C6/$N6 | D7: =D6/$N6 | E7: =E6/$N6 | F7: =F6/$N6 | G7: =G6/$N6 | H7: =H6/$N6 | I7: =I6/$N6 | J7: =J6/$N6 | ... M7: =M6/$N6 | N7: =SUM(C7:M7) | O7: =O6/$N6 | R7: QN4 | S7: 25 | T7: =COUNTIF('Formulário de Conformidade'!F1:F160, R7) | U7: =T7/$N5 | V7: =S7*T7
B8: % Pró-Ética | C8: 0.13 | D8: 0.13 | E8: 0.1 | F8: 0.05 | G8: 0.13 | H8: 0.11 | I8: 0.06 | J8: 0.09 | K8: 0.1 | L8: 0.05 | M8: 0.05 | N8: =SUM(C8:M8) | O8: - | R8: QN5 | S8: 18 | T8: =COUNTIF('Formulário de Conformidade'!F1:F160, R8) | U8: =T8/$N5 | V8: =S8*T8

Sheet Resultado
B3: Áreas Avaliadas | C3: Pontuação máxima | D3: Percentual mínimo | E3: Pontuação Atingida | F3: Percentual Antingido | G3: Questões QN1 | H3: Questões QN4
B4: Área I - Comprometimento da Alta Direção da Pessoa jurídica | C4: 154 | D4: 0.3 | E4: =SUM('Formulário de Conformidade'!J11:J24) | F4: =E4/C4
B5: Área II - Instância Interna Responsável pela Aplicação do Programa de Integridade | C5: 108 | D5: 0.3 | E5: =SUM('Formulário de Conformidade'!J27:J33) | F5: =E5/C5
B6: Área III - Gestão de Riscos para Integridade | C6: 78 | D6: 0.3 | E6: =SUM('Formulário de Conformidade'!J36:J44) | F6: =E6/C6
B7: Área IV - Código de Ética e Conduta | C7: 91 | D7: 0.3 | E7: =SUM('Formulário de Conformidade'!J47:J57) | F7: =E7/C7
B8: Área V - Políticas e Procedimentos de Integridade e de Prevenção de Ilícitos em Licitações e Contratos Administrativos | C8: 130 | D8: 0.3 | E8: =SUM('Formulário de Conformidade'!J61:J74) | F8: =E8/C8
B9: Área VI - Treinamentos e Ações de Comunicação sobre o Programa de Integridade | C9: 118 | D9: 0.3 | E9: =SUM('Formulário de Conformidade'!J77:J84) | F9: =E9/C9
B10: Área VII - Controles Contábeis, Financeiros e Auditoria Interna | C10: 106 | D10: 0.3 | E10: =SUM('Formulário de Conformidade'!J87:J96) | F10: =E10/C10
B11: Área VIII - Diligências para Contratação e Supervisão de Terceiros e para Fusões e Aquisições Societárias | C11: 114 | D11: 0.3 | E11: =SUM('Formulário de Conformidade'!J99:J112) | F11: =E11/C11
B12: Área IX - Canais de Denúncia, Remediação e Medidas Disciplinares | C12: 141 | D12: 0.3 | E12: =SUM('Formulário de Conformidade'!J115:J133) | F12: =E12/C12
B13: Área X - Monitoramento do Programa de Integridade | C13: 83 | D13: 0.3 | E13: =SUM('Formulário de Conformidade'!J136:J144) | F13: =E13/C13
B14: Área XI - Responsabilidade Socioambiental e Transparência | C14: 83 | D14: 0.3 | E14: =SUM('Formulário de Conformidade'!J147:J160) | F14: =E14/C14
B15: Área XII - Medidas de Remediação adotadas em face dos atos que ensejaram a aplicação da sanção | C15: 95 | D15: 0.7 | E15: =SUM('Formulário de Conformidade'!J163:J173) | F15: =E15/C15
B16: TOTAL | C16: =SUM(C4:C15) | D16: 0.45 | E16: =SUM(E4:E15) | F16: =E16/C16

Sheet Planilha2

Sheet 3  Validação da Tabela Pergunta
A1: DescTituloPerguntaFormularioTipoAvaliacao | B1: IdBlocoFormularioTipoAvaliacao | C1: FlgAgrupadora | D1: FlgDistribuicaoValorRespostaNaoSeAplica | E1: FlgRespostaPossivelNaoSeAplica | F1: FlgRespostaPossivelParcialmente | G1: FlgRespostaPossivelSimNao | H1: FlgSolicitantePodeResponder | I1: NumOrdem | J1: ValFixoPontuacaoItem | K1: FlgEvidenciaObrigatoria | L1: FlgMedidaMinimaAdocaoProgramaIntegridade | M1: FlgObservacaoObrigatoria | N1: TxtInformacaoAdicional
A2: 1.1 A pessoa jurídica possui critérios de integridade formalizados para seleção dos candidatos aos cargos da alta direção? Se sim, anexar documentos que comprovem a existência dos critérios de integridade para seleção e informar os cargos a que são aplicados, a forma como os critérios são considerados e os responsáveis por sua avaliação. | B2: 293 | C2: FALSE | D2: FALSE | E2: FALSE | F2: FALSE | G2: TRUE | H2: TRUE | I2: 1 | J2: 15 | K2: TRUE | L2: FALSE | M2: FALSE | N2: Evidências que comprovem que a pessoa jurídica possui critérios éticos, como políticas de seleção e procedimentos de contratação, para escolha de membros da alta direção.
A3: 1.2 A pessoa jurídica aplicou critérios de integridade para seleção dos ocupantes de cargos da alta direção contratados nos últimos 24 meses? Se sim, anexar documentos que comprovem a aplicação dos critérios de integridade para seleção. | B3: 293 | C3: FALSE | D3: TRUE | E3: TRUE | F3: FALSE | G3: TRUE | H3: TRUE | I3: 2 | J3: 18 | K3: TRUE | L3: FALSE | M3: FALSE | N3: Evidências que comprovem a aplicação de critérios de integridade na escolha da alta direção, incluindo testes de integridade, background check, Know Your Employee - KYE, pesquisas em fontes abertas e análises de antecedentes sobre histórico profissional, práticas ilícitas e conduta ética.
A4: 1.3 A pessoa jurídica possui política de remuneração variável para os membros da alta direção condicionada ao atingimento de metas de desempenho relacionadas aos indicadores de aplicação ao programa de integridade? Se sim, anexar a política de remuneração que comprova a existência dessa regra e descrever como ela é aplicada. | B4: 293 | C4: FALSE | D4: TRUE | E4: TRUE | F4: FALSE | G4: TRUE | H4: TRUE | I4: 3 | J4: 15 | K4: TRUE | L4: FALSE | M4: FALSE | N4: Evidências da adoção de norma formal que vincula a remuneração variável da alta direção ao cumprimento de metas relacionadas aos indicadores do programa de integridade.
A5: 2.1 A aprovação das principais políticas relacionadas ao programa de integridade é feita pelas mais elevadas instâncias decisórias da pessoa jurídica? Se sim, anexar documentos que comprovem a aprovação das principais políticas relacionadas ao programa de integridade pela alta direção. | B5: 294 | C5: FALSE | D5: FALSE | E5: FALSE | F5: FALSE | G5: TRUE | H5: TRUE | I5: 1 | J5: 20 | K5: TRUE | L5: TRUE | M5: FALSE | N5: Evidências da participação da alta direção na aprovação de políticas do programa de integridade, como atas de reuniões, e-mails ou documentos que comprovem a criação ou atualização de políticas, estruturas e procedimentos, ou registros incluídos na própria política.
A6: 2.2 A pessoa jurídica possui em sua estrutura de governança órgão colegiado (como comitê ou conselho de ética) para deliberar sobre temas de ética e integridade, que contam com a participação de membros da alta direção? Se sim, anexar documentos que comprovem a existência do órgão colegiado e a participação dos membros da alta direção em sua composição. | B6: 294 | C6: FALSE | D6: TRUE | E6: TRUE | F6: FALSE | G6: TRUE | H6: TRUE | I6: 2 | J6: 15 | K6: TRUE | L6: FALSE | M6: FALSE | N6: Evidências da existência de um órgão colegiado responsável por tratar de temas do programa de integridade, como estatutos, regimentos, políticas internas e atas, demonstrando a participação ativa dos membros da alta direção nesse colegiado.
A7: 2.3 A alta direção da pessoa jurídica supervisiona, diretamente ou por intermédio de órgão colegiado do qual ela participe, a implantação e a aplicação do programa de integridade, por meio do recebimento e avaliação de relatórios periódicos de acompanhamento das atividades relacionadas ao programa de integridade? | B7: 294 | C7: FALSE | D7: FALSE | E7: FALSE | F7: TRUE | G7: TRUE | H7: TRUE | I7: 3 | J7: 18 | K7: TRUE | L7: FALSE | M7: FALSE | N7: Evidências que comprovem a supervisão da alta direção na implantação e aplicação do programa de integridade, como atas de reuniões, e-mails, apresentações feitas em reuniões, registros de frequência das ações de supervisão, relatórios assinados e documentos que demonstrem o acompanhamento das atividades do programa.
A8: 3.1 Os membros da alta direção, individualmente, manifestam publicamente apoio ao programa de integridade? Se sim, anexar documentos e/ou indicar, no campo correspondente, link em que seja possível visualizar as manifestações de apoio ao programa de integridade por membros da alta direção. | B8: 295 | C8: FALSE | D8: FALSE | E8: FALSE | F8: FALSE | G8: TRUE | H8: TRUE | I8: 1 | J8: 20 | K8: TRUE | L8: FALSE | M8: FALSE | N8: Evidências de que a alta direção, de forma individualizada, reforça seu compromisso com a ética e a integridade, por meio de comunicados estratégicos em canais como e-mails, redes sociais, intranet, vídeos institucionais e comunicados internos e externos, demonstrando apoio ao programa de integridade.
A9: 3.2 As manifestações de apoio ao programa de integridade por membros da alta direção: | B9: 295 | C9: TRUE | D9: FALSE | E9: FALSE | F9: FALSE | G9: FALSE | H9: TRUE | I9: 2 | J9: 0 | K9: FALSE | L9: FALSE | M9: FALSE
A10: 3.2.1 são feitas de forma periódica e divulgadas por diferentes meios para alcançar o público interno e externo da pessoa jurídica em toda sua diversidade? Se sim, demonstrar a medida em que as manifestações de apoio ao programa de integridade ocorreram de forma periódica e direcionadas aos diferentes públicos da entidade. | B10: 295 | C10: FALSE | D10: FALSE | E10: FALSE | F10: TRUE | G10: TRUE | H10: TRUE | I10: 3 | J10: 5 | K10: TRUE | L10: FALSE | M10: FALSE | N10: Evidências de que as declarações de apoio ao programa de integridade foram feitas por diferentes membros da alta direção e de forma periódica, reforçando o compromisso da liderança com a ética e a transparência.
A11: 3.2.2 expressam uma mensagem de incentivo à adoção de uma conduta ética, seguindo os ditames do programa de integridade? Se sim, demonstrar a medida em que as manifestações de apoio ao programa de integridade expressaram o compromisso com os temas. | B11: 295 | C11: FALSE | D11: FALSE | E11: FALSE | F11: FALSE | G11: TRUE | H11: TRUE | I11: 4 | J11: 5 | K11: TRUE | L11: FALSE | M11: FALSE | N11: Evidências de mensagens claras da alta direção aos colaboradores, sociedade, mercado e stakeholders, reforçando o compromisso da pessoa jurídica no combate ao preconceito, discriminação e assédio em qualquer forma.
A12: 3.2.3 expressam o compromisso da alta direção com o combate ao preconceito, à discriminação e ao assédio de qualquer natureza? Se sim, demonstrar a medida em que as manifestações de apoio ao programa de integridade expressaram o compromisso com os temas. | B12: 295 | C12: FALSE | D12: FALSE | E12: FALSE | F12: FALSE | G12: TRUE | H12: TRUE | I12: 5 | J12: 5 | K12: TRUE | L12: FALSE | M12: FALSE | N12: Evidências de mensagens claras da alta direção aos colaboradores, sociedade, mercado e stakeholders, reforçando o compromisso da pessoa jurídica no combate ao preconceito, discriminação e assédio em qualquer forma.
A13: 3.3 A pessoa jurídica destina recursos em seu orçamento para a manutenção das atividades relacionadas ao programa de integridade? Se sim, anexar documentos que comprovem a destinação de recursos para o programa de integridade. | B13: 295 | C13: FALSE | D13: FALSE | E13: FALSE | F13: FALSE | G13: TRUE | H13: TRUE | I13: 6 | J13: 18 | K13: TRUE | L13: FALSE | M13: FALSE | N13: Evidências que comprovem a elaboração de orçamento que destine recursos específicos para a área responsável pelo programa de integridade, antes de cada exercício, tais como: orçamento, atas de reunião com aprovação orçamentária etc., que contemplem as despesas programadas para a área.
A14: 4.1 A pessoa jurídica possui área ou pessoa responsável pela aplicação do programa de integridade? Se sim, anexar documentos que comprovem a existência da área específica ou pessoa responsável, informando a data em que a área foi instituída ou em que a pessoa responsável foi contratada/designada para a função e o currículo do atual responsável pelo programa de integridade. | B14: 297 | C14: FALSE | D14: FALSE | E14: FALSE | F14: FALSE | G14: TRUE | H14: TRUE | I14: 1 | J14: 20 | K14: TRUE | L14: TRUE | M14: FALSE | N14: Evidências sobre a existência de uma instância interna (seja uma área ou pessoa designada) responsável pela implementação, fiscalização e monitoramento contínuo do programa de integridade no Brasil, tais como: políticas, regimento interno, estatuto, job description etc. Não serão considerados órgãos colegiados (comitês, conselhos etc).
A15: 4.2 A instância interna responsável pelo programa de integridade está formalmente constituída, tendo suas atribuições expressamente previstas em documento aprovado pela alta direção da pessoa jurídica? Se sim, anexar documentos que comprovem a constituição formal da área responsável pelo programa de integridade, com suas atribuições e responsabilidades definidas. | B15: 297 | C15: FALSE | D15: FALSE | E15: FALSE | F15: TRUE | G15: TRUE | H15: TRUE | I15: 2 | J15: 15 | K15: FALSE | L15: FALSE | M15: FALSE | N15: Evidências documentais que descrevam explicitamente a área responsável pelo programa de integridade, com suas atribuições e responsabilidades detalhadas, tais como regimentos internos, estatuto social, regimentos, políticas e atas de reuniões que comprovem a criação, estrutura e funcionamento do setor, aprovado pela alta direção.
A16: 4.3 A instância interna responsável pelo programa possui estrutura independente, não estando subordinada a outro departamento da pessoa jurídica – jurídico, auditoria, RH etc.? Se sim, anexar organograma que demonstre a estrutura atual da instância interna e suas linhas de reporte ou política/procedimento que formalize tal estrutura e linhas de reporte. | B16: 297 | C16: FALSE | D16: TRUE | E16: TRUE | F16: FALSE | G16: TRUE | H16: TRUE | I16: 3 | J16: 15 | K16: TRUE | L16: FALSE | M16: FALSE | N16: Evidência como política ou procedimento que formalize tal estrutura, organograma da pessoa jurídica que demonstre a posição hierárquica e as linhas de reporte da área de integridade.
A17: 4.4 A instância interna responsável pelo programa de integridade conta com quantitativo de funcionários proporcional às atribuições conferidas à área? Se sim, anexar documentos que demonstrem de forma expressa a estrutura de colaboradores alocados à área responsável pelo programa de integridade. | B17: 297 | C17: FALSE | D17: FALSE | E17: FALSE | F17: FALSE | G17: TRUE | H17: TRUE | I17: 4 | J17: 18 | K17: TRUE | L17: FALSE | M17: FALSE | N17: Evidências que demonstrem o quantitativo de funcionários alocados na área de integridade, exclusiva ou parcialmente, correlacionando essa estrutura às atribuições previstas para a instância responsável pelo programa de integridade.
A18: 5.1 O responsável pela instância interna de integridade possui garantias expressas que possibilitam o exercício das suas atribuições com independência e autoridade? Se sim, anexar documentos que comprovem a existência das garantias, a exemplo de mandato, nível de reporte, remuneração compatível com outras funções de mesmo nível hierárquico, livre acesso a documentos, pessoas e ativos da organização. | B18: 296 | C18: FALSE | D18: FALSE | E18: FALSE | F18: TRUE | G18: TRUE | H18: TRUE | I18: 1 | J18: 15 | K18: TRUE | L18: FALSE | M18: FALSE | N18: Evidências como estatuto, política de integridade ou job description, que definem garantias da área responsável pelo programa de integridade, incluindo independência, acesso a informações, proteção contra punições arbitrárias e validade de decisões.
A19: 5.2 O responsável pela instância interna de integridade atua (diretamente ou como instância supervisora) na investigação e apuração de situações que configurem violações éticas ou legais? Se sim, anexar documentos que comprovem, no fluxo de tratamento de investigações e apurações de violações éticas e legais, que a instância interna atua diretamente ou mediante supervisão. | B19: 296 | C19: FALSE | D19: FALSE | E19: FALSE | F19: FALSE | G19: TRUE | H19: TRUE | I19: 2 | J19: 25 | K19: TRUE | L19: FALSE | M19: FALSE | N19: Evidências como estatuto, política de integridade ou job description, que estabelecem a atuação direta ou supervisão da instância de integridade no fluxo de investigações e apurações.
A20: 6.1 Existe na pessoa jurídica política ou planejamento que trate da gestão de riscos e que defina a metodologia para a realização da análise de riscos? Se sim, anexar a política, metodologia ou outros documentos que formalizam a atividade de gestão de riscos. | B20: 298 | C20: FALSE | D20: FALSE | E20: FALSE | F20: TRUE | G20: TRUE | H20: TRUE | I20: 1 | J20: 15 | K20: TRUE | L20: FALSE | M20: FALSE | N20: Evidências como normas ou planejamento da pessoa jurídica que detalham a gestão de riscos, incluindo responsáveis, fluxo de aprovação, monitoramento e revisões.
A21: 6.2 A política ou planejamento que trata da gestão de riscos: | B21: 298 | C21: TRUE | D21: FALSE | E21: FALSE | F21: FALSE | G21: FALSE | H21: TRUE | I21: 2 | J21: 0 | K21: FALSE | L21: FALSE | M21: FALSE
A22: 6.2.1 institui a periodicidade mínima para atualização/revisão do processo de análise de riscos? Se sim, informar o item ou página da política, metodologia ou outro documento que comprove a existência do requisito. | B22: 298 | C22: FALSE | D22: FALSE | E22: FALSE | F22: FALSE | G22: TRUE | H22: TRUE | I22: 3 | J22: 5 | K22: TRUE | L22: FALSE | M22: FALSE | N22: Evidências como normas ou planejamento da pessoa jurídica que detalham revisões e a periodicidade mínima para atualização/revisão do processo de análise de riscos.
A23: 6.2.2 determina a área ou pessoa responsável pela gestão de riscos? Se sim, informar o item ou página da política, metodologia ou outro documento que comprove a existência do requisito. | B23: 298 | C23: FALSE | D23: FALSE | E23: FALSE | F23: FALSE | G23: TRUE | H23: TRUE | I23: 4 | J23: 5 | K23: TRUE | L23: FALSE | M23: FALSE | N23: Evidências como normas ou planejamento da pessoa jurídica que determina a área ou pessoa responsável pela gestão de riscos no âmbito do processo de análise de riscos.
A24: 6.2.3 inclui sua revisão e aprovação pela alta direção? Se sim, informar o item ou página da política, metodologia ou outro documento que comprove a existência do requisito. | B24: 298 | C24: FALSE | D24: FALSE | E24: FALSE | F24: FALSE | G24: TRUE | H24: TRUE | I24: 5 | J24: 5 | K24: TRUE | L24: FALSE | M24: FALSE | N24: Evidências como normas, atas de reunião ou planejamento da pessoa jurídica que incluem e detalham revisões e aprovação, por parte da alta direção, na gestão dos riscos.
A25: 6.3 A pessoa jurídica realizou, nos últimos 24 meses, uma análise de riscos que contempla expressamente riscos para integridade, isto é, aqueles relacionados a corrupção e fraude? Se sim, anexar a matriz de riscos ou documento equivalente, incluindo comprovação de que foi aprovado pela alta direção da entidade, no período indicado. | B25: 298 | C25: FALSE | D25: FALSE | E25: FALSE | F25: FALSE | G25: TRUE | H25: TRUE | I25: 6 | J25: 20 | K25: TRUE | L25: TRUE | M25: FALSE | N25: Evidências da análise de riscos para integridade, relacionadas à corrupção e fraude, realizada pela própria pessoa jurídica ou por terceiros, como relatórios internos, matriz de risco, e relatórios de consultorias.
A26: 6.3.1 A análise de riscos contempla o mapeamento dos riscos para integridade relacionados à sua participação em licitações e na execução de contratos administrativos? Se sim, anexar a matriz de riscos ou documento equivalente que contenha os riscos mapeados relacionados à participação da entidade em licitações e contratos administrativos. | B26: 298 | C26: FALSE | D26: FALSE | E26: FALSE | F26: FALSE | G26: TRUE | H26: TRUE | I26: 7 | J26: 5 | K26: TRUE | L26: FALSE | M26: FALSE | N26: Evidências como matriz de riscos e relatórios, que identificam e classificam riscos de integridade relacionados à participação em licitações e na execução de contratos administrativos
A27: 6.3.2 A análise de riscos realizada contempla a classificação dos riscos com base em sua probabilidade e impacto? Se sim, anexar a matriz de riscos ou documento equivalente que contenha a análise e avaliação dos riscos com base em seu impacto e probabilidade. | B27: 298 | C27: FALSE | D27: FALSE | E27: FALSE | F27: FALSE | G27: TRUE | H27: TRUE | I27: 8 | J27: 5 | K27: TRUE | L27: FALSE | M27: FALSE | N27: Evidências como matriz de riscos e relatórios, que identificam e classificam riscos de integridade, avaliando sua probabilidade e impacto.
A28: 6.3.3 A pessoa jurídica estabeleceu medidas voltadas para a mitigação dos riscos identificados, com a definição de prazos para implementação dessas medidas e dos responsáveis por sua implementação? Se sim, anexar documentos que demonstrem a definição das medidas de mitigação dos riscos identificados. | B28: 298 | C28: FALSE | D28: FALSE | E28: FALSE | F28: TRUE | G28: TRUE | H28: TRUE | I28: 9 | J28: 18 | K28: TRUE | L28: FALSE | M28: FALSE | N28: Evidências como matriz de riscos e relatórios, com as medidas voltadas para a mitigação dos riscos identificados.
A29: 7.1 A pessoa jurídica possui código de ética e conduta, ou documento equivalente, disponível em português? Se sim, anexar o código ou documento equivalente. | B29: 299 | C29: FALSE | D29: FALSE | E29: FALSE | F29: FALSE | G29: TRUE | H29: TRUE | I29: 1 | J29: 20 | K29: TRUE | L29: TRUE | M29: FALSE | N29: Evidência baseada no Código de Ética e Conduta, ou documento equivalente, em língua portuguesa.
A30: 7.2 O código de ética e conduta ou documento equivalente: | B30: 299 | C30: TRUE | D30: FALSE | E30: FALSE | F30: FALSE | G30: FALSE | H30: TRUE | I30: 2 | J30: 0 | K30: FALSE | L30: FALSE | M30: FALSE
A31: 7.2.1 foi formalmente aprovado pela alta direção da pessoa jurídica? Se sim, anexar documento ou registro que comprove a aprovação do código pela alta direção da entidade. | B31: 299 | C31: FALSE | D31: FALSE | E31: FALSE | F31: FALSE | G31: TRUE | H31: TRUE | I31: 3 | J31: 5 | K31: TRUE | L31: FALSE | M31: FALSE | N31: Evidência que valide a aprovação da alta direção, como ata de reunião, aprovação ou mensagem constante no próprio Código.
A32: 7.2.2 inclui expressamente a ética e/ou a integridade entre os princípios ou valores da pessoa jurídica? Se sim, indicar o dispositivo do código que atenda ao requisito. | B32: 299 | C32: FALSE | D32: FALSE | E32: FALSE | F32: FALSE | G32: TRUE | H32: TRUE | I32: 4 | J32: 5 | K32: TRUE | L32: FALSE | M32: FALSE | N32: Evidência que destaque a seção e a página do Código de Ética e Conduta ou documento equivalente onde a ética e/ou integridade são mencionadas expressamente como princípios ou valores da pessoa jurídica.
A33: 7.2.3 está alinhado com a legislação anticorrupção brasileira, contendo vedações expressas à prática de atos de corrupção e fraude e prevenção de conflito de interesses? Se sim, indicar o(s) dispositivo(s) do código que atenda(m) ao requisito. | B33: 299 | C33: FALSE | D33: FALSE | E33: FALSE | F33: TRUE | G33: TRUE | H33: TRUE | I33: 5 | J33: 5 | K33: TRUE | L33: FALSE | M33: FALSE | N33: Evidência que indique a seção e a página do Código de Ética e Conduta ou documento equivalente onde constam vedações expressas à prática de atos de corrupção e fraude e a prevenção de conflitos de interesses, alinhados com a legislação anticorrupção brasileira.
A34: 7.2.4 expressa o compromisso da pessoa jurídica em combater o preconceito, a discriminação e o assédio de qualquer natureza em suas relações internas e externas? Se sim, indicar o(s) dispositivo(s) do código que atenda(m) ao requisito. | B34: 299 | C34: FALSE | D34: FALSE | E34: FALSE | F34: TRUE | G34: TRUE | H34: TRUE | I34: 6 | J34: 5 | K34: TRUE | L34: FALSE | M34: FALSE | N34: Evidência que destaque a seção e a página do Código de Ética e Conduta ou documento equivalente onde a pessoa jurídica reafirma seu compromisso contra o preconceito, a discriminação e o assédio em todas as suas relações.
A35: 7.2.5 estabelece as condutas permitidas e proibidas na pessoa jurídica? Se sim, indicar o(s) dispositivo(s) do código que atenda(m) ao requisito. | B35: 299 | C35: FALSE | D35: FALSE | E35: FALSE | F35: FALSE | G35: TRUE | H35: TRUE | I35: 7 | J35: 5 | K35: TRUE | L35: FALSE | M35: FALSE | N35: Evidência que indique a seção e a página do Código de Ética e Conduta ou documento equivalente onde se estabelecem as condutas permitidas e proibidas dentro da pessoa jurídica.
A36: 7.2.6 menciona a possibilidade de aplicação de sanções para aqueles que cometerem violações éticas/legais, inclusive para os membros da alta direção da pessoa jurídica? Se sim, indicar o(s) dispositivo(s) do código que atenda(m) ao requisito. | B36: 299 | C36: FALSE | D36: FALSE | E36: FALSE | F36: TRUE | G36: TRUE | H36: TRUE | I36: 8 | J36: 5 | K36: TRUE | L36: FALSE | M36: FALSE | N36: Evidência que destaque a seção e a página do Código de Ética e Conduta ou documento equivalente que tratam das sanções aplicáveis a violações éticas ou legais, incluindo penalidades para membros da alta direção.
A37: 7.3 O código de ética e conduta, ou documento equivalente, encontra-se disponível na página institucional da pessoa jurídica na internet? Se sim, informar o link e descrever o caminho, desde a página inicial da entidade, para acesso ao documento. | B37: 299 | C37: FALSE | D37: FALSE | E37: FALSE | F37: FALSE | G37: TRUE | H37: TRUE | I37: 9 | J37: 18 | K37: TRUE | L37: FALSE | M37: FALSE | N37: Evidência que informe tanto o link de acesso quanto o caminho da página inicial do site da pessoa jurídica até o Código de Ética e Conduta ou documento equivalente.
A38: 7.4 A pessoa jurídica possui código de ética e conduta, ou documento equivalente, aplicável a terceiros e disponível em português? Se sim, informar o link e descrever o caminho, desde a página inicial da entidade para acesso ao documento. | B38: 299 | C38: FALSE | D38: FALSE | E38: FALSE | F38: FALSE | G38: TRUE | H38: TRUE | I38: 10 | J38: 5 | K38: TRUE | L38: FALSE | M38: FALSE | N38: Evidência baseada no Código de Ética e Conduta aplicável a terceiros, ou documento equivalente, em língua portuguesa. Caso seja parte do Código de Ética geral, este deve conter regras específicas para terceiros (disposições genéricas não serão aceitas).
A39: 7.5 A pessoa jurídica solicita aos terceiros que declarem expressamente que estão cientes da existência e do conteúdo do código, e que se comprometem a observar os termos e condições nele previstos? Se sim, anexar documentos que comprovem o comprometimento de terceiros e informar como e em que momento isso ocorre. | B39: 299 | C39: FALSE | D39: FALSE | E39: FALSE | F39: FALSE | G39: TRUE | H39: TRUE | I39: 11 | J39: 18 | K39: TRUE | L39: FALSE | M39: FALSE | N39: Evidências como termos de ciência, contratos ou declarações assinadas por terceiros, confirmando a ciência e o compromisso com o Código de Ética e Conduta ou documento equivalente, incluindo atualizações.
A40: 8.1 A pessoa jurídica possui políticas e procedimentos de integridade que: | B40: 301 | C40: TRUE | D40: FALSE | E40: FALSE | F40: FALSE | G40: FALSE | H40: TRUE | I40: 1 | J40: 0 | K40: FALSE | L40: FALSE | M40: FALSE
A41: 8.1.1 vedam expressamente a concessão de vantagens indevidas, econômicas ou não, a agentes públicos? Se sim, anexar a política ou procedimento e indicar o(s) dispositivo(s) do documento que atenda(m) ao requisito. | B41: 301 | C41: FALSE | D41: FALSE | E41: FALSE | F41: FALSE | G41: TRUE | H41: TRUE | I41: 2 | J41: 20 | K41: TRUE | L41: TRUE | M41: FALSE | N41: Evidência que indique a seção e a página de políticas, regras, orientações e/ou procedimentos que vedem expressamente a concessão de vantagens indevidas, econômicas ou não, a agentes públicos.
A42: 8.1.2 tratam do oferecimento de presentes, brindes e hospitalidades (refeições, entretenimento, viagem e hospedagem) a agentes públicos? Se sim, anexar a política ou procedimento e indicar o(s) dispositivo(s) do documento que atenda(m) ao requisito. | B42: 301 | C42: FALSE | D42: FALSE | E42: FALSE | F42: FALSE | G42: TRUE | H42: TRUE | I42: 3 | J42: 5 | K42: TRUE | L42: FALSE | M42: FALSE | N42: Evidência que indique a seção e a página das políticas, regras, orientações ou procedimentos que regulem o oferecimento de presentes, brindes e hospitalidades (como refeições, entretenimento, viagens e hospedagem) a agentes públicos.
A43: 8.1.3 tratam da prevenção de conflito de interesses nas relações com a Administração Pública, incluindo contratações de agentes públicos e seus familiares? Se sim, anexar a política ou procedimento e indicar o(s) dispositivo(s) do documento que atenda(m) ao requisito. | B43: 301 | C43: FALSE | D43: FALSE | E43: FALSE | F43: TRUE | G43: TRUE | H43: TRUE | I43: 4 | J43: 5 | K43: TRUE | L43: FALSE | M43: FALSE | N43: Evidência que indique a seção e a página das políticas, regras, orientações ou procedimentos que tratem da prevenção de conflitos de interesse nas relações com a Administração Pública, incluindo contratações de agentes públicos e seus familiares.
A44: 8.1.4 estabelecem orientações e controles sobre temas como realização de reuniões, encontros e outros tipos de interações entre administradores e empregados da pessoa jurídica com agentes públicos? Se sim, anexar a política ou procedimento e indicar o(s) dispositivo(s) do documento que atenda(m) ao requisito. | B44: 301 | C44: FALSE | D44: FALSE | E44: FALSE | F44: TRUE | G44: TRUE | H44: TRUE | I44: 5 | J44: 5 | K44: TRUE | L44: FALSE | M44: FALSE | N44: Evidência que indique a seção e a página das políticas, regras, orientações ou procedimentos que definam diretrizes e controles sobre reuniões, encontros e outras interações entre administradores ou empregados da pessoa jurídica e agentes públicos.
A45: 8.1.5 tratam da realização de doação e patrocínio, ou informam claramente que a pessoa jurídica não realiza essas atividades? Se sim, anexar política/procedimento de integridade. Indicar, no campo correspondente, o artigo, item e/ou página em que há essa previsão. | B45: 301 | C45: FALSE | D45: FALSE | E45: FALSE | F45: FALSE | G45: TRUE | H45: TRUE | I45: 6 | J45: 5 | K45: TRUE | L45: FALSE | M45: FALSE | N45: Evidência que indique a seção e a página das políticas, regras, orientações ou procedimentos que abordem a realização de doações e patrocínios, ou que deixem claro que a pessoa jurídica não realiza essas atividades.
A46: 8.2 As políticas e procedimentos de integridade relacionados às interações com a Administração Pública foram aplicadas periodicamente pela pessoa jurídica nos últimos 12 meses? Se sim, descrever as ocasiões e a forma como as políticas e procedimentos foram aplicados, anexando a documentação comprobatória pertinente. | B46: 301 | C46: FALSE | D46: FALSE | E46: FALSE | F46: TRUE | G46: TRUE | H46: TRUE | I46: 7 | J46: 25 | K46: TRUE | L46: FALSE | M46: FALSE | N46: Evidências como relatórios, atas de reuniões, e-mails, due diligence, medidas disciplinares aplicadas a empregados, contratos rescindidos e/ou multas aplicadas a terceiros, monitoramento dos canais de denúncias etc.
A47: 9.1. A pessoa jurídica possui políticas ou procedimentos específicos para prevenção de ilícitos em licitações e contratos administrativos? Se sim, anexar a política ou procedimentos que atenda(m) ao requisito. | B47: 300 | C47: FALSE | D47: FALSE | E47: FALSE | F47: FALSE | G47: TRUE | H47: TRUE | I47: 1 | J47: 20 | K47: TRUE | L47: TRUE | M47: FALSE | N47: Evidência que indique a seção e a página das políticas, regras, orientações ou procedimentos para prevenção de ilícitos em licitações e contratos administrativos.
A48: 9.2 As política ou procedimentos: | B48: 300 | C48: TRUE | D48: FALSE | E48: FALSE | F48: FALSE | G48: FALSE | H48: TRUE | I48: 2 | J48: 0 | K48: FALSE | L48: FALSE | M48: FALSE
A49: 9.2.1 estabelecem orientações sobre a conduta esperada (o que é permitido/proibido) para seus empregados e para terceiros que atuam em seu nome? Se sim, indicar o(s) dispositivo(s) da política ou procedimentos que atenda(m) ao requisito. | B49: 300 | C49: FALSE | D49: FALSE | E49: FALSE | F49: TRUE | G49: TRUE | H49: TRUE | I49: 3 | J49: 5 | K49: TRUE | L49: FALSE | M49: FALSE | N49: Evidência que indique a seção e a página das políticas, regras, orientações ou procedimentos que estabeleçam diretrizes claras sobre a conduta esperada dos empregados e terceiros, especificando ações permitidas e proibidas.
A50: 9.2.2 indicam expressamente os responsáveis por autorizar a adoção de medidas relacionadas à participação em licitações, bem como pela interação com os agentes públicos para tratar de questões relacionadas à gestão do contrato, como pagamento, alterações contratuais, aditivos e prorrogações? Se sim, indicar o(s) dispositivo(s) da política ou procedimentos que atenda(m) ao requisito. | B50: 300 | C50: FALSE | D50: FALSE | E50: FALSE | F50: TRUE | G50: TRUE | H50: TRUE | I50: 4 | J50: 5 | K50: TRUE | L50: FALSE | M50: FALSE | N50: Evidência que indique a seção e a página das políticas, regras, orientações ou procedimentos que indiquem expressamente os responsáveis pela autorização de medidas vinculadas à participação da pessoa jurídica em licitações e à gestão do contrato.
A51: 9.2.3 definem a necessidade de rotação periódica dos responsáveis por interagir com os agentes públicos em licitações e contratos administrativos? Se sim, indicar o(s) dispositivo(s) da política ou procedimentos que atenda(m) ao requisito. | B51: 300 | C51: FALSE | D51: FALSE | E51: FALSE | F51: FALSE | G51: TRUE | H51: TRUE | I51: 5 | J51: 5 | K51: TRUE | L51: FALSE | M51: FALSE | N51: Evidência que indique a seção e a página das políticas, regras, orientações ou procedimentos que estabeleçam a alternância dos responsáveis pela comunicação com agentes públicos nas licitações e na execução do contrato, considerando seu prazo de vigência.
A52: 9.2.4 orientam a relação da pessoa jurídica com seus concorrentes, a fim de evitar práticas anticoncorrenciais que possibilitem fraude em processos licitatórios? Se sim, indicar o(s) dispositivo(s) da política ou procedimentos que atenda(m) ao requisito. | B52: 300 | C52: FALSE | D52: FALSE | E52: FALSE | F52: FALSE | G52: TRUE | H52: TRUE | I52: 6 | J52: 5 | K52: TRUE | L52: FALSE | M52: FALSE | N52: Evidência que indique a seção e a página das políticas, regras, orientações ou procedimentos que estabeleçam diretrizes para a relação da pessoa jurídica com concorrentes, prevenindo práticas anticoncorrenciais e coibindo fraudes em processos licitatórios.
A53: 9.3 A pessoa jurídica aplicou, nos últimos 12 meses, as orientações e controles específicos para prevenção de fraudes e ilícitos em licitações e contratos administrativos? Se sim, descrever as ocasiões e a forma como as orientações e controles foram aplicados. | B53: 300 | C53: FALSE | D53: FALSE | E53: FALSE | F53: TRUE | G53: TRUE | H53: TRUE | I53: 7 | J53: 25 | K53: TRUE | L53: FALSE | M53: FALSE | N53: Exemplos de processos reais contendo: matriz de riscos, atas de reuniões, aprovações, e-mails e documentos da alta direção, que comprovem a aplicação das políticas de prevenção a ilícitos em licitações e contratos administrativos, incluindo ações implementadas e resultados para empregados e terceiros.
A54: 10.1 A pessoa jurídica possui um planejamento para a realização de treinamentos sobre integridade com definição do cronograma, temas, públicos-alvo, responsáveis e forma de execução? Se sim, anexar o documento ou informações que demonstrem o planejamento vigente. | B54: 302 | C54: FALSE | D54: FALSE | E54: FALSE | F54: FALSE | G54: TRUE | H54: TRUE | I54: 1 | J54: 20 | K54: TRUE | L54: TRUE | M54: FALSE | N54: Evidência que apresente o planejamento periódico das capacitações em integridade, especificando cronograma, temas, públicos-alvo, responsáveis e forma de execução.
A55: 10.2 A pessoa jurídica realizou, nos últimos 12 meses, treinamento(s) direcionado(s) a todos os seus colaboradores, abordando conteúdo de integridade, como aqueles relacionados ao código de ética, canais de denúncia ou políticas anticorrupção? Se sim, anexar documentos e/ou indicar, no campo correspondente, link em que seja possível visualizar os treinamentos realizados e descrever as ocasiões, temas, carga horária e público alcançado. | B55: 302 | C55: FALSE | D55: FALSE | E55: FALSE | F55: TRUE | G55: TRUE | H55: TRUE | I55: 2 | J55: 25 | K55: TRUE | L55: FALSE | M55: FALSE | N55: Evidências como listas de presença, materiais de estudo, links de treinamentos online ou registros de frequência que demonstrem a participação dos colaboradores em capacitações sobre o código de ética, canais de denúncia, política anticorrupção etc.
A56: 10.3 A pessoa jurídica realizou, nos últimos 12 meses, treinamento(s) direcionado(s) a públicos específicos, abordando conteúdo alinhado aos principais riscos daqueles públicos, como prevenção de fraudes e ilícitos em licitações e contratos administrativos, controles contábeis e financeiros, realização de diligências para contratação e supervisão de terceiros? Se sim, anexar documentos e/ou indicar, no campo correspondente, link em que seja possível visualizar os treinamentos realizados e descrever as ocasiões, temas, carga horária e público alcançado. | B56: 302 | C56: FALSE | D56: FALSE | E56: FALSE | F56: TRUE | G56: TRUE | H56: TRUE | I56: 3 | J56: 18 | K56: TRUE | L56: FALSE | M56: FALSE | N56: Evidências como listas de presença, materiais de estudo ou registros de frequência, que demonstrem treinamento direcionado a públicos expostos a riscos específicos, com temas relevantes para cada área, como licitações, controles financeiros e diligências em contratações etc.
A57: 10.4 Os treinamentos relacionados ao programa de integridade realizados pela pessoa jurídica nos últimos 12 meses atingiram, em média, 70% de cada um dos públicos-alvo? Se sim, anexar documentos ou informações que demonstrem o cumprimento do requisito. | B57: 302 | C57: FALSE | D57: FALSE | E57: FALSE | F57: FALSE | G57: TRUE | H57: TRUE | I57: 4 | J57: 5 | K57: TRUE | L57: FALSE | M57: FALSE | N57: Evidências documentais, como relatórios ou históricos de treinamentos contendo dados estatísticos ou percentuais de participação, acompanhados de listas de presença para comprovação.
A58: 11.1 A pessoa jurídica possui um planejamento para a realização de ações recorrentes de comunicação sobre integridade, com definição do cronograma, temas, responsáveis, públicos-alvo e meios de divulgação? Se sim, anexar o documento ou informações que demonstrem o planejamento vigente. | B58: 303 | C58: FALSE | D58: FALSE | E58: FALSE | F58: FALSE | G58: TRUE | H58: TRUE | I58: 1 | J58: 20 | K58: TRUE | L58: TRUE | M58: FALSE | N58: Evidências documentais que estabeleçam o planejamento das ações de comunicação sobre integridade para o período avaliado, detalhando cronograma, temas, responsáveis, públicos-alvo e meios de divulgação.
A59: 11.2 A pessoa jurídica promoveu, nos últimos 12 meses, ações de comunicação voltadas à divulgação dos aspectos gerais do programa de integridade, como código de ética e de conduta, política anticorrupção e canais de denúncia? Se sim, anexar documentos e/ou indicar, no campo correspondente, link em que seja possível visualizar as comunicações realizadas no período. | B59: 303 | C59: FALSE | D59: FALSE | E59: FALSE | F59: TRUE | G59: TRUE | H59: TRUE | I59: 2 | J59: 25 | K59: TRUE | L59: FALSE | M59: FALSE | N59: Evidências de comunicações internas destinadas à divulgação do Código de Ética, da política anticorrupção e canais de denúncia, por meio de e-mails, vídeos, cartazes, folders, registros de páginas da intranet etc, assegurando a identificação dos destinatários.
A60: 11.2.1 As ações de comunicação realizadas pela empresa no período avaliado foram feitas de forma periódica e contínua? Se sim, anexar documentos e/ou indicar, no campo correspondente, informações que demonstrem a realização de comunicações de forma periódica e contínua sobre integridade. | B60: 303 | C60: FALSE | D60: FALSE | E60: FALSE | F60: FALSE | G60: TRUE | H60: TRUE | I60: 3 | J60: 5 | K60: TRUE | L60: FALSE | M60: FALSE | N60: Evidências de que as comunicações foram contínuas e frequentes, reforçando a cultura de integridade, adaptando-se ao mercado e à legislação anticorrupção, e não se limitando a ações sazonais.
... A69: 13.5 As recomendações ou apontamentos emitidos pela função de auditoria interna são adequada e tempestivamente implementadas pela pessoa jurídica? Se sim, anexar documentos que demonstrem a adequada e tempestiva implementação das recomendações emitidas pela função de auditoria interna. | B69: 304 | C69: FALSE | D69: TRUE | E69: TRUE | F69: TRUE | G69: TRUE | H69: TRUE | I69: 5 | J69: 18 | K69: TRUE | L69: FALSE | M69: FALSE | N69: Evidências de tratamento das recomendações ou apontamentos emitidos pela função de auditoria interna, em que se constate, entre outros, o seu tempo médio de correção (print de sistemas, apresentações da área de auditoria interna, relatórios, atas de reuniões, plano de ação etc).
A70: 14.1 A pessoa jurídica possui políticas e procedimentos baseadas em risco para a realização de diligências, contratação e supervisão de terceiros, que: | B70: 307 | C70: TRUE | D70: FALSE | E70: FALSE | F70: FALSE | G70: FALSE | H70: TRUE | I70: 1 | J70: 0 | K70: FALSE | L70: FALSE | M70: FALSE
A71: 14.1.1 determinam a verificação de possível envolvimento do terceiro em casos de corrupção e práticas de fraude contra a Administração Pública? Se sim, anexar as políticas e/ou procedimentos, indicando o artigo, item e/ou página onde consta essa previsão. | B71: 307 | C71: FALSE | D71: FALSE | E71: FALSE | F71: FALSE | G71: TRUE | H71: TRUE | I71: 2 | J71: 20 | K71: TRUE | L71: TRUE | M71: FALSE | N71: Evidências de normas para identificar histórico de envolvimento em atos de corrupção ou fraude contra a Administração Pública, tanto por parte de pessoa jurídica terceira quanto de seus sócios.
A72: 14.1.2 determinam a verificação da existência de registro do terceiro em “listas sujas” de trabalho escravo ou em condições análogas às de escravo? Se sim, anexar as políticas e/ou procedimentos, indicando o artigo, item e/ou página onde consta essa previsão. | B72: 307 | C72: FALSE | D72: FALSE | E72: FALSE | F72: FALSE | G72: TRUE | H72: TRUE | I72: 3 | J72: 5 | K72: TRUE | L72: FALSE | M72: FALSE | N72: Evidências de normas para identificar histórico de registro em “listas sujas” de trabalho escravo ou em condições análogas às de escravo, tanto por parte de empresa terceira quanto de seus sócios.
A73: 14.1.3 determinam a verificação de possível envolvimento do terceiro em crimes ambientais ou em práticas nocivas ao meio ambiente? Se sim, anexar as políticas e/ou procedimentos, indicando o artigo, item e/ou página onde consta essa previsão. | B73: 307 | C73: FALSE | D73: TRUE | E73: TRUE | F73: FALSE | G73: TRUE | H73: TRUE | I73: 4 | J73: 5 | K73: TRUE | L73: FALSE | M73: FALSE | N73: Evidências de normas para identificar histórico de envolvimento em crimes ambientais ou práticas nocivas ao meio ambiente, tanto por parte de empresa terceira quanto de seus sócios.
A74: 14.1.4 estabelecem a necessidade de adoção de medidas para minimizar o risco da contratação de terceiro, caso o resultado das diligências realizadas indique alto risco de integridade na contratação? Se sim, anexar as políticas e/ou procedimentos, indicando o artigo, item e/ou página onde consta essa previsão. | B74: 307 | C74: FALSE | D74: FALSE | E74: FALSE | F74: FALSE | G74: TRUE | H74: TRUE | I74: 5 | J74: 5 | K74: TRUE | L74: FALSE | M74: FALSE | N74: Evidências de normas definindo medidas de mitigação a serem aplicadas no caso de contração de terceiros de alto risco.
A75: 14.2 A pessoa jurídica realizou diligências de integridade em relação aos terceiros com os quais estabeleceu relações negociais nos últimos 12 meses? Se sim, anexar documentos que comprovem a realização das diligências e as deliberações realizadas com base nos resultados das diligências. | B75: 307 | C75: FALSE | D75: FALSE | E75: FALSE | F75: FALSE | G75: TRUE | H75: TRUE | I75: 6 | J75: 18 | K75: TRUE | L75: FALSE | M75: FALSE | N75: Exemplos de resultados de diligências na qual a pessoa jurídica demonstre que aplicou seus procedimentos de avaliação de parceiros de negócios, e o fluxo de deliberação sobre a contratação.
A76: 15.1 As políticas e procedimentos sobre contratação de terceiros estabeleçam a inclusão de cláusulas, nos contratos relevantes celebrados com terceiros, que: | B76: 306 | C76: TRUE | D76: FALSE | E76: FALSE | F76: FALSE | G76: FALSE | H76: TRUE | I76: 1 | J76: 0 | K76: FALSE | L76: FALSE | M76: FALSE
A77: 15.1.1 estabelecem a vedação de práticas de fraude e corrupção e exigem a observância do cumprimento de normas éticas, trabalhistas e sociais? Se sim, anexar as políticas e/ou procedimentos, indicando o artigo, item e/ou página onde consta essa previsão. | B77: 306 | C77: FALSE | D77: FALSE | E77: FALSE | F77: FALSE | G77: TRUE | H77: TRUE | I77: 2 | J77: 5 | K77: TRUE | L77: FALSE | M77: FALSE | N77: Evidências de normas que exijam a utilização de cláusula anticorrupção e de cumprimento de normas éticas, trabalhistas e sociais nos contratos celebrados com terceiros.
A78: 15.1.2 preveem a aplicação de penalidades e/ou de rescisão contratual em caso de descumprimento de normas éticas e prática de fraude e corrupção? Se sim, anexar as políticas e/ou procedimentos, indicando o artigo, item e/ou página onde consta essa previsão. | B78: 306 | C78: FALSE | D78: FALSE | E78: FALSE | F78: FALSE | G78: TRUE | H78: TRUE | I78: 3 | J78: 5 | K78: TRUE | L78: FALSE | M78: FALSE | N78: Evidências de normas que prevejam as penalidades ou rescisão do contrato por práticas de corrupção e descumprimento de normas normas éticas, trabalhistas e sociais, segundo a legislação vigente.
A79: 15.2 A pessoa jurídica incluiu cláusulas, nos contratos relevantes celebrados com terceiros nos últimos 12 meses, que contemplem as medidas estabelecidas nas políticas e procedimentos anteriormente descritos? Se sim, anexar cópias de contratos celebrados nos últimos 12 meses, referenciando as cláusulas que contenham as previsões definidas nas políticas ou procedimentos. | B79: 306 | C79: FALSE | D79: FALSE | E79: FALSE | F79: TRUE | G79: TRUE | H79: TRUE | I79: 4 | J79: 18 | K79: TRUE | L79: FALSE | M79: FALSE | N79: Exemplos de contratos ou de trechos de contratos reais, que contemplem as medidas estabelecidas nas políticas e procedimentos anteriormente descritos, e que permitam identificar a pessoa jurídica como parte.
A80: 16.1 A pessoa jurídica possui políticas e procedimentos específicos para a realização de fusões, aquisições ou outras operações societárias que preveem a realização de diligências para verificar o histórico de prática de atos de corrupção, fraude ou violação de direitos humanos ou trabalhistas das empresas envolvidas nas operações? Se sim, anexar as políticas e/ou procedimentos, indicando o artigo, item e/ou página onde consta essa previsão. | B80: 308 | C80: FALSE | D80: TRUE | E80: TRUE | F80: TRUE | G80: TRUE | H80: TRUE | I80: 1 | J80: 15 | K80: TRUE | L80: FALSE | M80: FALSE | N80: Evidências de normas que prevejam a verificação do histórico de envolvimento das empresas envolvidas nas operações societárias corrupção, fraude ou violação de direitos humanos ou trabalhistas.
A81: 16.2 A pessoa jurídica realizou diligências prévias a fusões, aquisições e outras operações societárias nos últimos 24 meses? Se sim, anexar documentos que comprovem a aplicação das políticas/procedimentos. | B81: 308 | C81: FALSE | D81: TRUE | E81: TRUE | F81: TRUE | G81: TRUE | H81: TRUE | I81: 2 | J81: 18 | K81: FALSE | L81: FALSE | M81: FALSE | N81: Exemplos de relatórios, pareceres, comunicações internas, auditorias específicas etc, que comprovem as diligências para verificar o histórico de prática de atos de corrupção, fraude ou violação de direitos humanos ou trabalhistas nas empresas envolvidas.
A82: 17.1 A pessoa jurídica possui canal para realização de denúncias, disponível em português e informado na página institucional da empresa na internet? Se sim, informar o link e descrever o caminho, desde a página inicial da empresa, e eventuais outras formas de acesso ao canal. | B82: 310 | C82: FALSE | D82: FALSE | E82: FALSE | F82: FALSE | G82: TRUE | H82: TRUE | I82: 1 | J82: 20 | K82: TRUE | L82: TRUE | M82: FALSE | N82: Evidências da existência de canais de denúncias, com link direto para a área do site e o caminho de navegação a partir da página inicial ou telefone, em português.
A83: 17.2 O canal de denúncias da pessoa jurídica: | B83: 310 | C83: TRUE | D83: FALSE | E83: FALSE | F83: FALSE | G83: FALSE | H83: TRUE | I83: 2 | J83: 0 | K83: FALSE | L83: FALSE | M83: FALSE
A84: 17.2.1 é operacionalizado por meio de formulário eletrônico a partir da página institucional da pessoa jurídica na internet? Se sim, informar o link e descrever o caminho, desde a página inicial da empresa, para acesso ao canal. | B84: 310 | C84: FALSE | D84: FALSE | E84: FALSE | F84: FALSE | G84: TRUE | H84: TRUE | I84: 3 | J84: 5 | K84: TRUE | L84: FALSE | M84: FALSE | N84: Evidências da existência de canais de denúncias, operacionalizado por meio de formulário eletrônico, com link direto para a área do site e o caminho de navegação a partir da página inicial.
A85: 17.2.2 oferece expressamente garantias de proteção aos denunciantes de boa-fé, como anonimato e não retaliação? Se sim, anexar documentos que comprovem essa informação. | B85: 310 | C85: FALSE | D85: FALSE | E85: FALSE | F85: FALSE | G85: TRUE | H85: TRUE | I85: 4 | J85: 5 | K85: TRUE | L85: FALSE | M85: FALSE | N85: Indicações expressas, no próprio Canal, sobre as garantias de proteção oferecidas aos denunciantes de boa-fé.
A86: 17.2.3 permite o acompanhamento da apuração da denúncia pelo denunciante? Se sim, anexar documentos que comprovem essa informação. | B86: 310 | C86: FALSE | D86: FALSE | E86: FALSE | F86: FALSE | G86: TRUE | H86: TRUE | I86: 5 | J86: 5 | K86: TRUE | L86: FALSE | M86: FALSE | N86: Evidências da possibilidade de acompanhamento da apuração da denúncia pelo denunciante, inclusive com a disponibilização, no próprio canal, de campo específico para esse fim, tais como protocolo etc.
A87: 17.3 O canal de denúncias funcionou quando testado pelo avaliador? | B87: 310 | C87: FALSE | D87: FALSE | E87: FALSE | F87: FALSE | G87: TRUE | H87: FALSE | I87: 6 | J87: 25 | K87: FALSE | L87: FALSE | M87: FALSE
A88: 18.1 A pessoa jurídica possui políticas e procedimentos que estabelecem o fluxo e as responsabilidades quanto ao tratamento, apuração e remediação de casos de fraudes, corrupção ou violação de direitos humanos e trabalhistas? Se sim, anexar a política ou procedimentos e indicar o(s) dispositivo(s) do documento que atenda(m) ao requisito. | B88: 311 | C88: FALSE | D88: FALSE | E88: FALSE | F88: TRUE | G88: TRUE | H88: TRUE | I88: 1 | J88: 15 | K88: TRUE | L88: FALSE | M88: FALSE | N88: Evidências de normas que estabeleçam o fluxo de tratamento e apuração das denúncias, bem como ações de remediação para casos de fraudes, corrupção ou violação de direitos humanos e trabalhistas.
A89: 18.2 As políticas e procedimentos definem: | B89: 311 | C89: TRUE | D89: FALSE | E89: FALSE | F89: FALSE | G89: FALSE | H89: TRUE | I89: 2 | J89: 0 | K89: FALSE | L89: FALSE | M89: FALSE
A90: 18.2.1 salvaguardas e prerrogativas de acesso a documentos, sistemas e pessoas por parte dos responsáveis pela apuração? Se sim, anexar a política ou procedimentos e indicar o(s) dispositivo(s) do documento que atenda(m) ao requisito. | B90: 311 | C90: FALSE | D90: FALSE | E90: FALSE | F90: TRUE | G90: TRUE | H90: TRUE | I90: 3 | J90: 5 | K90: TRUE | L90: FALSE | M90: FALSE | N90: Evidências de normas que assegurem fluxo específico de apuração das denúncias no caso de envolvimento de membros da alta administração.
A91: 18.2.2 fluxo específico para apuração de denúncias envolvendo membros da alta direção? Se sim, anexar a política ou procedimentos e indicar o(s) dispositivo(s) do documento que atenda(m) ao requisito. | B91: 311 | C91: FALSE | D91: FALSE | E91: FALSE | F91: FALSE | G91: TRUE | H91: TRUE | I91: 4 | J91: 5 | K91: TRUE | L91: FALSE | M91: FALSE | N91: Evidências de normas que assegurem fluxo específico de apuração das denúncias no caso de envolvimento de membros da alta administração.
A92: 18.3 A pessoa jurídica realizou o tratamento das denúncias recebidas nos últimos 24 meses? Se sim, anexar documentos que demonstrem o tratamento do universo de denúncias recebidas no período. | B92: 311 | C92: FALSE | D92: TRUE | E92: TRUE | F92: FALSE | G92: TRUE | H92: TRUE | I92: 5 | J92: 18 | K92: TRUE | L92: FALSE | M92: FALSE | N92: Evidências de dados e estatísticas sobre denúncias registradas e exemplos de documentos reais de apurações e seus desdobramentos (relatórios, atas de reuniões, dashboards etc)
A93: 19.1 As políticas e procedimentos relacionadas ao tratamento, apuração e remediação de casos de fraudes, corrupção ou violação de direitos humanos e trabalhistas definem: | B93: 309 | C93: TRUE | D93: FALSE | E93: FALSE | F93: FALSE | G93: FALSE | H93: TRUE | I93: 1 | J93: 0 | K93: FALSE | L93: FALSE | M93: FALSE
A94: 19.1.1 as medidas disciplinares aplicáveis aos casos de infrações relacionadas a fraudes, corrupção ou violação de direitos humanos e trabalhistas? Se sim, anexar a política ou procedimentos e indicar o(s) dispositivo(s) do documento que atenda(m) ao requisito. | B94: 309 | C94: FALSE | D94: FALSE | E94: FALSE | F94: FALSE | G94: TRUE | H94: TRUE | I94: 2 | J94: 5 | K94: TRUE | L94: FALSE | M94: FALSE | N94: Evidências de normas que indiquem as medidas disciplinares aplicáveis.
A95: 19.1.2 a correlação entre as medidas disciplinares e os tipos de infração cometidas e as alçadas para sua aplicação? Se sim, anexar a política ou procedimentos e indicar o(s) dispositivo(s) do documento que atenda(m) ao requisito. | B95: 309 | C95: FALSE | D95: FALSE | E95: FALSE | F95: FALSE | G95: TRUE | H95: TRUE | I95: 3 | J95: 5 | K95: TRUE | L95: FALSE | M95: FALSE | N95: Evidências de normas que correlacionem as infrações das normas da pessoa jurídica às medidas disciplinares previstas.
A96: 19.1.3 a pronta interrupção de irregularidades, inclusive com a possibilidade de afastamento cautelar de membros da alta direção suspeitos de envolvimento em atos de corrupção e fraude? Se sim, anexar a política ou procedimentos e indicar o(s) dispositivo(s) do documento que atenda(m) ao requisito. | B96: 309 | C96: FALSE | D96: FALSE | E96: FALSE | F96: FALSE | G96: TRUE | H96: TRUE | I96: 4 | J96: 5 | K96: TRUE | L96: FALSE | M96: FALSE | N96: Evidências de normas que visem garantir a aplicação de medidas cautelares para pronta interrupção de irregularidades, incluindo o afastamento de membros da alta administração suspeitos de envolvimento em atos de corrupção ou fraude.
A97: 19.1.4 os procedimentos aplicáveis para encaminhamento de denúncias às autoridades competentes? Se sim, anexar a política ou procedimentos e indicar o(s) dispositivo(s) do documento que atenda(m) ao requisito. | B97: 309 | C97: FALSE | D97: FALSE | E97: FALSE | F97: FALSE | G97: TRUE | H97: TRUE | I97: 5 | J97: 5 | K97: TRUE | L97: FALSE | M97: FALSE | N97: Evidências de normas que orientem a decisão sobre quando e como deve ser feito o encaminhamento às autoridades competentes de denúncias de irregularidades envolvendo funcionários, dirigentes, intermediários, fornecedores e prestadores de serviço.
A98: 19.2 A pessoa jurídica aplicou procedimentos para interrupção de irregularidades, remediação e aplicação de medidas disciplinares nos últimos 24 meses? Se sim, anexar a política ou procedimentos e indicar o(s) dispositivo(s) do documento que atenda(m) ao requisito. | B98: 309 | C98: FALSE | D98: TRUE | E98: TRUE | F98: FALSE | G98: TRUE | H98: TRUE | I98: 6 | J98: 18 | K98: TRUE | L98: FALSE | M98: FALSE | N98: Exemplos de processos reais de apuração de denúncia e/ou de remediação de infração às normas da pessoa jurídica, preservando as informações sensíveis, mas de forma que permita a avaliação quanto aos procedimentos adotados, ou dashboards, relatórios, atas de reunião, relacionados a medidas disciplinares.
A99: 20.1 A pessoa jurídica possui política ou procedimentos que estabelecem o monitoramento contínuo do programa de integridade? Se sim, anexar a política ou procedimentos e indicar o(s) dispositivo(s) do documento que atenda(m) ao requisito. | B99: 319 | C99: FALSE | D99: FALSE | E99: FALSE | F99: FALSE | G99: TRUE | H99: TRUE | I99: 1 | J99: 20 | K99: TRUE | L99: TRUE | M99: FALSE | N99: Evidências de normas internas que estabeleçam regras para o monitoramento do programa de integridade.
A100: 20.2 A política ou procedimentos que estabelecem o monitoramento contínuo do programa de integridade definem: | B100: 319 | C100: TRUE | D100: FALSE | E100: FALSE | F100: FALSE | G100: FALSE | H100: TRUE | I100: 2 | J100: 0 | K100: FALSE | L100: FALSE | M100: FALSE
A101: 20.2.1 os responsáveis pelo monitoramento? Se sim, anexar a política ou procedimentos e indicar o(s) dispositivo(s) do documento que atenda(m) ao requisito. | B101: 319 | C101: FALSE | D101: FALSE | E101: FALSE | F101: FALSE | G101: TRUE | H101: TRUE | I101: 3 | J101: 5 | K101: TRUE | L101: FALSE | M101: FALSE | N101: Evidências de normas internas que definam os responsáveis pelo monitoramento do programa de integridade.
A102: 20.2.2 a periodicidade para realização do monitoramento? Se sim, anexar a política ou procedimentos e indicar o(s) dispositivo(s) do documento que atenda(m) ao requisito. | B102: 319 | C102: FALSE | D102: FALSE | E102: FALSE | F102: FALSE | G102: TRUE | H102: TRUE | I102: 4 | J102: 5 | K102: FALSE | L102: FALSE | M102: FALSE | N102: Evidências de normas internas que definam a periodicidade de monitoramento do programa de integridade.
A103: 20.2.3 as instâncias para as quais serão submetidos os dados e as informações apurados no monitoramento? Se sim, anexar a política ou procedimentos e indicar o(s) dispositivo(s) do documento que atenda(m) ao requisito. | B103: 319 | C103: FALSE | D103: FALSE | E103: FALSE | F103: FALSE | G103: TRUE | H103: TRUE | I103: 5 | J103: 5 | K103: TRUE | L103: FALSE | M103: FALSE | N103: Evidências de normas internas que definam as instâncias para as quais os dados e as informações de monitoramento serão submetidos.
A104: 20.3 A pessoa jurídica realiza um monitoramento contínuo do programa de integridade por meio de: | B104: 319 | C104: TRUE | D104: FALSE | E104: FALSE | F104: FALSE | G104: FALSE | H104: TRUE | I104: 6 | J104: 0 | K104: FALSE | L104: FALSE | M104: FALSE
A105: 20.3.1 utilização de indicadores e estabelecimento de metas de desempenho sobre o programa de integridade, visando avaliar sua efetividade e cumprimento? Se sim, anexar documentos que comprovem a existência das metas e a utilização dos indicadores. | B105: 319 | C105: FALSE | D105: FALSE | E105: FALSE | F105: FALSE | G105: TRUE | H105: TRUE | I105: 7 | J105: 15 | K105: TRUE | L105: FALSE | M105: FALSE | N105: Evidências em documentos, relatórios, dashboards ou apresentações, contendo os indicadores utilizados e as metas de desempenho definidas, evidenciando-se os resultados alcançados em cada período etc.
A106: 20.3.2 relatórios periódicos com dados e estatísticas sobre aplicação das principais políticas e procedimentos de integridade? Se sim, informar os tipos de relatórios produzidos, o conteúdo neles abordado e os sistemas/softwares eventualmente utilizados. | B106: 319 | C106: FALSE | D106: FALSE | E106: FALSE | F106: FALSE | G106: TRUE | H106: TRUE | I106: 8 | J106: 15 | K106: TRUE | L106: FALSE | M106: FALSE | N106: Evidências da regularidade do monitoramento, como relatórios, registros históricos, prints de tela, dashboards, apresentações realizadas, atas de reuniões etc.
A107: 20.4 A pessoa jurídica utiliza as informações obtidas a partir do monitoramento para aprimorar seu programa de integridade e demais políticas, procedimentos e controles? Se sim, anexar documentos que comprovem a adoção de medidas de aprimoramento que sejam baseadas nas informações obtidas no monitoramento. | B107: 319 | C107: FALSE | D107: TRUE | E107: TRUE | F107: FALSE | G107: TRUE | H107: TRUE | I107: 9 | J107: 18 | K107: TRUE | L107: FALSE | M107: FALSE | N107: Evidências do aperfeiçoamento do programa de integridade realizadas a partir do monitoramento, como pesquisas internas, relatórios, atas de reuniões e estudos que embasaram as ações e melhorias implementadas.
A108: 21.1 A pessoa jurídica possui política ou procedimentos formais sobre questões ambientais, como gestão de resíduos, consumo de recursos naturais, emissão de poluentes e medidas de mitigação de impactos? Se sim, anexar a política ou procedimentos e indicar o(s) dispositivo(s) do documento que atenda(m) ao requisito. | B108: 320 | C108: FALSE | D108: TRUE | E108: TRUE | F108: TRUE | G108: TRUE | H108: TRUE | I108: 1 | J108: 5 | K108: TRUE | L108: FALSE | M108: FALSE | N108: Evidências de documentos formais, aprovados alta direção, que estabeleçam regras para gestão de resíduos, consumo de recursos naturais, emissão de poluentes e medidas de mitigação de impactos etc.
...

Sheet Checklist SAMPI
C1: Check | H1: CONF | L1: CONF | P1: CONF | Y1: SAMPI | Z1: FORM | AA1: CONF
B2: 1.1 A pessoa jurídica possui critérios de integridade formalizados para seleção dos candidatos aos cargos da alta direção? Se sim, anexar documentos que comprovem a existência dos critérios de integridade para seleção e informar os cargos a que são aplicados, a forma como os critérios são considerados e os responsáveis por sua avaliação. | C2: =B2=Tabela_3__Validação_da_Tabela_PerguntaFormularioTipoAvaliacao[[#This Row],[DescTituloPerguntaFormularioTipoAvaliacao]] | F2: 1.2 A pessoa jurídica aplicou critérios de integridade para seleção dos ocupantes de cargos da alta direção contratados nos últimos 24 meses? Se sim, anexar documentos que comprovem a aplicação dos critérios de integridade para seleção. | G2: 1.2 A pessoa jurídica aplicou critérios de integridade para seleção dos ocupantes de cargos da alta direção contratados nos últimos 24 meses? Se sim, anexar documentos que comprovem a aplicação dos critérios de integridade para seleção. | H2: =F2=G2 | J2: 2.3 A alta direção da pessoa jurídica supervisiona, diretamente ou por intermédio de órgão colegiado do qual ela participe, a implantação e a aplicação do programa de integridade, por meio do recebimento e avaliação de relatórios periódicos de acompanhamento das atividades relacionadas ao programa de integridade? | K2: 2.3 A alta direção da pessoa jurídica supervisiona, diretamente ou por intermédio de órgão colegiado do qual ela participe, a implantação e a aplicação do programa de integridade, por meio do recebimento e avaliação de relatórios periódicos de acompanhamento das atividades relacionadas ao programa de integridade? | L2: =J2=K2 | N2: 15 | O2: 15 | P2: =N2=O2 | S2: 2.1 A aprovação das principais políticas relacionadas ao programa de integridade é feita pelas mais elevadas instâncias decisórias da pessoa jurídica? Se sim, anexar documentos que comprovem a aprovação das principais políticas relacionadas ao programa de integridade pela alta direção. | T2: 2.1 A aprovação das principais políticas relacionadas ao programa de integridade é feita pelas mais elevadas instâncias decisórias da pessoa jurídica? Se sim, anexar documentos que comprovem a aprovação das principais políticas relacionadas ao programa de integridade pela alta direção. | U2: =S2=T2 | Y2: Evidências que comprovem que a pessoa jurídica possui critérios éticos, como políticas de seleção e procedimentos de contratação, para escolha de membros da alta direção. | Z2: Evidências que comprovem que a pessoa jurídica possui critérios éticos, como políticas de seleção e procedimentos de contratação, para escolha de membros da alta direção. | AA2: =Y2=Z2 | AE2: 3.2 As manifestações de apoio ao programa de integridade por membros da alta direção: | AF2: 3.2 As manifestações de apoio ao programa de integridade por membros da alta direção: | AG2: =AE2=AF2 | AJ2: DB1. Nome da pessoa jurídica - Razão Social: | AK2: DB1. Nome da pessoa jurídica - Razão Social: | AL2: =AJ2=AK2 | AO2: Informar a denominação pela qual a pessoa jurídica está registrada no Cadastro Nacional da Pessoa Jurídica. | AP2: Informar a denominação pela qual a pessoa jurídica está registrada no Cadastro Nacional da Pessoa Jurídica. | AQ2: =AO2=AP2 | AS2: 1. Adoção de critérios de integridade para seleção e remuneração de candidatos a cargos da alta direção | AT2: 1. Adoção de critérios de integridade para seleção e remuneração de candidatos a cargos da alta direção | AU2: =AS2=AT2
B3: 1.2 A pessoa jurídica aplicou critérios de integridade para seleção dos ocupantes de cargos da alta direção contratados nos últimos 24 meses? Se sim, anexar documentos que comprovem a aplicação dos critérios de integridade para seleção. | C3: =B3=Tabela_3__Validação_da_Tabela_PerguntaFormularioTipoAvaliacao[[#This Row],[DescTituloPerguntaFormularioTipoAvaliacao]] | F3: 1.3 A pessoa jurídica possui política de remuneração variável para os membros da alta direção condicionada ao atingimento de metas de desempenho relacionadas aos indicadores de aplicação ao programa de integridade? Se sim, anexar a política de remuneração que comprova a existência dessa regra e descrever como ela é aplicada. | G3: 1.3 A pessoa jurídica possui política de remuneração variável para os membros da alta direção condicionada ao atingimento de metas de desempenho relacionadas aos indicadores de aplicação ao programa de integridade? Se sim, anexar a política de remuneração que comprova a existência dessa regra e descrever como ela é aplicada. | H3: =F3=G3 | J3: 3.2.1 são feitas de forma periódica e divulgadas por diferentes meios para alcançar o público interno e externo da pessoa jurídica em toda sua diversidade? Se sim, demonstrar a medida em que as manifestações de apoio ao programa de integridade ocorreram de forma periódica e direcionadas aos diferentes públicos da entidade. | K3: 3.2.1 são feitas de forma periódica e divulgadas por diferentes meios para alcançar o público interno e externo da pessoa jurídica em toda sua diversidade? Se sim, demonstrar a medida em que as manifestações de apoio ao programa de integridade ocorreram de forma periódica e direcionadas aos diferentes públicos da entidade. | L3: =J3=K3 | N3: 18 | O3: 18 | P3: =N3=O3 | T3: 3.1 Os membros da alta direção, individualmente, manifestam publicamente apoio ao programa de integridade? Se sim, anexar documentos e/ou indicar, no campo correspondente, link em que seja possível visualizar as manifestações de apoio ao programa de integridade por membros da alta direção. | U3: =S3=T3 | V3: Corrigido | Y3: Evidências que comprovem a aplicação de critérios de integridade na escolha da alta direção, incluindo testes de integridade, background check, Know Your Employee - KYE, pesquisas em fontes abertas e análises de antecedentes sobre histórico profissional, práticas ilícitas e conduta ética. | Z3: Evidências que comprovem a aplicação de critérios de integridade na escolha da alta direção, incluindo testes de integridade, background check, Know Your Employee - KYE, pesquisas em fontes abertas e análises de antecedentes sobre histórico profissional, práticas ilícitas e conduta ética. | AA3: =Y3=Z3 | AE3: 6.2 A política ou planejamento que trata da gestão de riscos: | AF3: 6.2 A política ou planejamento que trata da gestão de riscos: | AG3: =AE3=AF3 | AJ3: DB2. E-mail institucional da área de integridade: | AK3: DB2. E-mail institucional da área de integridade: | AL3: =AJ3=AK3 | AO3: Informar o e-mail da área ou pessoa responsável pelo programa de integridade. Indicar e-mail institucional, evitando-se conta de uso pessoal. Este e-mail poderá ser utilizado pela CGU para dúvidas, informes, pedidos de esclarecimentos etc. | AP3: Informar o e-mail da área ou pessoa responsável pelo programa de integridade. Indicar e-mail institucional, evitando-se conta de uso pessoal. Este e-mail poderá ser utilizado pela CGU para dúvidas, informes, pedidos de esclarecimentos etc. | AQ3: =AO3=AP3 | AS3: 2. Envolvimento da alta direção na implementação e supervisão do programa de integridade | AT3: 2. Envolvimento da alta direção na implementação e supervisão do programa de integridade | AU3: =AS3=AT3
B4: 1.3 A pessoa jurídica possui política de remuneração variável para os membros da alta direção condicionada ao atingimento de metas de desempenho relacionadas aos indicadores de aplicação ao programa de integridade? Se sim, anexar a política de remuneração que comprova a existência dessa regra e descrever como ela é aplicada. | C4: =B4=Tabela_3__Validação_da_Tabela_PerguntaFormularioTipoAvaliacao[[#This Row],[DescTituloPerguntaFormularioTipoAvaliacao]] | F4: 2.2 A pessoa jurídica possui em sua estrutura de governança órgão colegiado (como comitê ou conselho de ética) para deliberar sobre temas de ética e integridade, que contam com a participação de membros da alta direção? Se sim, anexar documentos que comprovem a existência do órgão colegiado e a participação dos membros da alta direção em sua composição. | G4: 2.2 A pessoa jurídica possui em sua estrutura de governança órgão colegiado (como comitê ou conselho de ética) para deliberar sobre temas de ética e integridade, que contam com a participação de membros da alta direção? Se sim, anexar documentos que comprovem a existência do órgão colegiado e a participação dos membros da alta direção em sua composição. | H4: =F4=G4 | J4: 4.2 A instância interna responsável pelo programa de integridade está formalmente constituída, tendo suas atribuições expressamente previstas em documento aprovado pela alta direção da pessoa jurídica? Se sim, anexar documentos que comprovem a constituição formal da área responsável pelo programa de integridade, com suas atribuições e responsabilidades definidas. | K4: 4.2 A instância interna responsável pelo programa de integridade está formalmente constituída, tendo suas atribuições expressamente previstas em documento aprovado pela alta direção da pessoa jurídica? Se sim, anexar documentos que comprovem a constituição formal da área responsável pelo programa de integridade, com suas atribuições e responsabilidades definidas. | L4: =J4=K4 | N4: 15 | O4: 15 | P4: =N4=O4 | S4: 4.1 A pessoa jurídica possui área ou pessoa responsável pela aplicação do programa de integridade? Se sim, anexar documentos que comprovem a existência da área específica ou pessoa responsável, informando a data em que a área foi instituída ou em que a pessoa responsável foi contratada/designada para a função e o currículo do atual responsável pelo programa de integridade. | T4: 4.1 A pessoa jurídica possui área ou pessoa responsável pela aplicação do programa de integridade? Se sim, anexar documentos que comprovem a existência da área específica ou pessoa responsável, informando a data em que a área foi instituída ou em que a pessoa responsável foi contratada/designada para a função e o currículo do atual responsável pelo programa de integridade. | U4: =S4=T4 | Y4: Evidências da adoção de norma formal que vincula a remuneração variável da alta direção ao cumprimento de metas relacionadas aos indicadores do programa de integridade. | Z4: Evidências da adoção de norma formal que vincula a remuneração variável da alta direção ao cumprimento de metas relacionadas aos indicadores do programa de integridade. | AA4: =Y4=Z4 | AE4: 7.2 O código de ética e conduta ou documento equivalente: | AF4: 7.2 O código de ética e conduta ou documento equivalente: | AG4: =AE4=AF4 | AJ4: DB3. CNPJ: | AK4: DB3. CNPJ: | AL4: =AJ4=AK4 | AO4: Informar o CNPJ da pessoa jurídica. | AP4: Informar o CNPJ da pessoa jurídica. | AQ4: =AO4=AP4 | AS4: 3. Apoio visível e inequívoco da alta direção ao programa de integridade, incluindo a destinação de recursos adequados | AT4: 3. Apoio visível e inequívoco da alta direção ao programa de integridade, incluindo a destinação de recursos adequados | AU4: =AS4=AT4
B5: 2.1 A aprovação das principais políticas relacionadas ao programa de integridade é feita pelas mais elevadas instâncias decisórias da pessoa jurídica? Se sim, anexar documentos que comprovem a aprovação das principais políticas relacionadas ao programa de integridade pela alta direção. | C5: =B5=Tabela_3__Validação_da_Tabela_PerguntaFormularioTipoAvaliacao[[#This Row],[DescTituloPerguntaFormularioTipoAvaliacao]] | F5: 4.3 A instância interna responsável pelo programa possui estrutura independente, não estando subordinada a outro departamento da pessoa jurídica – jurídico, auditoria, RH etc.? Se sim, anexar organograma que demonstre a estrutura atual da instância interna e suas linhas de reporte ou política/procedimento que formalize tal estrutura e linhas de reporte. | G5: 4.3 A instância interna responsável pelo programa possui estrutura independente, não estando subordinada a outro departamento da pessoa jurídica – jurídico, auditoria, RH etc.? Se sim, anexar organograma que demonstre a estrutura atual da instância interna e suas linhas de reporte ou política/procedimento que formalize tal estrutura e linhas de reporte. | H5: =F5=G5 | J5: 5.1 O responsável pela instância interna de integridade possui garantias expressas que possibilitam o exercício das suas atribuições com independência e autoridade? Se sim, anexar documentos que comprovem a existência das garantias, a exemplo de mandato, nível de reporte, remuneração compatível com outras funções de mesmo nível hierárquico, livre acesso a documentos, pessoas e ativos da organização. | K5: 5.1 O responsável pela instância interna de integridade possui garantias expressas que possibilitam o exercício das suas atribuições com independência e autoridade? Se sim, anexar documentos que comprovem a existência das garantias, a exemplo de mandato, nível de reporte, remuneração compatível com outras funções de mesmo nível hierárquico, livre acesso a documentos, pessoas e ativos da organização. | L5: =J5=K5 | N5: 20 | O5: 20 | P5: =N5=O5 | S5: 6.3 A pessoa jurídica realizou, nos últimos 24 meses, uma análise de riscos que contempla expressamente riscos para integridade, isto é, aqueles relacionados a corrupção e fraude? Se sim, anexar a matriz de riscos ou documento equivalente, incluindo comprovação de que foi aprovado pela alta direção da entidade, no período indicado. | T5: 6.3 A pessoa jurídica realizou, nos últimos 24 meses, uma análise de riscos que contempla expressamente riscos para integridade, isto é, aqueles relacionados a corrupção e fraude? Se sim, anexar a matriz de riscos ou documento equivalente, incluindo comprovação de que foi aprovado pela alta direção da entidade, no período indicado. | U5: =S5=T5 | Y5: Evidências da participação da alta direção na aprovação de políticas do programa de integridade, como atas de reuniões, e-mails ou documentos que comprovem a criação ou atualização de políticas, estruturas e procedimentos, ou registros incluídos na própria política. | Z5: Evidências da participação da alta direção na aprovação de políticas do programa de integridade, como atas de reuniões, e-mails ou documentos que comprovem a criação ou atualização de políticas, estruturas e procedimentos, ou registros incluídos na própria política. | AA5: =Y5=Z5 | AE5: 8.1 A pessoa jurídica possui políticas e procedimentos de integridade que: | AF5: 8.1 A pessoa jurídica possui políticas e procedimentos de integridade que: | AG5: =AE5=AF5 | AJ5: DB4. Representante do programa de integridade: | AK5: DB4. Representante do programa de integridade: | AL5: =AJ5=AK5 | AO5: Informar o nome do representante da pessoa jurídica para ser comunicado em relação à avaliação do programa de integridade | AP5: Informar o nome do representante da pessoa jurídica para ser comunicado em relação à avaliação do programa de integridade | AQ5: =AO5=AP5 | AS5: 4. Existência e estrutura da instância interna responsável pela aplicação do programa de integridade | AT5: 4. Existência e estrutura da instância interna responsável pela aplicação do programa de integridade | AU5: =AS5=AT5
B6: 2.2 A pessoa jurídica possui em sua estrutura de governança órgão colegiado (como comitê ou conselho de ética) para deliberar sobre temas de ética e integridade, que contam com a participação de membros da alta direção? Se sim, anexar documentos que comprovem a existência do órgão colegiado e a participação dos membros da alta direção em sua composição. | C6: =B6=Tabela_3__Validação_da_Tabela_PerguntaFormularioTipoAvaliacao[[#This Row],[DescTituloPerguntaFormularioTipoAvaliacao]] | F6: 13.1 A pessoa jurídica possui função de auditoria interna formalmente estabelecida, seja de forma direta ou terceirizada? Se sim, anexar oi estatuto ou documento que demonstre o estabelecimento da função de auditoria interna. | G6: 13.1 A pessoa jurídica possui função de auditoria interna formalmente estabelecida, seja de forma direta ou terceirizada? Se sim, anexar oi estatuto ou documento que demonstre o estabelecimento da função de auditoria interna. | H6: =F6=G6 | J6: 6.1 Existe na pessoa jurídica política ou planejamento que trate da gestão de riscos e que defina a metodologia para a realização da análise de riscos? Se sim, anexar a política, metodologia ou outros documentos que formalizam a atividade de gestão de riscos. | K6: 6.1 Existe na pessoa jurídica política ou planejamento que trate da gestão de riscos e que defina a metodologia para a realização da análise de riscos? Se sim, anexar a política, metodologia ou outros documentos que formalizam a atividade de gestão de riscos. | L6: =J6=K6 | N6: 15 | O6: 15 | P6: =N6=O6 | S6: 7.1 A pessoa jurídica possui código de ética e conduta, ou documento equivalente, disponível em português? Se sim, anexar o código ou documento equivalente. | T6: 7.1 A pessoa jurídica possui código de ética e conduta, ou documento equivalente, disponível em português? Se sim, anexar o código ou documento equivalente. | U6: =S6=T6 | Y6: Evidências da existência de um órgão colegiado responsável por tratar de temas do programa de integridade, como estatutos, regimentos, políticas internas e atas, demonstrando a participação ativa dos membros da alta direção nesse colegiado. | Z6: Evidências da existência de um órgão colegiado responsável por tratar de temas do programa de integridade, como estatutos, regimentos, políticas internas e atas, demonstrando a participação ativa dos membros da alta direção nesse colegiado. | AA6: =Y6=Z6 | AE6: 9.2 As política ou procedimentos: | AF6: 9.2 As política ou procedimentos: | AG6: =AE6=AF6 | AJ6: DB5. Cargo do representante: | AK6: DB5. Cargo do representante: | AL6: =AJ6=AK6 | AO6: Informar o cargo do representante da pessoa jurídica. | AP6: Informar o cargo do representante da pessoa jurídica. | AQ6: =AO6=AP6 | AS6: 5. Garantias atribuídas ao responsável pela instância interna para o exercício de suas atividades com autoridade e independência | AT6: 5. Garantias atribuídas ao responsável pela instância interna para o exercício de suas atividades com autoridade e independência | AU6: =AS6=AT6
B7: 2.3 A alta direção da pessoa jurídica supervisiona, diretamente ou por intermédio de órgão colegiado do qual ela participe, a implantação e a aplicação do programa de integridade, por meio do recebimento e avaliação de relatórios periódicos de acompanhamento das atividades relacionadas ao programa de integridade? | C7: =B7=Tabela_3__Validação_da_Tabela_PerguntaFormularioTipoAvaliacao[[#This Row],[DescTituloPerguntaFormularioTipoAvaliacao]] | F7: 13.2 A função de auditoria interna reporta-se diretamente à alta direção ou instância de governança da pessoa jurídica? Se sim, anexar o estatuto ou outro documento que demonstre o nível de reporte da função de auditoria interna. | G7: 13.2 A função de auditoria interna reporta-se diretamente à alta direção ou instância de governança da pessoa jurídica? Se sim, anexar o estatuto ou outro documento que demonstre o nível de reporte da função de auditoria interna. | H7: =F7=G7 | J7: 6.3.3 A pessoa jurídica estabeleceu medidas voltadas para a mitigação dos riscos identificados, com a definição de prazos para implementação dessas medidas e dos responsáveis por sua implementação? Se sim, anexar documentos que demonstrem a definição das medidas de mitigação dos riscos identificados. | K7: 6.3.3 A pessoa jurídica estabeleceu medidas voltadas para a mitigação dos riscos identificados, com a definição de prazos para implementação dessas medidas e dos responsáveis por sua implementação? Se sim, anexar documentos que demonstrem a definição das medidas de mitigação dos riscos identificados. | L7: =J7=K7 | N7: 18 | O7: 18 | P7: =N7=O7 | S7: 8.1.1 vedam expressamente a concessão de vantagens indevidas, econômicas ou não, a agentes públicos? Se sim, anexar a política ou procedimento e indicar o(s) dispositivo(s) do documento que atenda(m) ao requisito. | T7: 8.1.1 vedam expressamente a concessão de vantagens indevidas, econômicas ou não, a agentes públicos? Se sim, anexar a política ou procedimento e indicar o(s) dispositivo(s) do documento que atenda(m) ao requisito. | U7: =S7=T7 | Y7: Evidências que comprovem a supervisão da alta direção na implantação e aplicação do programa de integridade, como atas de reuniões, e-mails, apresentações feitas em reuniões, registros de frequência das ações de supervisão, relatórios assinados e documentos que demonstrem o acompanhamento das atividades do programa. | Z7: Evidências que comprovem a supervisão da alta direção na implantação e aplicação do programa de integridade, como atas de reuniões, e-mails, apresentações feitas em reuniões, registros de frequência das ações de supervisão, relatórios assinados e documentos que demonstrem o acompanhamento das atividades do programa. | AA7: =Y7=Z7 | AE7: 14.1 A pessoa jurídica possui políticas e procedimentos baseadas em risco para a realização de diligências, contratação e supervisão de terceiros, que: | AF7: 14.1 A pessoa jurídica possui políticas e procedimentos baseadas em risco para a realização de diligências, contratação e supervisão de terceiros, que: | AG7: =AE7=AF7 | AJ7: DB6. Telefone do representante: | AK7: DB6. Telefone do representante: | AL7: =AJ7=AK7 | AO7: Informar o telefone do representante da pessoa jurídica. | AP7: Informar o telefone do representante da pessoa jurídica. | AQ7: =AO7=AP7 | AS7: 6. Gestão de riscos para integridade | AT7: 6. Gestão de riscos para integridade | AU7: =AS7=AT7
B8: 3.1 Os membros da alta direção, individualmente, manifestam publicamente apoio ao programa de integridade? Se sim, anexar documentos e/ou indicar, no campo correspondente, link em que seja possível visualizar as manifestações de apoio ao programa de integridade por membros da alta direção. | C8: =B8=Tabela_3__Validação_da_Tabela_PerguntaFormularioTipoAvaliacao[[#This Row],[DescTituloPerguntaFormularioTipoAvaliacao]] | F8: 13.3 A função de auditoria interna dispõe de estrutura, recursos e nível de acesso adequados ao cumprimento de suas atribuições? Se sim, anexar o estatuto e demais documentos que demonstrem a adequação da estrutura, recursos e nível de acesso da função de auditoria interna. | G8: 13.3 A função de auditoria interna dispõe de estrutura, recursos e nível de acesso adequados ao cumprimento de suas atribuições? Se sim, anexar o estatuto e demais documentos que demonstrem a adequação da estrutura, recursos e nível de acesso da função de auditoria interna. | H8: =F8=G8 | J8: 7.2.3 está alinhado com a legislação anticorrupção brasileira, contendo vedações expressas à prática de atos de corrupção e fraude e prevenção de conflito de interesses? Se sim, indicar o(s) dispositivo(s) do código que atenda(m) ao requisito. | K8: 7.2.3 está alinhado com a legislação anticorrupção brasileira, contendo vedações expressas à prática de atos de corrupção e fraude e prevenção de conflito de interesses? Se sim, indicar o(s) dispositivo(s) do código que atenda(m) ao requisito. | L8: =J8=K8 | N8: 20 | O8: 20 | P8: =N8=O8 | S8: 9.1. A pessoa jurídica possui políticas ou procedimentos específicos para prevenção de ilícitos em licitações e contratos administrativos? Se sim, anexar a política ou procedimentos que atenda(m) ao requisito. | T8: 9.1. A pessoa jurídica possui políticas ou procedimentos específicos para prevenção de ilícitos em licitações e contratos administrativos? Se sim, anexar a política ou procedimentos que atenda(m) ao requisito. | U8: =S8=T8 | Y8: Evidências de que a alta direção, de forma individualizada, reforça seu compromisso com a ética e a integridade, por meio de comunicados estratégicos em canais como e-mails, redes sociais, intranet, vídeos institucionais e comunicados internos e externos, demonstrando apoio ao programa de integridade. | Z8: Evidências de que a alta direção, de forma individualizada, reforça seu compromisso com a ética e a integridade, por meio de comunicados estratégicos em canais como e-mails, redes sociais, intranet, vídeos institucionais e comunicados internos e externos, demonstrando apoio ao programa de integridade. | AA8: =Y8=Z8 | AE8: 15.1 As políticas e procedimentos sobre contratação de terceiros estabeleçam a inclusão de cláusulas, nos contratos relevantes celebrados com terceiros, que: | AF8: 15.1 As políticas e procedimentos sobre contratação de terceiros estabeleçam a inclusão de cláusulas, nos contratos relevantes celebrados com terceiros, que: | AG8: =AE8=AF8 | AJ8: EA1. Qual a atividade econômica principal? | AK8: EA1. Qual a atividade econômica principal? | AL8: =AJ8=AK8 | AO8: Selecionar a opção que se refere a sua atividade econômica principal. A pessoa jurídica deverá observar os dois primeiros dígitos do CNAE e correlacioná-los com alguma das atividades descritas na lista. Exemplo: CNAE: 64.62-0-00 Atividade a ser selecionada na lista: (64 a 66) | AP8: Selecionar a opção que se refere a sua atividade econômica principal. A pessoa jurídica deverá observar os dois primeiros dígitos do CNAE e correlacioná-los com alguma das atividades descritas na lista. Exemplo: CNAE: 64.62-0-00 Atividade a ser selecionada na lista: (64 a 66) | AQ8: =AO8=AP8 | AS8: 7. Código de Ética e Conduta | AT8: 7. Código de Ética e Conduta | AU8: =AS8=AT8
B9: 3.2 As manifestações de apoio ao programa de integridade por membros da alta direção: | C9: =B9=Tabela_3__Validação_da_Tabela_PerguntaFormularioTipoAvaliacao[[#This Row],[DescTituloPerguntaFormularioTipoAvaliacao]] | F9: 13.4 São produzidos relatórios periódicos de auditoria interna? Se sim, anexar o último relatório anual de atividades da unidade de auditoria interna. | G9: 13.4 São produzidos relatórios periódicos de auditoria interna? Se sim, anexar o último relatório anual de atividades da unidade de auditoria interna. | H9: =F9=G9 | J9: 7.2.4 expressa o compromisso da pessoa jurídica em combater o preconceito, a discriminação e o assédio de qualquer natureza em suas relações internas e externas? Se sim, indicar o(s) dispositivo(s) do código que atenda(m) ao requisito. | K9: 7.2.4 expressa o compromisso da pessoa jurídica em combater o preconceito, a discriminação e o assédio de qualquer natureza em suas relações internas e externas? Se sim, indicar o(s) dispositivo(s) do código que atenda(m) ao requisito. | L9: =J9=K9 | N9: 0 | O9: 0 | P9: =N9=O9 | S9: 10.1 A pessoa jurídica possui um planejamento para a realização de treinamentos sobre integridade com definição do cronograma, temas, públicos-alvo, responsáveis e forma de execução? Se sim, anexar o documento ou informações que demonstrem o planejamento vigente. | T9: 10.1 A pessoa jurídica possui um planejamento para a realização de treinamentos sobre integridade com definição do cronograma, temas, públicos-alvo, responsáveis e forma de execução? Se sim, anexar o documento ou informações que demonstrem o planejamento vigente. | U9: =S9=T9 | AA9: =Y9=Z9 | AE9: 17.2 O canal de denúncias da pessoa jurídica: | AF9: 17.2 O canal de denúncias da pessoa jurídica: | AG9: =AE9=AF9 | AJ9: EA2. Qual o porte da pessoa jurídica? | AK9: EA2. Qual o porte da pessoa jurídica? | AL9: =AJ9=AK9 | AO9: Critério para a definição do porte conf. faturamento anual: - Microempresa: até R$ 360 mil - Empresa de Pequeno Porte: de R$ 360 mil até R$ 4,8 milhões - Média empresa: de R$ 4,8 milhões até R$ 300 milhões - Grande empresa: acima de R$ 300 milhões. | AP9: Critério para a definição do porte conf. faturamento anual: - Microempresa: até R$ 360 mil - Empresa de Pequeno Porte: de R$ 360 mil até R$ 4,8 milhões - Média empresa: de R$ 4,8 milhões até R$ 300 milhões - Grande empresa: acima de R$ 300 milhões. | AQ9: =AO9=AP9 | AS9: 8. Políticas e procedimentos de integridade | AT9: 8. Políticas e procedimentos de integridade | AU9: =AS9=AT9
B10: 3.2.1 são feitas de forma periódica e divulgadas por diferentes meios para alcançar o público interno e externo da pessoa jurídica em toda sua diversidade? Se sim, demonstrar a medida em que as manifestações de apoio ao programa de integridade ocorreram de forma periódica e direcionadas aos diferentes públicos da entidade. | C10: =B10=Tabela_3__Validação_da_Tabela_PerguntaFormularioTipoAvaliacao[[#This Row],[DescTituloPerguntaFormularioTipoAvaliacao]] | F10: 13.5 As recomendações ou apontamentos emitidos pela função de auditoria interna são adequada e tempestivamente implementadas pela pessoa jurídica? Se sim, anexar documentos que demonstrem a adequada e tempestiva implementação das recomendações emitidas pela função de auditoria interna. | G10: 13.5 As recomendações ou apontamentos emitidos pela função de auditoria interna são adequada e tempestivamente implementadas pela pessoa jurídica? Se sim, anexar documentos que demonstrem a adequada e tempestiva implementação das recomendações emitidas pela função de auditoria interna. | H10: =F10=G10 | J10: 7.2.6 menciona a possibilidade de aplicação de sanções para aqueles que cometerem violações éticas/legais, inclusive para os membros da alta direção da pessoa jurídica? Se sim, indicar o(s) dispositivo(s) do código que atenda(m) ao requisito. | K10: 7.2.6 menciona a possibilidade de aplicação de sanções para aqueles que cometerem violações éticas/legais, inclusive para os membros da alta direção da pessoa jurídica? Se sim, indicar o(s) dispositivo(s) do código que atenda(m) ao requisito. | L10: =J10=K10 | N10: 5 | O10: 5 | P10: =N10=O10 | S10: 11.1 A pessoa jurídica possui um planejamento para a realização de ações recorrentes de comunicação sobre integridade, com definição do cronograma, temas, responsáveis, públicos-alvo e meios de divulgação? Se sim, anexar o documento ou informações que demonstrem o planejamento vigente. | T10: 11.1 A pessoa jurídica possui um planejamento para a realização de ações recorrentes de comunicação sobre integridade, com definição do cronograma, temas, responsáveis, públicos-alvo e meios de divulgação? Se sim, anexar o documento ou informações que demonstrem o planejamento vigente. | U10: =S10=T10 | Y10: Evidências de que as declarações de apoio ao programa de integridade foram feitas por diferentes membros da alta direção e de forma periódica, reforçando o compromisso da liderança com a ética e a transparência. | Z10: Evidências de que as declarações de apoio ao programa de integridade foram feitas por diferentes membros da alta direção e de forma periódica, reforçando o compromisso da liderança com a ética e a transparência. | AA10: =Y10=Z10 | AE10: 18.2 As políticas e procedimentos definem: | AF10: 18.2 As políticas e procedimentos definem: | AG10: =AE10=AF10 | AJ10: EA3. Qual o faturamento anual? | AK10: EA3. Qual o faturamento anual? | AL10: =AJ10=AK10 | AO10: Selecionar a opção que se refere ao faturamento estimado, obtido pela pessoa jurídica a cada ano. | AP10: Selecionar a opção que se refere ao faturamento estimado, obtido pela pessoa jurídica a cada ano. | AQ10: =AO10=AP10 | AS10: 9. Políticas e procedimentos específicos para prevenção de ilícitos em licitações e contratos administrativos | AT10: 9. Políticas e procedimentos específicos para prevenção de ilícitos em licitações e contratos administrativos | AU10: =AS10=AT10
B11: 3.2.2 expressam uma mensagem de incentivo à adoção de uma conduta ética, seguindo os ditames do programa de integridade? Se sim, demonstrar a medida em que as manifestações de apoio ao programa de integridade expressaram o compromisso com os temas. | C11: =B11=Tabela_3__Validação_da_Tabela_PerguntaFormularioTipoAvaliacao[[#This Row],[DescTituloPerguntaFormularioTipoAvaliacao]] | F11: 14.1.3 determinam a verificação de possível envolvimento do terceiro em crimes ambientais ou em práticas nocivas ao meio ambiente? Se sim, anexar as políticas e/ou procedimentos, indicando o artigo, item e/ou página onde consta essa previsão. | G11: 14.1.3 determinam a verificação de possível envolvimento do terceiro em crimes ambientais ou em práticas nocivas ao meio ambiente? Se sim, anexar as políticas e/ou procedimentos, indicando o artigo, item e/ou página onde consta essa previsão. | H11: =F11=G11 | J11: 8.1.3 tratam da prevenção de conflito de interesses nas relações com a Administração Pública, incluindo contratações de agentes públicos e seus familiares? Se sim, anexar a política ou procedimento e indicar o(s) dispositivo(s) do documento que atenda(m) ao requisito. | K11: 8.1.3 tratam da prevenção de conflito de interesses nas relações com a Administração Pública, incluindo contratações de agentes públicos e seus familiares? Se sim, anexar a política ou procedimento e indicar o(s) dispositivo(s) do documento que atenda(m) ao requisito. | L11: =J11=K11 | N11: 5 | O11: 5 | P11: =N11=O11 | S11: 12.1 A pessoa jurídica possui procedimentos definidos para a realização dos lançamentos contábeis e financeiros? Se sim, anexar os documentos ou informações que estabeleçam os procedimentos existentes. | T11: 12.1 A pessoa jurídica possui procedimentos definidos para a realização dos lançamentos contábeis e financeiros? Se sim, anexar os documentos ou informações que estabeleçam os procedimentos existentes. | U11: =S11=T11 | Y11: Evidências de mensagens claras da alta direção aos colaboradores, sociedade, mercado e stakeholders, reforçando o compromisso da pessoa jurídica no combate ao preconceito, discriminação e assédio em qualquer forma. | Z11: Evidências de mensagens claras da alta direção aos colaboradores, sociedade, mercado e stakeholders, reforçando o compromisso da pessoa jurídica com a adoção de uma conduta ética, seguindo os ditames do programa de integridade. | AA11: =Y11=Z11 | AB11: Corrigir | AE11: 19.1 As políticas e procedimentos relacionadas ao tratamento, apuração e remediação de casos de fraudes, corrupção ou violação de direitos humanos e trabalhistas definem: | AF11: 19.1 As políticas e procedimentos relacionadas ao tratamento, apuração e remediação de casos de fraudes, corrupção ou violação de direitos humanos e trabalhistas definem: | AG11: =AE11=AF11 | AJ11: EA4. Descrever a estrutura organizacional da pessoa jurídica (Ex.: presidência, conselhos, comitês, diretorias etc.): | AK11: EA4. Descrever a estrutura organizacional da pessoa jurídica (Ex.: presidência, conselhos, comitês, diretorias etc.): | AL11: =AJ11=AK11 | AO11: Informar a estrutura organizacional, apresentando breve resumo das instâncias que a compõem, suas atribuições, membros e as relações de hierarquia/subordinação existentes. | AP11: Informar a estrutura organizacional, apresentando breve resumo das instâncias que a compõem, suas atribuições, membros e as relações de hierarquia/subordinação existentes. | AQ11: =AO11=AP11 | AS11: 10. Treinamentos sobre o Programa de Integridade | AT11: 10. Treinamentos sobre o Programa de Integridade | AU11: =AS11=AT11
B12: 3.2.3 expressam o compromisso da alta direção com o combate ao preconceito, à discriminação e ao assédio de qualquer natureza? Se sim, demonstrar a medida em que as manifestações de apoio ao programa de integridade expressaram o compromisso com os temas. | C12: =B12=Tabela_3__Validação_da_Tabela_PerguntaFormularioTipoAvaliacao[[#This Row],[DescTituloPerguntaFormularioTipoAvaliacao]] | F12: 16.1 A pessoa jurídica possui políticas e procedimentos específicos para a realização de fusões, aquisições ou outras operações societárias que preveem a realização de diligências para verificar o histórico de prática de atos de corrupção, fraude ou violação de direitos humanos ou trabalhistas das empresas envolvidas nas operações? Se sim, anexar as políticas e/ou procedimentos, indicando o artigo, item e/ou página onde consta essa previsão. | G12: 16.1 A pessoa jurídica possui políticas e procedimentos específicos para a realização de fusões, aquisições ou outras operações societárias que preveem a realização de diligências para verificar o histórico de prática de atos de corrupção, fraude ou violação de direitos humanos ou trabalhistas das empresas envolvidas nas operações? Se sim, anexar as políticas e/ou procedimentos, indicando o artigo, item e/ou página onde consta essa previsão. | H12: =F12=G12 | J12: 8.1.4 estabelecem orientações e controles sobre temas como realização de reuniões, encontros e outros tipos de interações entre administradores e empregados da pessoa jurídica com agentes públicos? Se sim, anexar a política ou procedimento e indicar o(s) dispositivo(s) do documento que atenda(m) ao requisito. | K12: 8.1.4 estabelecem orientações e controles sobre temas como realização de reuniões, encontros e outros tipos de interações entre administradores e empregados da pessoa jurídica com agentes públicos? Se sim, anexar a política ou procedimento e indicar o(s) dispositivo(s) do documento que atenda(m) ao requisito. | L12: =J12=K12 | N12: 5 | O12: 5 | P12: =N12=O12 | S12: 14.1.1 determinam a verificação de possível envolvimento do terceiro em casos de corrupção e práticas de fraude contra a Administração Pública? Se sim, anexar as políticas e/ou procedimentos, indicando o artigo, item e/ou página onde consta essa previsão. | T12: 14.1.1 determinam a verificação de possível envolvimento do terceiro em casos de corrupção e práticas de fraude contra a Administração Pública? Se sim, anexar as políticas e/ou procedimentos, indicando o artigo, item e/ou página onde consta essa previsão. | U12: =S12=T12 | Y12: Evidências de mensagens claras da alta direção aos colaboradores, sociedade, mercado e stakeholders, reforçando o compromisso da pessoa jurídica no combate ao preconceito, discriminação e assédio em qualquer forma. | Z12: Evidências de mensagens claras da alta direção aos colaboradores, sociedade, mercado e stakeholders, reforçando o compromisso da pessoa jurídica no combate ao preconceito, discriminação e assédio em qualquer forma. | AA12: =Y12=Z12 | AE12: 20.2 A política ou procedimentos que estabelecem o monitoramento contínuo do programa de integridade definem: | AF12: 20.2 A política ou procedimentos que estabelecem o monitoramento contínuo do programa de integridade definem: | AG12: =AE12=AF12 | AJ12: EA5. Integra algum grupo econômico? | AK12: EA5. Integra algum grupo econômico? | AL12: =AJ12=AK12 | AO12: Selecionar “Sim” ou “Não”, conforme o caso. | AP12: Selecionar “Sim” ou “Não”, conforme o caso. | AQ12: =AO12=AP12 | AS12: 11. Comunicações sobre o Programa de Integridade | AT12: 11. Comunicações sobre o Programa de Integridade | AU12: =AS12=AT12
B13: 3.3 A pessoa jurídica destina recursos em seu orçamento para a manutenção das atividades relacionadas ao programa de integridade? Se sim, anexar documentos que comprovem a destinação de recursos para o programa de integridade. | C13: =B13=Tabela_3__Validação_da_Tabela_PerguntaFormularioTipoAvaliacao[[#This Row],[DescTituloPerguntaFormularioTipoAvaliacao]] | F13: 16.2 A pessoa jurídica realizou diligências prévias a fusões, aquisições e outras operações societárias nos últimos 24 meses? Se sim, anexar documentos que comprovem a aplicação das políticas/procedimentos. | G13: 16.2 A pessoa jurídica realizou diligências prévias a fusões, aquisições e outras operações societárias nos últimos 24 meses? Se sim, anexar documentos que comprovem a aplicação das políticas/procedimentos. | H13: =F13=G13 | J13: 8.2 As políticas e procedimentos de integridade relacionados às interações com a Administração Pública foram aplicadas periodicamente pela pessoa jurídica nos últimos 12 meses? Se sim, descrever as ocasiões e a forma como as políticas e procedimentos foram aplicados, anexando a documentação comprobatória pertinente. | K13: 8.2 As políticas e procedimentos de integridade relacionados às interações com a Administração Pública foram aplicadas periodicamente pela pessoa jurídica nos últimos 12 meses? Se sim, descrever as ocasiões e a forma como as políticas e procedimentos foram aplicados, anexando a documentação comprobatória pertinente. | L13: =J13=K13 | N13: 18 | O13: 18 | P13: =N13=O13 | S13: 17.1 A pessoa jurídica possui canal para realização de denúncias, disponível em português e informado na página institucional da empresa na internet? Se sim, informar o link e descrever o caminho, desde a página inicial da empresa, e eventuais outras formas de acesso ao canal. | T13: 17.1 A pessoa jurídica possui canal para realização de denúncias, disponível em português e informado na página institucional da empresa na internet? Se sim, informar o link e descrever o caminho, desde a página inicial da empresa, e eventuais outras formas de acesso ao canal. | U13: =S13=T13 | Y13: Evidências que comprovem a elaboração de orçamento que destine recursos específicos para a área responsável pelo programa de integridade, antes de cada exercício, tais como: orçamento, atas de reunião com aprovação orçamentária etc., que contemplem as despesas programadas para a área. | Z13: Evidências que comprovem a elaboração de orçamento que destine recursos específicos para a área responsável pelo programa de integridade, antes de cada exercício, tais como: orçamento, atas de reunião com aprovação orçamentária etc., que contemplem as despesas programadas para a área. | AA13: =Y13=Z13 | AE13: 20.3 A pessoa jurídica realiza um monitoramento contínuo do programa de integridade por meio de: | AF13: 20.3 A pessoa jurídica realiza um monitoramento contínuo do programa de integridade por meio de: | AG13: =AE13=AF13 | AJ13: EA5.1. Informar o nome do grupo econômico: | AK13: EA5.1. Informar o nome do grupo econômico: | AL13: =AJ13=AK13 | AO13: Informar o nome do grupo econômico ao qual a pessoa jurídica pertence. | AP13: Informar o nome do grupo econômico ao qual a pessoa jurídica pertence. | AQ13: =AO13=AP13 | AS13: 12. Controles Contábeis e Financeiros | AT13: 12. Controles Contábeis e Financeiros | AU13: =AS13=AT13
